Workbook

Sheet 範型_苦情クレーム
A1: 第1カタログ 範型 ── 発語内行為「苦情・クレーム（Complaining）」
A2: 類型：指示的（directive）＋表出的要素 ／ 本質：相手（店・機関・個人）に、現状が期待に反することを伝え、是正を求める。非難と要求の二面を持ち、両者のバランスが行為の成否を決める。
A4: モード | B4: レベル | C4: No. | D4: CEFR記述文（原文） | E4: 記述文（作業訳） | F4: 実例（exponent） | G4: 場面 | H4: 効くhow well軸 | I4: 日本語話者へのL1語用論注意 | J4: 隣接レベルとの差分
A5: 口頭 | B5: A2 | C5: 544 | D5: Can point out when something is wrong (e.g. “The food is cold” or “There is no light in my room”). | E5: 何かがおかしいときに指摘できる（「料理が冷たい」「部屋の電気がつかない」など）。 | F5: • Excuse me, the food is cold. • Sorry, there is no light in my room. • Excuse me, this is not what I ordered. | G5: レストランやホテルで、出されたもの・状態が違うとき、その事実を一言告げる。 | H5: 社会言語的適切さ（最小）：Excuse me / Sorry を頭に置けるか。 | I5: 日本語話者は「事実の指摘」を非難と感じて言い出せない傾向。英語では The food is cold. と現状を述べること自体は失礼でなく、むしろ必要な情報提供。黙って我慢する方が不自然。ただし頭に Excuse me を欠くと唐突。 | J5: （起点）行為の最小形。まだ是正要求は含まず、問題の存在を告げるだけ。
A6: 口頭 | B6: B1 | C6: 533 | D6: Can make a complaint. | E6: 苦情を言える。 | F6: • Excuse me, I ordered the pasta but this is a pizza. Could you change it, please? • I'm sorry, but the room is really noisy. Would it be possible to move to another one? • There seems to be a problem with the bill — I think we've been charged twice. | G6: 注文違い・部屋の問題・請求の誤りなど、具体的な不都合について、是正を求めるところまで言う。 | H6: 社会言語的適切さ＋叙述の正確さ：問題の describe と要求の request を一続きにできるか。 | I6: 日本語の「すみません、これ頼んでないんですけど……」は語尾を濁して相手に察してもらう構造。英語では Could you change it? まで言い切らないと要求が伝わらず、問題提起だけで終わると「ただ不機嫌な人」になる。緩衝（I'm sorry but / There seems to be）＋明示的要求、の二点セットが鍵。 | J6: A2からの飛躍：問題の指摘に「是正の要求」が加わる。行為が完結する最初のレベル。
A7: 口頭 | B7: B1 | C7: 532 | D7: Can cope with less routine situations in shops, post offices, banks, e.g. returning an unsatisfactory purchase. | E7: 満足できない買い物の返品など、店・郵便局・銀行でのあまり日常的でない状況に対処できる。 | F7: • I bought this shirt yesterday, but there's a hole in the sleeve. I'd like to return it, please. • This isn't working properly — can I get a refund or an exchange? • I'd like to return this. Do you need the receipt? | G7: 店で不良品を返品する、想定外のやりとり（理由の説明・レシートの授受）に対応する。 | H7: 柔軟さ：相手の反応（レシートは？交換か返金か）に応じて言い足せるか。 | I7: 返品は日本でも増えたが、英語圏では「正当な権利の行使」であり、過度に低姿勢だと逆に不審。I'd like to return this と平叙で切り出してよい。「返品してもらえますか」を Can I possibly...? と過剰に婉曲化すると、かえって要領を得ない。 | J7: 同じB1でも、単発の苦情から「一連のやりとりへの対処」へ。相手の応答を捌く柔軟さが問われる。
A8: 口頭 | B8: B2+ | C8: 526 | D8: Can cope linguistically to negotiate a solution to a dispute like an undeserved traffic ticket, financial responsibility for damage in a flat, or blame regarding an accident. | E8: 不当な交通違反切符、住居の損傷の金銭的責任、事故の責めなど、争いの解決を交渉する言語的能力がある。 | F8: • I understand your position, but I don't think I'm liable for this. The damage was already there when I moved in. • I'd like to contest this. Could you tell me exactly which regulation I'm supposed to have broken? • I'm willing to cover part of it, but not the full amount — let me explain why. | G8: 責任の所在が争われる場面で、相手の主張を受けつつ自分の立場を通し、着地点を探る。 | H8: 叙述の正確さ＋柔軟さ＋社会言語的適切さ：反論しつつ関係を壊さない語調の制御。 | I8: 日本語話者は対立局面で沈黙するか、逆に感情的に強く出るかの両極に振れやすい。英語の交渉苦情は I understand X, but Y（相手の承認→自分の主張）という型が定石で、冷静に but でつなぐ。謝罪の I'm sorry を安易に挟むと責任を認めた含意になり不利。 | J8: 苦情から「交渉」へ。一方的要求ではなく、相手の立場の承認と自分の譲歩限度の提示が入る。
A9: 口頭 | B9: B2+ | C9: 527 | D9: Can outline a case for compensation, using persuasive language to demand satisfaction and state clearly the limits to any concession they are prepared to make. | E9: 説得力のある言葉で補償を求める主張を組み立て、満足を要求し、譲歩できる限度を明確に述べられる。 | F9: • Given the inconvenience caused, I believe a full refund plus compensation for the extra costs is reasonable. • I'm prepared to accept a replacement, but only if it's delivered by Friday — otherwise I'll expect a refund. • This has cost me two days of work. I'd like that reflected in whatever you're offering. | G9: 実害が生じた案件で、補償の根拠を筋道立てて示し、受け入れ条件と限度を明言する。 | H9: 叙述の正確さ（最大）＋話題の展開：根拠→要求→条件を論理的に積む構成力。 | I9: 「譲歩の限度を明示する」は日本語の交渉文化と最も遠い。日本語では限度をあえて曖昧にして含みで交渉するが、英語では but only if... / otherwise I'll... と条件と帰結を言語化するのが誠実で強い。曖昧なままだと足元を見られる。 | J9: 交渉に「論理的な根拠づけ」と「条件の明示的言語化」が加わる。口頭系列の到達点。
A10: 書面 | B10: B1+ | C10: 638 | D10: Can compose basic formal e-mails/letters (e.g. to make a complaint and request action). | E10: 基本的な公式のメールや手紙（苦情を述べ対応を求めるなど）を書ける。 | F10: • Dear Sir or Madam, I am writing to complain about the delayed delivery of my order (#12345). I would like to request a full refund. • I ordered the item on 3 May, but it has still not arrived. Please let me know how you intend to resolve this. | G10: 遅延・不良・誤請求について、公式メールで苦情と対応要求を伝える。 | H10: 社会言語的適切さ（書面レジスター）：I am writing to... の定型と Dear/Yours の枠を守れるか。 | I10: 日本語のビジネス苦情メールは長い前置き（お世話になっております＋クッション）から入るが、英語は I am writing to complain about... と冒頭で用件を明示するのが正しい作法。前置きを長くすると要領を得ない印象。 | J10: 口頭B1と並行して、書面系列が独立に立ち上がる。定型（I am writing to）とレジスターの獲得が核。
A11: 書面 | B11: B2+ | C11: 629 | D11: Can compose a forceful but polite letter of complaint, including supporting details and a statement of the desired outcome. | E11: 裏づけの詳細と望む結果を明記した、力強くも丁寧な苦情の手紙を書ける。 | F11: • Despite my email of 3 May, the issue remains unresolved. I have now been waiting three weeks for a replacement. • I trust you will appreciate my frustration and arrange a full refund within seven days. | G11: 一度目の苦情が解決されない案件で、経緯を裏づけつつ、丁寧さを保って強く要求する。 | H11: 話題の展開＋社会言語的適切さ：forceful と polite を両立させる語調設計。 | I11: 「力強くも丁寧に」の両立が難所。日本語話者は polite に振れすぎて要求が弱まるか、直訳的に強く書いて無礼になるか。英語は I trust you will... / I would appreciate it if... で、丁寧な形式のまま圧をかける定型がある。この「丁寧な強さ」の語彙庫を持つことが鍵。 | J11: 書面B1+からの飛躍：単発の苦情から、経緯の裏づけ・望む結果の明記・語調の制御へ。
A12: 書面 | B12: B2+ | C12: 628 | D12: Can compose formal correspondence such as letters of enquiry, request, application and complaint using appropriate register, structure and conventions. | E12: 適切な言語使用域・構成・慣習を使って、問い合わせ・依頼・応募・苦情などの公式の通信文を書ける。 | F12: • I am writing with reference to invoice #789, which appears to contain an error. • I would be grateful if you could look into this matter and respond at your earliest convenience. | G12: 苦情を含む各種公式通信を、型・レジスター・慣習に則って書き分ける。 | H12: 社会言語的適切さ（慣習の体系）：with reference to / at your earliest convenience 等の定型群の運用。 | I12: 英語の公式通信は定型表現の体系（with reference to, I would be grateful if, at your earliest convenience）で動く。日本語の敬語体系とは別物なので、日本語敬語を英語に写そうとせず、英語独自の formal 定型を丸ごと語彙として習得する必要がある。 | J12: 個別の苦情から「公式通信文一般の型」への一般化。苦情が他の書面行為（依頼・応募）と型を共有すると気づく段。
A13: 書面 | B13: C1 | C13: 625 | D13: Can, with good expression and accuracy, compose formal correspondence such as letters of clarification, application, recommendation, reference, complaint, sympathy and condolence. | E13: 明確化・応募・推薦・照会・苦情・見舞い・弔慰の手紙など、公式の通信文を、うまい表現と正確さで書ける。 | F13: • While I appreciate that delays can occur, a three-week silence following my formal complaint is difficult to justify. • I would ask that you treat this as a matter of urgency and confirm your proposed resolution in writing. | G13: 洗練を要する公式通信で、含意・語調・正確さを制御して苦情を述べる。 | H13: 叙述の正確さ＋柔軟さ（最大）：含意・皮肉・緩衝を精密に制御する表現力。 | I13: C1では While I appreciate that..., ... is difficult to justify のような、譲歩節で相手を立てつつ論理で追い込む高度な緩衝が要る。日本語の高等な苦情（慇懃な圧）に感覚は近いが、英語独自のレトリックなので、日本語の語感からの類推は危険。個別の表現を範例で覚える段階。 | J13: B2+からの到達点：正確さに加え「うまい表現（good expression）」＝含意と語調の精密制御。書面系列の頂点。
A15: DISCUSSION ── この行為をパターンとして読む（アレグザンダー式・行為全体への散文）
A16: 【緩衝（mitigation）が行為の背骨である】 英語の苦情を貫く原理は「非難性の緩衝」である。同じ事実（料理が冷たい）を、A2では Excuse me を頭に置くだけ、B1では There seems to be... で事実を非人称化し、B2+では I understand your position, but... で相手を立て、C1では While I appreciate that... と譲歩節で包む——レベルが上がるとは、緩衝の技法が精緻化することにほかならない。この行為において how well の主軸は一貫して社会言語的適切さであり、文法的正確さではない。文法的に完璧な The food is cold and I want a new one now. は、B1の緩衝された表現より「下手」なのである。 【日本語話者にとっての二重の壁】 第一の壁は「言い出せない」こと。日本語文化では苦情＝関係を損なう行為とされ、我慢が美徳になりやすい。だが英語圏では、正当な苦情は消費者の権利であり情報提供でもあって、黙る方が不自然に映る。第二の壁は、言い出せた場合に「振れすぎる」こと——過度に低姿勢で要求が伝わらないか、直訳的に強く出て無礼になるかの両極。英語の苦情は「丁寧な形式を保ったまま要求を明示する」ことを求めるが、これは日本語の「察してもらう」構造とも「けんか腰」とも異なる第三の様式であり、明示的に学ぶしかない。 【苦情は依頼と背中合わせである】 「部屋が寒い」（苦情）は「暖房を入れてほしい」（依頼）と表裏一体で、多くの苦情は是正の依頼を含意する。25行為インベントリで苦情と依頼を別立てにしたが、実運用では連続する。苦情を教えるとき、是正要求（依頼）まで一続きで示さないと、行為が完結しない——日本語話者が問題提起だけで止まりがちなのは、この連続性が母語で言語化されないためでもある。 【口頭と書面は別の行為に近い】 CEFRが苦情を口頭スケール（Obtaining goods and services）と書面スケール（Correspondence）に分けて記述しているのは示唆的である。口頭の苦情は即時・対面で、緩衝も即興的（Excuse me, sorry）。書面の苦情は経緯の裏づけ・構成・レジスターが前面に出て、定型表現の体系（I am writing to, I would be grateful if）で動く。学習者にとっては習得順序も異なり、口頭A2から始まる系列と、書面B1+から始まる系列は、並行して別々に登らせるのが自然である。 【なぜこの行為が範型に適するか】 苦情は、発語内行為25種の中でも、L1語用論的転移が最も激しく、かつレベル差分が最も明瞭に観察できる。緩衝技法の精緻化としてA2→C1が一直線に読め、how wellの主軸（社会言語的適切さ）が行為全体を貫く。他の24行為を作り込む際、この「緩衝の精緻化」「言い出せない／振れすぎるの二重の壁」「隣接行為との連続」「口頭・書面の分岐」という4つの観察軸が、そのまま点検リストになる。

Sheet 範型_挨拶別れ安否
A1: 第1カタログ 範型 ── 発語内行為「挨拶・別れ・安否（Greeting, Leave-taking & Phatic exchange）」
A2: 類型：交話的（phatic）── 情報伝達より関係の確立・維持が目的 ／ 本質：出会いと別れの区切りに定型表現を交わし、相手との社会的接触を開き・保ち・閉じる。内容の正しさより、型の適切さとテンポが行為の成否を決める。
A4: モード | B4: レベル | C4: No. | D4: CEFR記述文（原文） | E4: 記述文（作業訳） | F4: 実例（exponent） | G4: 場面 | H4: 効くhow well軸 | I4: 日本語話者へのL1語用論注意 | J4: 隣接レベルとの差分
A5: 口頭 | B5: Pre-A1 | C5: 453 | D5: Can understand and use basic, formulaic expressions such as “Yes”, “No”, “Excuse me”, “Please”, “Thank you”, “No thank you”, “Sorry”. | E5: 「はい」「いいえ」「すみません」「お願いします」「ありがとう」「けっこうです」「ごめんなさい」などの基本的な決まり文句を理解し、使える。 | F5: • Yes. / No. • Thank you. / No thank you. • Excuse me. / Sorry. • Please. | G5: あらゆる接触の潤滑油となる最小の定型語を、適切な場面で口にする。 | H5: 社会言語的適切さ（最小単位）：型を型として口に出せるか。 | I5: No thank you を「いいえ、結構です」の丁寧な断りとして使えず、単に No と言って冷たく響くことがある。また Sorry と Excuse me の使い分け（謝罪／呼びかけ・断り）が日本語の「すみません」に一括されるため混同しやすい。 | J5: （起点）語彙ですらなく「機能語の塊」。関係の潤滑油の最小部品。
A6: 口頭 | B6: Pre-A1 | C6: 455 | D6: Can greet people, state their name and take leave in a simple way. | E6: 挨拶し、名前を名乗り、簡単な方法で別れを告げられる。 | F6: • Hello. / Hi. • I'm Kenji. • Goodbye. / Bye. • See you. | G6: 初対面や店・受付で、挨拶し名乗り、辞去する。会話の開閉の枠。 | H6: 社会言語的適切さ：出会いと別れの型をペアで押さえられるか。 | I6: 別れ際の See you. や Bye. を言わずに立ち去る、あるいは Goodbye だけで済ませて素っ気なくなる。日本語の「じゃあ」「どうも」に当たる軽い辞去表現の層が薄い。 | J6: 定型語から「会話の開閉」へ。挨拶と別れは対で機能する。
A7: 口頭 | B7: A1 | C7: 451 | D7: Can make an introduction and use basic greeting and leave-taking expressions. | E7: 紹介をし、基本的な挨拶や別れの表現を使える。 | F7: • Good morning. / Good afternoon. • This is my friend, Aya. • Nice to meet you. • Have a nice day! | G7: 他者を紹介し、時間帯に応じた挨拶と、別れ際の一言を添える。 | H7: 社会言語的適切さ：時間帯・相手による型の選択。 | I7: Nice to meet you.（初対面）と Nice to see you.（再会）の別を知らず、再会でも meet を使ってしまう。Have a nice day! のような別れ際の「気遣いの一言」を添える習慣が乏しく、挨拶が短く切れる。 | J7: Pre-A1からの差分：時間帯別（morning/afternoon）と紹介（This is...）が加わり、型が場面分化する。
A8: 口頭 | B8: A1 | C8: 452 | D8: Can ask how people are and react to news. | E8: 人の調子を尋ね、知らせに反応できる。 | F8: • How are you? — Fine, thanks. And you? • How's it going? • That's great! / Oh, I'm sorry to hear that. | G8: 相手の近況・体調を尋ね、返ってきた知らせに感情で応じる。 | H8: 社会言語的適切さ＋テンポ：定型的な問い返し（And you?）の即応。 | I8: How are you? を「本当に体調を訊く質問」と受け取り、長々と実際の状態を答えてしまう。英語では儀礼的な往復（Fine, thanks. And you?）が基本で、中身より往復のテンポが大事。この phatic な性質が日本語話者に最も伝わりにくい。 | J8: 一方向の挨拶から「往復」へ。相手の応答に反応する対話性が入る。
A9: 口頭 | B9: A2 | C9: 444 | D9: Can use simple, everyday, polite forms of greeting and address. | E9: 簡単な日常の丁寧な挨拶や呼びかけの表現形式を使える。 | F9: • Good evening, Mr. Tanaka. • Excuse me, sir. / Excuse me, madam. • How do you do?（改まった初対面） | G9: 目上や公的な相手に、丁寧なレジスターで挨拶し呼びかける。 | H9: 社会言語的適切さ（レジスター）：親しさ／改まりで型を選び分けられるか。 | I9: 英語の呼びかけには sir/madam や Mr./Ms.＋姓があるが、日本語の「〜さん」を万能に使う感覚で first name を使い、目上に馴れ馴れしく響く。逆に過度に Mr. を連発して不自然になることも。相手との距離に応じた呼称選択は明示的な学習を要する。 | J9: A1からの差分：中立な挨拶から「丁寧なレジスター」の選択へ。呼びかけ（address）が加わる。
A10: 口頭 | B10: A2+ | C10: 438 | D10: Can establish social contact (e.g. greetings and farewells, introductions, giving thanks). | E10: 社交的接触（挨拶と別れ、紹介、感謝など）を確立できる。 | F10: • Hi, I don't think we've met — I'm Kenji. • It was really nice talking to you. • Thanks so much for having me. / Let's keep in touch. | G10: パーティや職場で、自ら関係を開き、会話を交わし、良い印象で閉じる一連。 | H10: 社会言語的適切さ＋柔軟さ：開始・維持・終了を状況に合わせて束ねる。 | I10: 関係を自分から「開く」定型（I don't think we've met）や、良い印象で「閉じる」定型（It was nice talking to you / keep in touch）の層が薄く、挨拶が入口だけで終わりがち。日本語では別れの挨拶が定型的に厚いのに、英語ではその機能表現を別途習得しないと使えない。 | J10: 個別の挨拶から「社交的接触の確立」へ。開始〜維持〜終了を一続きの営みとして統合する到達点。
A11: 書面 | B11: Pre-A1 | C11: 686 | D11: Can post simple online greetings, using basic formulaic expressions and emoticons. | E11: 基本的な決まり文句と絵文字を使って、簡単なオンラインの挨拶を投稿できる。 | F11: • Happy birthday! 🎉 • Good luck! 😊 • Congrats! | G11: SNSやチャットで、定型句＋絵文字の短い挨拶を投稿する。 | H11: 社会言語的適切さ（オンライン・レジスター）：くだけた場の型と絵文字の運用。 | I11: 日本語のオンライン儀礼（「おめでとう🎊」）の感覚は近いが、英語の Congrats! / Happy belated birthday!（遅れた誕生日祝い）のような口語省略形を知らず、硬い Congratulations に留まる。絵文字の使用も控えめすぎることがある。 | J11: （書面起点）口頭の定型語が、オンラインでは絵文字と結んで機能する。
A12: 書面 | B12: A1 | C12: 648 | D12: Can compose a short, simple postcard. | E12: 短く簡単なはがきを書ける。 | F12: • Dear Aya, Greetings from Kyoto! The temples are beautiful. See you soon, Kenji • Hi Mom, Having a great time here. Weather is lovely. Love, Kenji | G12: 旅先などから、近況の一言を添えた短いはがきを書く。 | H12: 社会言語的適切さ（書面枠）：Dear... と結び（Love/See you soon）の枠を守れるか。 | I12: はがき・手紙の結びの語（Love, / Best, / See you soon,）の層が薄く、日本語の「それでは」を直訳して不自然になる。宛名の Dear は日本語の「親愛なる」より軽く日常的、という温度感も掴みにくい。 | J12: オンライン挨拶からの差分：書面の「枠」（宛名・本文・結び）が加わる。
A13: 書面 | B13: A2 | C13: 682 | D13: Can engage in basic social communication online (e.g. a simple message on a virtual card for special occasions, sharing news and making/confirming arrangements to meet). | E13: オンラインで基本的な社交（特別な機会のカードへの一言、近況共有、会う約束の設定・確認など）ができる。 | F13: • Congratulations on your new job! So happy for you. • Long time no see! How have you been? • Shall we meet around 7? — Sounds good, see you then! | G13: オンラインで、祝い・近況・約束の確認まで含む社交的なやりとりをする。 | H13: 社会言語的適切さ＋テンポ：非同期のやりとりで型と応答を回す。 | I13: Long time no see! のような口語定型や、約束確認の Sounds good, see you then! のテンポある応答が出てこず、事務的な確認に終始しがち。日本語のオンライン社交の「クッション」を英語の口語定型に置き換える必要がある。 | J13: はがきの一方向から、オンラインの「往復する社交」へ。約束の設定・確認まで機能が広がる書面系列の到達点。
A15: DISCUSSION ── この行為をパターンとして読む（アレグザンダー式・行為全体への散文）
A16: 【この行為に「上級」は無い ── 儀礼型の本質】 苦情がA2からC1まで長い梯子を持つのに対し、挨拶・別れ・安否はPre-A1からA2+に完全に収まり、B1以上に記述文が一つも無い。これは欠落ではなく、交話的（phatic）行為の本質である。挨拶に高度な熟達は存在しない ── C2話者も "Hi, how are you?" と言う。CEFRがこの行為を初級だけで記述し尽くしているのは、関係の潤滑という機能が、初級の定型表現でほぼ充足されるからである。したがってこの行為のカタログは「レベルを上る」構造ではなく、「初級の型を、いかに場に合わせて選ぶか」という水平の広がりを持つ。 【難しさは「レベル」ではなく「レジスターとテンポ」にある】 では日本語話者にとって易しいかというと逆で、難所がレベル軸と直交する二つの次元に潜む。第一はレジスター（親しさ・改まりの選択）。sir/madam、Mr.＋姓、first name、ニックネームの使い分けは、日本語の「〜さん」一括感覚では捌けず、相手との距離を英語の呼称体系で測り直す必要がある。第二はテンポ。How are you? — Fine, thanks. And you? の往復は、中身ではなく「間髪入れず型を返す」ことに意味がある。この二つは文法でも語彙でもなく、how well の軸でいえば社会言語的適切さに全面的に属する。 【How are you? は質問ではない ── phatic の核心的誤解】 日本語話者が最もつまずくのは、儀礼的な問いを情報要求と受け取ることである。How are you? に実際の体調を長々答える、How's it going? に詰まる ── これは英語力ではなく、phatic communion（意味の交換ではなく接触の確認そのものが目的の発話）という概念が母語で意識されないために起こる。この行為を教えるとき、「中身より往復」「型は型として回す」という phatic の性質そのものを明示的に伝えることが、どの実例よりも効く。 【開始は言えるが、維持と終了が言えない】 日本語話者の挨拶は入口（Hello, Nice to meet you）に偏り、関係を「閉じる」定型（It was nice talking to you / Let's keep in touch / Have a nice day）の層が決定的に薄い。日本語では別れの挨拶がむしろ厚い（「それでは失礼します」「お世話になりました」）のに英語で出てこないのは、機能が同じでも表現が一対一で写らず、英語側の閉じる定型を別個の語彙として持っていないためである。カタログでは開始・維持・終了を必ず三点セットで示し、とりわけ終了の定型を厚くする。 【範型としての検証 ── 苦情型との対比で見えたこと】 苦情（指示型）では「緩衝の精緻化」がレベル軸を貫いたが、挨拶（儀礼型）ではレベル軸がほぼ消え、代わりに「レジスター選択」「テンポ」「phaticの理解」という水平の難しさが前面に出た。これは範型が行為の類型ごとに異なる顔を持つことを示す。指示型の点検軸（緩衝・二重の壁・隣接行為・口頭書面）はそのままでは効かず、儀礼型には「レベルの梯子が短い／無い」「難所がレジスターとテンポに移る」「phatic性の明示的説明が要る」という別の点検軸が要る。25行為を作り込む際は、まず各行為が指示型・儀礼型・主張型・表出型のどれに属するかを見極め、類型ごとの点検軸を当てるのが正しい ── 単一のテンプレートを全行為に機械適用してはならない。

Sheet 範型_事実質問応答
A1: 第1カタログ 範型 ── 発語内行為「事実情報の質問と応答（Asking & answering factual questions）」
A2: 類型：主張的（assertive）── 世界の事実を尋ね、真偽の判断を伴って答える ／ 本質：名前・時刻・場所・予定などの事実情報を、質問と応答のペアで往復させる。行為の核は情報の正確な授受であり、緩衝もレジスターも二次的。疑問文の構造そのものが遂行の要となる。
A4: モード | B4: レベル | C4: No. | D4: CEFR記述文（原文） | E4: 記述文（作業訳） | F4: 実例（exponent） | G4: 場面 | H4: 効くhow well軸 | I4: 日本語話者へのL1語用論注意 | J4: 隣接レベルとの差分
A5: 口頭 | B5: Pre-A1 | C5: 579 | D5: Can tell people their name and ask other people their names. | E5: 自分の名前を名乗り、他の人に名前を尋ねられる。 | F5: • What's your name? — My name is Kenji. / I'm Kenji. • And you? What's your name? | G5: 初対面で名前を尋ね合う、最も基本的な情報交換。 | H5: 文法的正確さ（疑問文の骨格）：What's your name? の語順を作れるか。 | I5: 日本語は「お名前は？」と述語を略しても成立するが、英語は What is your name? と疑問詞＋be動詞＋主語の語順が必須。主語を落として Name? だけだと幼稚か無礼に響く。疑問文の骨格そのものが最初の壁。 | J5: （起点）疑問文の最小形。事実の授受の最小単位。
A6: 口頭 | B6: Pre-A1 | C6: 585 | D6: Can ask very simple questions for information, such as “What is this?” and understand one- or two-word/sign answers. | E6: 「これは何?」等の簡単な情報の質問をし、1〜2語の答えを理解できる。 | F6: • What is this? — It's a key. • What's that in English? | G6: 物を指して名称を尋ね、短い答えを受け取る。 | H6: 文法的正確さ＋受容：What疑問文と一語応答の理解。 | I6: 答えの It's a key. の It's を省いて A key と答えるのは英語でも自然だが、日本語話者は逆に「これはキーです」に引きずられ This is key.（冠詞落ち）としがち。冠詞は日本語に無い範疇なので、事実応答のたびに落ちる。 | J6: 名前から一般の事物へ。What+be動詞の疑問を汎用化。
A7: 口頭 | B7: Pre-A1 | C7: 581 | D7: Can ask and tell what day, time of day and date it is. | E7: 何曜日か、一日のうちのいつか、何日かを尋ね、言える。 | F7: • What day is it today? — It's Monday. • What time is it? — It's half past three. • What's the date today? — It's the 5th of July. | G7: 曜日・時刻・日付という定型的事実を尋ね合う。 | H7: 文法的正確さ（非人称の it）：時刻・日付の it is 構文。 | I7: 時刻・曜日の主語 it（It's Monday）は日本語に対応物が無く、主語を落として Monday. とだけ答えがち。また half past three（3時半）like の英語独特の時刻表現は、日本語の「3時半」から直訳できず、型として覚える必要がある。 | J7: 事物から「定型的事実（時・日付）」へ。非人称itの構文が加わる。
A8: 口頭 | B8: A1 | C8: 575 | D8: Can ask and answer questions about themselves and other people, where they live, people they know, things they have. | E8: 自分や他の人、住んでいる場所、知っている人、持っているものについて質問し、答えられる。 | F8: • Where do you live? — I live in Osaka. • Do you have any brothers or sisters? — Yes, I have one sister. • Who's that? — That's my friend Aya. | G8: 居住地・家族・所有物など、身辺の事実を双方向に尋ね合う。 | H8: 文法的正確さ（一般動詞の疑問）：do/does を使った疑問文の構築。 | I8: Where do you live? の do は日本語に対応が無く、Where you live? と do を落とす誤りが頻発。日本語の疑問は語尾（〜か）だけで作れるため、英語の「助動詞doを前に立てる」操作が身につきにくい。主張型の中核的な文法的つまずき。 | J8: Pre-A1からの飛躍：be動詞疑問から一般動詞疑問（do支持）へ。扱う事実も身辺全般に拡大。
A9: 口頭 | B9: A2 | C9: 572 | D9: Can ask and answer simple questions about an event (e.g. ask where and when it took place, who was there and what it was like). | E9: 出来事について簡単な質問をし答えられる（どこで・いつ・誰が・どうだったか）。 | F9: • Where was the party? — It was at Kenji's place. • How was it? — It was really fun. • Who was there? — Aya and some people from work. | G9: 済んだ出来事について、場所・時・参加者・様子を尋ね合う。 | H9: 文法的正確さ（過去時制）：was/were と過去疑問の運用。 | I9: 過去の出来事なので was/were や did が要るが、日本語話者は時制標示を落として Where the party? / How it was?（語順崩れ）としやすい。日本語の過去「〜だった」は英語の時制ほど厳密な一致を求めないため、疑問文中の時制保持が弱い。 | J9: 現在の事実から「過去の出来事」へ。過去時制の疑問・応答が加わる。
A10: 口頭 | B10: A2 | C10: 570 | D10: Can ask for and give directions referring to a map or plan. | E10: 地図や見取り図を参照しながら道順を尋ね、教えられる。 | F10: • How do I get to the station? — Go straight and turn left at the bank. • Is it far? — No, about five minutes on foot. • Where are we now? — We're here, near the museum. | G10: 地図を見ながら、目的地への行き方を尋ね教え合う。 | H10: 叙述の正確さ＋文法（命令文の道案内）：方向表現の連鎖。 | I10: 道案内の応答は命令文（Go straight, Turn left）を使うが、日本語話者は命令形が強く聞こえると感じて避け、遠回しにしがち。英語では道案内の命令文は失礼でなく標準。また前置詞（at the bank, on your right）の選択が日本語の助詞感覚とずれる。 | J10: 口頭事実交換の応用：静的事実から「空間的手順の授受」へ。命令文応答が加わる。
A11: 口頭 | B11: A2+ | C11: 563 | D11: Can ask and answer questions about habits and routines. | E11: 習慣や日課について質問し、答えられる。 | F11: • What time do you usually get up? — Around seven. • How often do you exercise? — Twice a week. • Do you always take the train? — Usually, yes. | G11: 日常の習慣・頻度について尋ね合う。 | H11: 文法的正確さ（頻度・習慣の現在形）：頻度副詞と現在形の運用。 | I11: 頻度副詞（usually, often, twice a week）の位置が日本語と異なり、I usually get up... の語中位置を外して文末や文頭に置きがち。また習慣を表す現在形と進行形の別（I take the train / I'm taking）が、日本語の「〜している」一括感覚で混同される。 | J11: 単発の出来事から「反復する習慣」へ。頻度表現と習慣の現在形が加わる。
A12: 口頭 | B12: A2+ | C12: 565 | D12: Can ask and answer questions about plans and intentions. | E12: 計画や意図について質問し、答えられる。 | F12: • What are you doing this weekend? — I'm meeting some friends. • Are you going to travel this summer? — Yes, I'm planning to. • What time will you arrive? — Probably around six. | G12: 予定・意図について尋ね合う。 | H12: 文法的正確さ（未来表現の選択）：will / be going to / 現在進行形の使い分け。 | I12: 英語の未来表現は三系統（will＝その場の決定・予測、be going to＝既定の意図、現在進行形＝手配済みの予定）あるが、日本語の「〜する／〜するつもり」の二分では捌けず、どれを使うか判断できない。この使い分けは主張型・未来事実の最大の難所。 | J12: 過去・現在の事実から「未来の予定・意図」へ。未来表現の体系が加わる。主張型口頭系列の到達点。
A13: 書面 | B13: A1 | C13: 643 | D13: Can convey personal information of a routine nature, for example in a short e-mail or letter introducing themselves. | E13: 日常的な個人情報を伝えられる（自己紹介する短いメールなど）。 | F13: • Hi, I'm Kenji. I'm from Osaka and I work at a software company. • I have two cats and I like hiking. What about you? | G13: 自己紹介のメールで、身辺の事実情報を文章で伝える。 | H13: 文法的正確さ（平叙文の事実記述）：I am / I have / I work の平叙連鎖。 | I13: 口頭では往復で成立するが、書面では自己完結した平叙文を連ねる必要がある。日本語話者は主語 I の反復を冗長に感じて落としがちだが、英語では各文に主語が要る。話し言葉の省略を書면に持ち込むと非文になる。 | J13: （書面起点）口頭の質問応答が、書面では一方向の事実記述として立ち上がる。
A14: 書面 | B14: A2 | C14: 642 | D14: Can exchange information by text message, by e-mail or in short letters, responding to questions from the other person (e.g. about a new product or activity). | E14: テキスト・メール・短い手紙で情報を交換できる（相手の質問に答えながら）。 | F14: • Q: When does the event start? — A: It starts at 2 pm on Saturday. • Q: Where is it? — A: At the community hall, near the station. | G14: メールやテキストで、相手の質問に答えつつ事実情報をやりとりする。 | H14: 文法的正確さ＋叙述の正確さ：問いに対応した事実の返信。 | I14: 書面の非同期往復では、相手の質問の時制・焦点に合わせて答える必要があるが、日本語話者は質問を受け止めず自分の言いたい情報を返しがち（質問と応答のかみ合わせのずれ）。英語のQ&Aは問いの構造に応答を対応させる明示性が要る。 | J14: 自己紹介の一方向から、書面の「往復する情報交換」へ。書面系列の到達点。
A16: DISCUSSION ── この行為をパターンとして読む（アレグザンダー式・行為全体への散文）
A17: 【主張型の核は疑問文の構造そのものである】 苦情（指示型）の核が緩衝、挨拶（儀礼型）の核がレジスターとテンポだったのに対し、事実情報の質問と応答（主張型）の核は、疑問文と応答の文法構造そのものにある。この行為で一貫して効く how well 軸は社会言語的適切さではなく文法的正確さである。What's your name? / Where do you live? / What are you doing this weekend? ── レベルが上がるとは、扱える疑問の時制と法が広がること（be動詞疑問→do支持疑問→過去疑問→未来表現の三系統）にほかならない。緩衝もレジスターも、この行為ではほぼ問われない。 【日本語話者のつまずきは「疑問文の作り方」に集中する】 指示型・儀礼型のL1問題が語用論（言い出せない、phaticの誤解）だったのに対し、主張型のL1問題は純粋に文法・統語に寄る。第一に do 支持 ── 日本語は語尾「〜か」だけで疑問を作れるため、Where do you live? の do を立てる操作が身につかず Where you live? が頻発する。第二に時制の保持 ── 疑問文中で was/did を落とす。第三に冠詞と主語 ── This is key. / 主語Iの脱落。これらは語用論的配慮ではなく、日本語に存在しない文法範疇（助動詞do、厳密な時制一致、冠詞）が事実の授受のたびに露出する現象である。したがってこの行為のL1注意は「文化」ではなく「構造」を突くものになる。 【未来表現の三系統が唯一の高度な難所】 主張型はおおむね平明だが、一点だけ質的な難所がある ── 未来の予定・意図（A2+）を表す will / be going to / 現在進行形の使い分けである。日本語の「〜する／〜するつもり」の二分では英語の三系統に対応できない。ここだけは文法項目の暗記では足りず、話者の心的態度（その場の決定か、既定の意図か、手配済みか）と結びつけて教える必要がある。カタログではこの一点を厚く扱う。 【口頭は往復、書面は自己完結】 情報交換はCEFRでは圧倒的に口頭（Information exchange スケール）に記述が集中し、書面はCorrespondence由来の情報記述が少数あるのみ。この非対称は本質的で、事実の授受は本来リアルタイムの往復（Q — A）に最も自然に宿る。書面に移ると、口頭の省略（主語や述語の脱落）が使えず、自己完結した平叙文を連ねる必要が生じる ── 話し言葉の省略を書面に持ち込むと非文になる、という書面固有の壁が現れる。 【範型としての検証 ── 主張型の点検軸】 主張型に効く点検軸は、指示型・儀礼型と異なる。(1) レベル軸は「疑問の時制・法の拡大」として明快に立つ（初級で出尽くすが、内部に文法的段階がある）。(2) L1注意は語用論ではなく統語（do支持・時制・冠詞・主語）を突く。(3) how well の主軸は文法的正確さ。(4) 唯一の高度な難所は未来表現の三系統。(5) 口頭往復と書面自己完結の差。この5点が、同じ主張型の他行為（自己に関する情報提供、経験・出来事の叙述、問題・事情の説明など）を作る際の点検リストになる。ただし主張型内でも「経験・出来事の叙述」は疑問応答ではなく一方向の語りなので、疑問文構造の軸が効かない可能性がある ── これは汎用性検証で確かめるべき論点である。

Sheet 範型_意見表明
A1: 第1カタログ 範型 ── 発語内行為「意見・見解の表明（Expressing opinions & views）」
A2: 類型：表出的（expressive）＋主張的要素 ── 話者の心的態度（賛否・評価）を表明し、根拠で支える ／ 本質：ある事柄について自分の立場・評価・信念を述べ、レベルが上がるほど根拠と論拠で支え、他者の見解と関係づける。主張の中身より、立場表明の型と、対立を許容する作法が要となる。
A4: モード | B4: レベル | C4: No. | D4: CEFR記述文（原文） | E4: 記述文（作業訳） | F4: 実例（exponent） | G4: 場面 | H4: 効くhow well軸 | I4: 日本語話者へのL1語用論注意 | J4: 隣接レベルとの差分
A5: 口頭 | B5: A2 | C5: 479 | D5: Can express opinions in a limited way. | E5: 意見を限られた形で表明できる。 | F5: • I think it's good. • I like it. / I don't like it. • For me, it's too expensive. | G5: 身近な事柄に、ごく短く賛否や評価を述べる。 | H5: 文法（I think 節）：I think + 文 の骨格。 | I5: I think を付けずに It's good. と言い切ると断定に響く。日本語は「〜と思う」を多用して主観を和らげるが、英語でも I think は立場表明の基本枠。ただし日本語の「思う」ほど義務的ではなく、乱発すると自信なさげにも響く、という温度差がある。 | J5: （起点）意見表明の最小形。I think＋評価語のみ。
A6: 口頭 | B6: A2+ | C6: 473 | D6: Can exchange opinions and compare things and people using simple language. | E6: 簡単な言葉で意見を交換し、物や人を比較できる。 | F6: • I think summer is better than winter. • This one is nicer, but that one is cheaper. • What do you think? — I agree. / I'm not sure. | G6: 二つの選択肢を比べ、意見を交換し合う。 | H6: 文法（比較級）＋社会言語的適切さ：比較構文と同意/留保の応答。 | I6: 比較級（better than, nicer）の構造は日本語の「〜より」と語順が逆で作りにくい。また I'm not sure.（やんわり不同意）のような中間的応答の層が薄く、賛成か沈黙かの二択になりがち。 | J6: 単独の意見から「意見の交換と比較」へ。比較と応答の往復が加わる。
A7: 口頭 | B7: B1 | C7: 471 | D7: Can express beliefs, opinions and agreement and disagreement politely. | E7: 信念・意見・賛否を丁寧に表明できる。 | F7: • I see your point, but I think... • I agree with you up to a point. • Actually, I don't really think that's true. | G7: 議論の中で、賛成・反対を相手を立てつつ丁寧に表明する。 | H7: 社会言語的適切さ（不同意の緩衝）：反対を丁寧に包めるか。 | I7: ここが表出型最大のL1難所。日本語話者は不同意を避けて曖昧にするか、逆に But that's wrong. と裸で否定して角を立てるかに振れる。英語は I see your point, but... / I'm not sure I agree で、相手をまず受けてから反対する型が定石。この「受けてから返す」二段構えは明示的に教える必要がある。 | J7: A2+からの飛躍：単なる評価から「賛否の丁寧な表明」へ。不同意の緩衝が中心課題に。
A8: 口頭 | B8: B1+ | C8: 464 | D8: Can express their thoughts about abstract or cultural topics such as music or films. | E8: 音楽や映画などの抽象的・文化的な話題について考えを表現できる。 | F8: • What I like about this film is how it handles memory. • It's not really my kind of music, but I can see why people love it. • The story felt a bit slow, but the ending made up for it. | G8: 映画・音楽など抽象度の高い対象に、込み入った感想を述べる。 | H8: 叙述の正確さ＋語彙範囲：抽象的評価の語彙と構造。 | I8: 抽象的対象の評価は、日本語では「よかった／いまいち」で済ませがちだが、英語では what I like about X is... のような焦点化構文や、譲歩（but I can see why...）を使って立場を立体的に述べる。この構文の層を持たないと、抽象評価が幼く聞こえる。 | J8: 身近な物から「抽象的・文化的対象」へ。評価語彙と焦点化構文が加わる。
A9: 口頭 | B9: B2 | C9: 462 | D9: Can account for and sustain their opinions in discussion by providing relevant explanations, arguments and comments. | E9: 適切な説明・論拠・コメントを提供して、議論の中で自分の意見を述べ、支持できる。 | F9: • I'd argue that... for two reasons. First,... Second,... • That's a fair point, but the evidence actually suggests otherwise. • I stand by what I said, because... | G9: 議論で自分の立場を、根拠を挙げて主張し、反論にも耐えて維持する。 | H9: 話題の展開＋叙述の正確さ：意見を論拠で構造的に支える。 | I9: 「意見を論拠で支え、維持する」は日本語話者に不慣れ。日本語の議論は結論を曖昧に残す作法もあるが、英語では I'd argue that... because... と立場と根拠を明示し、反論されても I stand by... と保持することが誠実とされる。撤回しすぎると立場が無いと見なされる。 | J9: B1+からの飛躍：感想の表明から「論拠で支え維持する主張」へ。表出が論証に接続する。
A10: 口頭 | B10: C1 | C10: 670 | D10: Can evaluate, restate and challenge arguments in professional or academic live online chat and discussion. | E10: 専門的・学術的なライブのオンライン議論で、論を評価・言い直し・反論できる。 | F10: • If I understand your position correctly, you're saying... — but that assumes... • I'd push back on that slightly. The data you cite doesn't quite support... • Let me reframe: the real question isn't X, it's Y. | G10: 専門的議論で、相手の論を正確に捉え直し、的確に反論・再構成する。 | H10: 叙述の正確さ＋柔軟さ（最大）：論の評価・言い直し・反論の精密制御。 | I10: C1では相手の論を restate（言い直して確認）してから challenge する高度な型が要る。日本語話者は相手の論の要約確認を飛ばして直接反論しがちで、議論がかみ合わない。If I understand you correctly...→but... の型は、正確さと礼節を両立させる英語アカデミック議論の作法として明示的に習得を要する。 | J10: B2からの到達点：主張の維持から「他者の論の評価・再構成・反論」へ。表出型口頭系列の頂点。
A11: 書面 | B11: A2 | C11: 683 | D11: Can make brief positive or negative comments online about embedded links and media using a repertoire of basic language, though they will generally have to refer to an online translation tool and other resources. | E11: 埋め込みリンクやメディアに、基本的な言葉で短い肯定・否定コメントをオンラインでできる。 | F11: • Love this! 😍 • Not for me, sorry. • So true! | G11: SNSの投稿やリンクに、短い賛否のコメントを付ける。 | H11: 社会言語的適切さ（オンライン簡略表現）：口語的な短評の型。 | I11: 英語オンラインの超短評（So true! / Not for me / This!）の語彙が乏しく、硬い I think this is good. で返しがち。日本語の「わかる」「それな」に当たる口語共感表現を、英語の型として別途持つ必要がある。 | J11: （書面起点）口頭の意見表明が、オンラインでは超短評として立ち上がる。
A12: 書面 | B12: B1 | C12: 677 | D12: Can post a comprehensible contribution in an online discussion on a familiar topic of interest, provided they can prepare the text beforehand and use online tools to fill gaps in language and check accuracy. | E12: 事前に準備できれば、関心のある身近な話題のオンライン議論に理解可能な投稿ができる。 | F12: • I think the article raises a good point about remote work, but it overlooks the cost side. • In my experience, this approach works better for small teams. | G12: 準備の上で、オンライン議論に理由を添えた意見を投稿する。 | H12: 叙述の正確さ（書面）：準備された、自己完結した意見投稿。 | I12: 書面の意見投稿では、口頭の往復に頼れず、立場＋理由を一つの投稿で自己完結させる必要がある。日本語話者は結論を最後に置き前置きを長くしがちだが、英語オンライン議論は要点先行（I think X, but Y）が読まれやすい。 | J12: 超短評から「理由を添えた議論への投稿」へ。準備を挟んだ自己完結した表明。
A13: 書面 | B13: B1+ | C13: 635 | D13: Can compose personal letters giving news and expressing thoughts about abstract or cultural topics such as music or film. | E13: 近況を伝え、音楽や映画などの抽象的・文化的話題についての考えを表現する個人的な手紙を書ける。 | F13: • I finally watched that film you recommended. I loved the visuals, though the plot lost me a bit. • Lately I've been getting into jazz — there's something about it that really calms me down. | G13: 私信で、近況とともに文化的対象への考えを綴る。 | H13: 叙述の正確さ＋語彙範囲：私信レジスターでの抽象的感想。 | I13: 私信での考えの表明は、口語的親密さと一定の内容を両立させる。日本語の手紙の様式（時候の挨拶等）を英語に持ち込むと不自然で、英語私信は近況と感想を地続きに書く。この様式差は書面ならではの注意点。 | J13: 議論投稿から「私信での考えの表明」へ。親密なレジスターでの抽象的感想。書面系列の到達点。
A15: DISCUSSION ── この行為をパターンとして読む（アレグザンダー式・行為全体への散文）
A16: 【表出型の核は「不同意を許容する作法」である】 苦情（指示型）の核が緩衝、挨拶（儀礼型）がレジスターとテンポ、事実Q&A（主張型）が疑問文構造だったのに対し、意見・見解の表明（表出型）の核は、立場の表明と、とりわけ対立を許容し丁寧に扱う作法にある。レベルが上がるとは、意見を「述べる」だけから、根拠で「支え」、他者の論と「関係づけ」、最終的に「評価・再構成・反論する」へと、社会的な議論の営みへ深化することである。効く how well 軸は、低位では文法（I think節・比較級）だが、B1以降は社会言語的適切さと叙述の正確さ（論拠の構造）へ移る。 【最大のL1難所は「受けてから返す」不同意の型】 日本語話者にとって表出型の中心的困難は、不同意の扱いにある。日本語文化では公然の不同意が回避されやすく、その結果、英語でも二つの失敗形に振れる ── 曖昧にして立場を消すか、But that's wrong. と裸で否定して角を立てるか。英語の作法は第三の道で、I see your point, but... / That's a fair point, but... と、まず相手を受けてから反対する二段構えである。この「受けてから返す」型は、B1で登場しC1まで一貫して深化する（C1では相手の論を restate してから challenge する）。表出型カタログの背骨は、この不同意の作法の段階的精緻化として引くべきである。 【意見は「維持」まで含めて一つの行為である】 主張型の事実Q&Aが単発の授受で完結するのに対し、意見表明はB2で「維持する（sustain）」が加わる点が質的に異なる。I stand by what I said, because... ── 反論されても根拠とともに立場を保つことが、英語では誠実さとされる。日本語話者は対立を避けて安易に撤回しがちだが、それは英語の議論では「立場が無い」と受け取られる。表明・支持・維持を一続きの行為として示すことが、この行為のカタログの要点である。 【抽象的対象には専用の構文がある】 B1+以降、評価対象が身近な物から抽象的・文化的対象（音楽・映画・思想）へ移ると、what I like about X is... の焦点化構文や、I can see why..., though... の譲歩構文が要る。日本語の「よかった／いまいち」の二元では抽象評価が幼く響く。この構文層は語彙ではなく「立場を立体的に述べる型」であり、表出型に固有の習得課題である。 【範型としての検証 ── 表出型の点検軸】 表出型に効く点検軸：(1) レベル軸は「表明→支持→維持→評価・反論」という議論の深化として長く立つ（苦情型に似て梯子が長い）。(2) L1注意の中心は不同意の作法（受けてから返す）。(3) how well の主軸は低位で文法、B1以降は社会言語的適切さ＋叙述の正確さへ移動する。(4) 意見の「維持」が行為の一部。(5) 抽象的対象用の焦点化・譲歩構文。この5点が、同じ表出型の他行為（感情の表出、好悪の表明、感謝・詫び・祝意など）を作る際の点検リストになる。ただし表出型内でも「感謝・詫び」は定型性が高く儀礼型に近い顔を持つ可能性があり、「感情の表出」は不同意の作法が効かない ── 表出型は内部の振れ幅が大きく、汎用性検証で下位分化を確かめる必要がある。

Sheet 類型別点検軸
A1: 四類型の点検軸 ── 範型から抽出した、類型別テンプレートの骨子
A2: 類型 | B2: 範型とした行為 | C2: レベル軸の性格 | D2: L1注意の中心 | E2: 効くhow well主軸 | F2: 汎用性検証で確かめる論点
A3: 指示型 (directive) | B3: 苦情・クレーム | C3: A2→C1の長い梯子。緩衝の精緻化として一直線に読める | D3: 言い出せない／振れすぎるの二重の壁。緩衝技法の欠如 | E3: 社会言語的適切さ（緩衝） | F3: 依頼・要求に当てて、緩衝軸と口頭書面分岐がそのまま効くか
A4: 儀礼型 (phatic) | B4: 挨拶・別れ・安否 | C4: Pre-A1〜A2+で出尽くす。上級が無い。レベル軸がほぼ消える | D4: phaticの誤解（How are you?を情報要求と取る）。レジスターとテンポ。終了定型の欠如 | E4: 社会言語的適切さ（レジスター） | F4: 会話の開始・維持に当てて、レベル軸消失とphatic説明が効くか
A5: 主張型 (assertive) | B5: 事実情報の質問と応答 | C5: 初中級で出尽くすが、内部に疑問の時制・法の文法的段階 | D5: 語用論でなく統語（do支持・時制・冠詞・主語の脱落） | E5: 文法的正確さ | F5: 経験・出来事の叙述に当てて、疑問文構造の軸が効くか（一方向の語りでは効かない可能性）
A6: 表出型 (expressive) | B6: 意見・見解の表明 | C6: A2→C1の長い梯子。表明→支持→維持→評価・反論と深化 | D6: 不同意の作法（受けてから返す）。安易な撤回／裸の否定 | E6: 社会言語的適切さ＋叙述の正確さ | F6: 感謝・詫び（定型的で儀礼型寄り）／感情の表出（不同意作法が効かない）で下位分化を確認
A8: 四類型すべてに範型を1つずつ作成完了。次段階：各類型内で範型を「同類の別行為」に適用し、テンプレートの汎用性を検証する（右端列の論点）。単一テンプレートの全行為機械適用は不可 ── 類型判定→類型別テンプレート→類型内検証の三段が量産の前提。

Sheet 発語内行為インベントリ
A1: 大類型 | B1: 発語内行為 | C1: 記述文数 | D1: Pre-A1 | E1: A1 | F1: A2 | G1: B1 | H1: B2 | I1: C1 | J1: C2 | K1: 最低レベル | L1: 該当No.
A2: 交話・儀礼 | B2: 挨拶・別れ・安否 | C2: 9 | D2: 3 | E2: 3 | F2: 3 | K2: Pre-A1 | L2: 438, 444, 451, 452, 453, 455, 648, 682, 686
A3: 交話・儀礼 | B3: 会話の開始・維持 | C3: 5 | E3: 1 | F3: 1 | G3: 2 | H3: 1 | K3: A1 | L3: 427, 432, 434, 445, 450
A4: 表出 | B4: 意見・見解の表明 | C4: 18 | F4: 4 | G4: 10 | H4: 3 | I4: 1 | K4: A2 | L4: 460, 462, 464, 466, 469, 470, 471, 473, 479, 512, 514, 515, 635, 670, 672, 677, 681, 683
A5: 表出 | B5: 感情の表出 | C5: 8 | F5: 1 | G5: 5 | H5: 2 | K5: A2 | L5: 431, 437, 447, 630, 636, 639, 676, 678
A6: 表出 | B6: 感謝・詫び・祝意 | C6: 6 | E6: 1 | F6: 4 | H6: 1 | K6: A1 | L6: 441, 446, 632, 644, 646, 685
A7: 表出 | B7: 好悪の表明 | C7: 4 | E7: 3 | F7: 1 | K7: A1 | L7: 448, 480, 647, 684
A8: 表出 | B8: 理解状態の表明 | C8: 3 | E8: 2 | F8: 1 | K8: A1 | L8: 745, 747, 748
A9: 主張 | B9: 事実情報の授受 | C9: 15 | E9: 1 | F9: 6 | G9: 6 | H9: 2 | K9: A1 | L9: 541, 554, 555, 557, 559, 562, 568, 591, 633, 640, 642, 649, 656, 659, 679
A10: 主張 | B10: 事実情報の質問と応答 | C10: 15 | D10: 6 | E10: 3 | F10: 6 | K10: Pre-A1 | L10: 563, 564, 565, 569, 570, 572, 574, 575, 578, 579, 581, 582, 583, 584, 585
A11: 主張 | B11: 問題・事情の説明 | C11: 8 | E11: 1 | F11: 2 | G11: 4 | H11: 1 | K11: A1 | L11: 465, 511, 529, 590, 593, 596, 598, 600
A12: 主張 | B12: 面接での質問と応答 | C12: 6 | F12: 2 | G12: 2 | H12: 2 | K12: A2 | L12: 588, 589, 592, 594, 595, 597
A13: 主張 | B13: 伝言の授受 | C13: 6 | E13: 1 | F13: 1 | G13: 3 | H13: 1 | K13: A1 | L13: 653, 654, 655, 657, 658, 662
A14: 主張 | B14: 自己に関する情報提供 | C14: 5 | D14: 2 | E14: 1 | F14: 2 | K14: Pre-A1 | L14: 571, 599, 643, 650, 687
A15: 主張 | B15: 経験・出来事の叙述 | C15: 1 | F15: 1 | K15: A2+ | L15: 680
A16: 指示 | B16: 明確化・繰り返しの要求 | C16: 14 | F16: 4 | G16: 5 | H16: 3 | I16: 2 | K16: A2 | L16: 531, 668, 699, 702, 704, 737, 738, 739, 740, 741, 742, 743, 744, 746
A17: 指示 | B17: 取引（購入・注文） | C17: 12 | D17: 1 | F17: 8 | G17: 1 | H17: 1 | I17: 1 | K17: Pre-A1 | L17: 537, 539, 540, 542, 543, 545, 549, 691, 695, 700, 703, 705
A18: 指示 | B18: 苦情・クレーム | C18: 9 | F18: 1 | G18: 3 | H18: 4 | I18: 1 | K18: A2 | L18: 526, 527, 532, 533, 544, 625, 628, 629, 638
A19: 指示 | B19: 提案・誘い・計画の相談 | C19: 8 | F19: 5 | G19: 1 | H19: 2 | K19: A2 | L19: 467, 474, 475, 477, 478, 508, 645, 697
A20: 指示 | B20: 依頼・要求 | C20: 6 | E20: 3 | F20: 3 | K20: A1 | L20: 442, 519, 522, 538, 546, 547
A21: 指示 | B21: 問い合わせ | C21: 3 | F21: 1 | G21: 1 | H21: 1 | K21: A2 | L21: 528, 637, 706
A22: 指示 | B22: 道案内の依頼と提供 | C22: 3 | F22: 2 | G22: 1 | K22: A2+ | L22: 517, 558, 566
A23: 指示 | B23: 助言 | C23: 2 | G23: 1 | J23: 1 | K23: B1 | L23: 456, 560
A24: 指示 | B24: 同意・不同意 | C24: 2 | F24: 1 | H24: 1 | K24: A2+ | L24: 428, 476
A25: 指示 | B25: 応募・出願 | C25: 1 | G25: 1 | K25: B1 | L25: 641
A26: 指示 | B26: 指示への応答 | C26: 1 | F26: 1 | K26: A2 | L26: 707
A28: 言語行為論的に純粋なcan do＝170記述文を発語内行為で集約すると25種。サール類型: 交話・儀礼/表出/主張/指示。列はレベル別記述文数（プラスレベルは基本級に集約）。上級ほど新規行為は増えず、既存行為のhow well化が進む。

Sheet サマリー
A1: CEFR Companion Volume 2020 記述文（Descriptor）全数集計
A2: 出典: CEFR_Descriptors__2020_.xlsx（Englishシート）。訳語の正準は「対訳マスタ」シート（作業訳・公式訳併記）。プレースホルダ行はReal=0として集計から除外。
A4: データ行（空行除く） | B4: =COUNTA(Data!$A$2:$A$1833) -> 1832
A5: 実記述文（プレースホルダ除外） | B5: =SUM(Data!$H$2:$H$1833) -> 1712
A6: うち 手話能力（対象外） | B6: =COUNTIFS(Data!$B$2:$B$1833,"Signing competences",Data!$H$2:$H$1833,1) -> 488
A7: 音声言語の実記述文 | B7: =B5-B6 -> 1224
A9: スキーム × レベル（実記述文）
A10: スキーム | B10: Pre-A1 | C10: A1 | D10: A2 | E10: A2+ | F10: B1 | G10: B1+ | H10: B2 | I10: B2+ | J10: C1 | K10: C2 | L10: 計 | N10: EN:Scheme
A11: =IFERROR(INDEX(対訳マスタ!$C$2:$C$136,MATCH($N11,対訳マスタ!$B$2:$B$136,0)),$N11) -> コミュニケーション言語活動 | B11: =COUNTIFS(Data!$B$2:$B$1833,$N11,Data!$F$2:$F$1833,B$10,Data!$H$2:$H$1833,1) -> 41 | C11: =COUNTIFS(Data!$B$2:$B$1833,$N11,Data!$F$2:$F$1833,C$10,Data!$H$2:$H$1833,1) -> 78 | D11: =COUNTIFS(Data!$B$2:$B$1833,$N11,Data!$F$2:$F$1833,D$10,Data!$H$2:$H$1833,1) -> 115 | E11: =COUNTIFS(Data!$B$2:$B$1833,$N11,Data!$F$2:$F$1833,E$10,Data!$H$2:$H$1833,1) -> 85 | F11: =COUNTIFS(Data!$B$2:$B$1833,$N11,Data!$F$2:$F$1833,F$10,Data!$H$2:$H$1833,1) -> 131 | G11: =COUNTIFS(Data!$B$2:$B$1833,$N11,Data!$F$2:$F$1833,G$10,Data!$H$2:$H$1833,1) -> 80 | H11: =COUNTIFS(Data!$B$2:$B$1833,$N11,Data!$F$2:$F$1833,H$10,Data!$H$2:$H$1833,1) -> 115 | I11: =COUNTIFS(Data!$B$2:$B$1833,$N11,Data!$F$2:$F$1833,I$10,Data!$H$2:$H$1833,1) -> 68 | ... K11: =COUNTIFS(Data!$B$2:$B$1833,$N11,Data!$F$2:$F$1833,K$10,Data!$H$2:$H$1833,1) -> 60 | L11: =SUM(B11:K11) -> 874 | N11: Communicative language activities
A12: =IFERROR(INDEX(対訳マスタ!$C$2:$C$136,MATCH($N12,対訳マスタ!$B$2:$B$136,0)),$N12) -> コミュニケーション言語方略 | B12: =COUNTIFS(Data!$B$2:$B$1833,$N12,Data!$F$2:$F$1833,B$10,Data!$H$2:$H$1833,1) -> 2 | C12: =COUNTIFS(Data!$B$2:$B$1833,$N12,Data!$F$2:$F$1833,C$10,Data!$H$2:$H$1833,1) -> 5 | D12: =COUNTIFS(Data!$B$2:$B$1833,$N12,Data!$F$2:$F$1833,D$10,Data!$H$2:$H$1833,1) -> 11 | E12: =COUNTIFS(Data!$B$2:$B$1833,$N12,Data!$F$2:$F$1833,E$10,Data!$H$2:$H$1833,1) -> 7 | F12: =COUNTIFS(Data!$B$2:$B$1833,$N12,Data!$F$2:$F$1833,F$10,Data!$H$2:$H$1833,1) -> 18 | G12: =COUNTIFS(Data!$B$2:$B$1833,$N12,Data!$F$2:$F$1833,G$10,Data!$H$2:$H$1833,1) -> 16 | H12: =COUNTIFS(Data!$B$2:$B$1833,$N12,Data!$F$2:$F$1833,H$10,Data!$H$2:$H$1833,1) -> 21 | I12: =COUNTIFS(Data!$B$2:$B$1833,$N12,Data!$F$2:$F$1833,I$10,Data!$H$2:$H$1833,1) -> 12 | ... K12: =COUNTIFS(Data!$B$2:$B$1833,$N12,Data!$F$2:$F$1833,K$10,Data!$H$2:$H$1833,1) -> 8 | L12: =SUM(B12:K12) -> 116 | N12: Communicative language strategies
A13: =IFERROR(INDEX(対訳マスタ!$C$2:$C$136,MATCH($N13,対訳マスタ!$B$2:$B$136,0)),$N13) -> コミュニケーション言語能力 | B13: =COUNTIFS(Data!$B$2:$B$1833,$N13,Data!$F$2:$F$1833,B$10,Data!$H$2:$H$1833,1) -> 4 | C13: =COUNTIFS(Data!$B$2:$B$1833,$N13,Data!$F$2:$F$1833,C$10,Data!$H$2:$H$1833,1) -> 15 | D13: =COUNTIFS(Data!$B$2:$B$1833,$N13,Data!$F$2:$F$1833,D$10,Data!$H$2:$H$1833,1) -> 22 | E13: =COUNTIFS(Data!$B$2:$B$1833,$N13,Data!$F$2:$F$1833,E$10,Data!$H$2:$H$1833,1) -> 10 | F13: =COUNTIFS(Data!$B$2:$B$1833,$N13,Data!$F$2:$F$1833,F$10,Data!$H$2:$H$1833,1) -> 25 | G13: =COUNTIFS(Data!$B$2:$B$1833,$N13,Data!$F$2:$F$1833,G$10,Data!$H$2:$H$1833,1) -> 8 | H13: =COUNTIFS(Data!$B$2:$B$1833,$N13,Data!$F$2:$F$1833,H$10,Data!$H$2:$H$1833,1) -> 36 | I13: =COUNTIFS(Data!$B$2:$B$1833,$N13,Data!$F$2:$F$1833,I$10,Data!$H$2:$H$1833,1) -> 11 | ... K13: =COUNTIFS(Data!$B$2:$B$1833,$N13,Data!$F$2:$F$1833,K$10,Data!$H$2:$H$1833,1) -> 18 | L13: =SUM(B13:K13) -> 182 | N13: Communicative language competences
A14: =IFERROR(INDEX(対訳マスタ!$C$2:$C$136,MATCH($N14,対訳マスタ!$B$2:$B$136,0)),$N14) -> 複言語・複文化能力 | B14: =COUNTIFS(Data!$B$2:$B$1833,$N14,Data!$F$2:$F$1833,B$10,Data!$H$2:$H$1833,1) -> 0 | C14: =COUNTIFS(Data!$B$2:$B$1833,$N14,Data!$F$2:$F$1833,C$10,Data!$H$2:$H$1833,1) -> 3 | D14: =COUNTIFS(Data!$B$2:$B$1833,$N14,Data!$F$2:$F$1833,D$10,Data!$H$2:$H$1833,1) -> 10 | E14: =COUNTIFS(Data!$B$2:$B$1833,$N14,Data!$F$2:$F$1833,E$10,Data!$H$2:$H$1833,1) -> 0 | F14: =COUNTIFS(Data!$B$2:$B$1833,$N14,Data!$F$2:$F$1833,F$10,Data!$H$2:$H$1833,1) -> 13 | G14: =COUNTIFS(Data!$B$2:$B$1833,$N14,Data!$F$2:$F$1833,G$10,Data!$H$2:$H$1833,1) -> 0 | H14: =COUNTIFS(Data!$B$2:$B$1833,$N14,Data!$F$2:$F$1833,H$10,Data!$H$2:$H$1833,1) -> 15 | I14: =COUNTIFS(Data!$B$2:$B$1833,$N14,Data!$F$2:$F$1833,I$10,Data!$H$2:$H$1833,1) -> 0 | ... K14: =COUNTIFS(Data!$B$2:$B$1833,$N14,Data!$F$2:$F$1833,K$10,Data!$H$2:$H$1833,1) -> 3 | L14: =SUM(B14:K14) -> 52 | N14: Plurilingual and pluricultural competence
A15: =IFERROR(INDEX(対訳マスタ!$C$2:$C$136,MATCH($N15,対訳マスタ!$B$2:$B$136,0)),$N15) -> 手話能力 | B15: =COUNTIFS(Data!$B$2:$B$1833,$N15,Data!$F$2:$F$1833,B$10,Data!$H$2:$H$1833,1) -> 0 | C15: =COUNTIFS(Data!$B$2:$B$1833,$N15,Data!$F$2:$F$1833,C$10,Data!$H$2:$H$1833,1) -> 47 | D15: =COUNTIFS(Data!$B$2:$B$1833,$N15,Data!$F$2:$F$1833,D$10,Data!$H$2:$H$1833,1) -> 46 | E15: =COUNTIFS(Data!$B$2:$B$1833,$N15,Data!$F$2:$F$1833,E$10,Data!$H$2:$H$1833,1) -> 41 | F15: =COUNTIFS(Data!$B$2:$B$1833,$N15,Data!$F$2:$F$1833,F$10,Data!$H$2:$H$1833,1) -> 65 | G15: =COUNTIFS(Data!$B$2:$B$1833,$N15,Data!$F$2:$F$1833,G$10,Data!$H$2:$H$1833,1) -> 61 | H15: =COUNTIFS(Data!$B$2:$B$1833,$N15,Data!$F$2:$F$1833,H$10,Data!$H$2:$H$1833,1) -> 67 | I15: =COUNTIFS(Data!$B$2:$B$1833,$N15,Data!$F$2:$F$1833,I$10,Data!$H$2:$H$1833,1) -> 58 | ... K15: =COUNTIFS(Data!$B$2:$B$1833,$N15,Data!$F$2:$F$1833,K$10,Data!$H$2:$H$1833,1) -> 35 | L15: =SUM(B15:K15) -> 488 | N15: Signing competences
A16: 計 | B16: =SUM(B11:B15) -> 47 | C16: =SUM(C11:C15) -> 148 | D16: =SUM(D11:D15) -> 204 | E16: =SUM(E11:E15) -> 143 | F16: =SUM(F11:F15) -> 252 | G16: =SUM(G11:G15) -> 165 | H16: =SUM(H11:H15) -> 254 | I16: =SUM(I11:I15) -> 149 | ... L16: =SUM(L11:L15) -> 1712

Sheet Data
A1: No | B1: Scheme | C1: Mode | D1: Activity | E1: Scale | F1: Level | G1: Descriptor | H1: Real
A2: 1 | B2: Communicative language activities | C2: Reception | D2: Oral comprehension | E2: Overall oral comprehension | F2: C2 | G2: Can understand with ease virtually any kind of language, whether live or broadcast, delivered at fast natural speed. | H2: 1
A3: 2 | B3: Communicative language activities | C3: Reception | D3: Oral comprehension | E3: Overall oral comprehension | F3: C1 | G3: Can understand enough to follow extended discourse on abstract and complex topics beyond their own field, though they may need to confirm occasional details, especially if the variety is unfamiliar. | H3: 1
A4: 3 | B4: Communicative language activities | C4: Reception | D4: Oral comprehension | E4: Overall oral comprehension | F4: C1 | G4: Can recognise a wide range of idiomatic expressions and colloquialisms, appreciating register shifts. | H4: 1
A5: 4 | B5: Communicative language activities | C5: Reception | D5: Oral comprehension | E5: Overall oral comprehension | F5: C1 | G5: Can follow extended discourse even when it is not clearly structured and when relationships are only implied and not signalled explicitly. | H5: 1
A6: 5 | B6: Communicative language activities | C6: Reception | D6: Oral comprehension | E6: Overall oral comprehension | F6: B2+ | G6: Can understand standard language or a familiar variety, live or broadcast, on both familiar and unfamiliar topics normally encountered in personal, social, academic or vocational life. Only extreme [auditory/visual] background noise, inadequate discourse structure and/or idiomatic usage influence the ability to understand. | H6: 1
A7: 6 | B7: Communicative language activities | C7: Reception | D7: Oral comprehension | E7: Overall oral comprehension | F7: B2 | G7: Can understand the main ideas of propositionally and linguistically complex discourse on both concrete and abstract topics delivered in standard language or a familiar variety, including technical discussions in their field of specialisation. | H7: 1
A8: 7 | B8: Communicative language activities | C8: Reception | D8: Oral comprehension | E8: Overall oral comprehension | F8: B2 | G8: Can follow extended discourse and complex lines of argument, provided the topic is reasonably familiar, and the direction of the argument is signposted by explicit markers. | H8: 1
A9: 8 | B9: Communicative language activities | C9: Reception | D9: Oral comprehension | E9: Overall oral comprehension | F9: B1+ | G9: Can understand straightforward factual information about common everyday or job-related topics, identifying both general messages and specific details, provided people articulate clearly in a generally familiar variety. | H9: 1
A10: 9 | B10: Communicative language activities | C10: Reception | D10: Oral comprehension | E10: Overall oral comprehension | F10: B1 | G10: Can understand the main points made in clear standard language or a familiar variety on familiar matters regularly encountered at work, school, leisure, etc., including short narratives. | H10: 1
A11: 10 | B11: Communicative language activities | C11: Reception | D11: Oral comprehension | E11: Overall oral comprehension | F11: A2+ | G11: Can understand enough to be able to meet needs of a concrete type, provided people articulate clearly and slowly. | H11: 1
A12: 11 | B12: Communicative language activities | C12: Reception | D12: Oral comprehension | E12: Overall oral comprehension | F12: A2 | G12: Can understand phrases and expressions related to areas of most immediate priority (e.g. very basic personal and family information, shopping, local geography, employment), provided people articulate clearly and slowly. | H12: 1
A13: 12 | B13: Communicative language activities | C13: Reception | D13: Oral comprehension | E13: Overall oral comprehension | F13: A1 | G13: Can follow language which is very slow and carefully articulated, with long pauses for them to assimilate meaning. | H13: 1
... A1833: 1832 | B1833: Signing competences | C1833: — | D1833: Pragmatic competence | E1833: Signing fluency | F1833: A1 | G1833: No descriptors available | H1833: 0

Sheet 対訳マスタ
A1: 区分 | B1: English（正準キー・原文verbatim） | C1: 日本語（作業訳） | D1: 公式訳（随伴版・日本語版2024） | E1: 一致 | F1: 備考
A2: 列見出し | B2: No | C2: 番号 | D2: 番号 | E2: =IF($C2=$D2,"○","≠") -> ○
A3: 列見出し | B3: CEFR Descriptor Scheme (updated) | C3: スキーム（記述文の大区分） | D3: CEFR能力記述文スキーム（更新版） | E3: =IF($C3=$D3,"○","≠") -> ≠
A4: 列見出し | B4: Mode of communication | C4: コミュニケーション・モード | D4: コミュニケーションのモード | E4: =IF($C4=$D4,"○","≠") -> ≠
A5: 列見出し | B5: Activity, strategy or competence | C5: 活動・方略・能力の種別 | D5: 活動・方略・能力 | E5: =IF($C5=$D5,"○","≠") -> ≠
A6: 列見出し | B6: Scale | C6: スケール（尺度＝適用範囲） | D6: 尺度 | E6: =IF($C6=$D6,"○","≠") -> ≠
A7: 列見出し | B7: Level | C7: レベル | D7: レベル | E7: =IF($C7=$D7,"○","≠") -> ○
A8: 列見出し | B8: Descriptor | C8: 記述文（Can-Do） | D8: 能力記述文 | E8: =IF($C8=$D8,"○","≠") -> ≠
A9: スキーム | B9: Communicative language activities | C9: コミュニケーション言語活動 | D9: コミュニケーション言語活動 | E9: =IF($C9=$D9,"○","≠") -> ○ | F9: 「何ができるか」の本体
A10: スキーム | B10: Communicative language strategies | C10: コミュニケーション言語方略 | D10: コミュニケーション方略 | E10: =IF($C10=$D10,"○","≠") -> ≠ | F10: 「戦略」とも訳される
A11: スキーム | B11: Communicative language competences | C11: コミュニケーション言語能力 | D11: 言語コミュニケーション能力 | E11: =IF($C11=$D11,"○","≠") -> ≠ | F11: 「どれくらいうまく」の物差し（言語・社会言語・語用）
A12: スキーム | B12: Plurilingual and pluricultural competence | C12: 複言語・複文化能力 | D12: 複言語能力と複文化能力 | E12: =IF($C12=$D12,"○","≠") -> ≠
A13: スキーム | B13: Signing competences | C13: 手話能力 | D13: 手話能力 | E13: =IF($C13=$D13,"○","≠") -> ○ | F13: 音声英語カタログの対象外
A14: モード | B14: Reception | C14: 受容 | D14: 受容 | E14: =IF($C14=$D14,"○","≠") -> ○ | F14: 聞く・読む
A15: モード | B15: Production | C15: 産出 | D15: 産出 | E15: =IF($C15=$D15,"○","≠") -> ○ | F15: 話す・書く
A16: モード | B16: Interaction | C16: 相互行為 | D16: やり取り | E16: =IF($C16=$D16,"○","≠") -> ≠ | F16: やりとり。提案書の用語に合わせた
A17: モード | B17: Mediation | C17: 仲介 | D17: 仲介 | E17: =IF($C17=$D17,"○","≠") -> ○ | F17: 橋渡し・言い換え・要約など
A18: 活動・方略・能力の種別 | B18: Oral comprehension | C18: 口頭理解（聞くこと） | D18: 聴解 | E18: =IF($C18=$D18,"○","≠") -> ≠
A19: 活動・方略・能力の種別 | B19: Audio-visual comprehension | C19: 視聴覚理解 | D19: 視聴覚による理解 | E19: =IF($C19=$D19,"○","≠") -> ≠
A20: 活動・方略・能力の種別 | B20: Reading comprehension | C20: 読解（読むこと） | D20: 読解 | E20: =IF($C20=$D20,"○","≠") -> ≠
A21: 活動・方略・能力の種別 | B21: Oral production | C21: 口頭産出（話すこと） | D21: 口頭での産出活動（話すこと） | E21: =IF($C21=$D21,"○","≠") -> ≠
A22: 活動・方略・能力の種別 | B22: Written production | C22: 記述産出（書くこと） | D22: 書く活動 | E22: =IF($C22=$D22,"○","≠") -> ≠
A23: 活動・方略・能力の種別 | B23: Oral interaction | C23: 口頭の相互行為 | D23: 口頭でのやり取り | E23: =IF($C23=$D23,"○","≠") -> ≠
A24: 活動・方略・能力の種別 | B24: Written interaction | C24: 筆記の相互行為 | D24: 文書によるやり取り | E24: =IF($C24=$D24,"○","≠") -> ≠
A25: 活動・方略・能力の種別 | B25: Online interaction | C25: オンラインの相互行為 | D25: オンラインでのやり取り | E25: =IF($C25=$D25,"○","≠") -> ≠
A26: 活動・方略・能力の種別 | B26: Mediating a text | C26: テキストの仲介 | D26: テクストの仲介 | E26: =IF($C26=$D26,"○","≠") -> ≠
A27: 活動・方略・能力の種別 | B27: Mediating concepts | C27: 概念の仲介 | D27: 概念/想念/思考の仲介 | E27: =IF($C27=$D27,"○","≠") -> ≠
A28: 活動・方略・能力の種別 | B28: Mediating communication | C28: コミュニケーションの仲介 | D28: コミュニケーションの仲介 | E28: =IF($C28=$D28,"○","≠") -> ○
A29: 活動・方略・能力の種別 | B29: Strategies to explain a new concept | C29: 新しい概念を説明する方略 | D29: 新概念説明の方略 | E29: =IF($C29=$D29,"○","≠") -> ≠
... A33: 活動・方略・能力の種別 | B33: Pragmatic competence | C33: 語用能力 | D33: 運用能力 | E33: =IF($C33=$D33,"○","≠") -> ≠
A34: レベル | B34: Pre-A1 | C34: Pre-A1 | D34: Pre-A1 | E34: =IF($C34=$D34,"○","≠") -> ○ | F34: A1未満の入門段階
A35: レベル | B35: A1 | C35: A1 | D35: A1 | E35: =IF($C35=$D35,"○","≠") -> ○
A36: レベル | B36: A2 | C36: A2 | D36: A2 | E36: =IF($C36=$D36,"○","≠") -> ○
A37: レベル | B37: A2+ | C37: A2+ | D37: A2+ | E37: =IF($C37=$D37,"○","≠") -> ○ | F37: プラスレベル＝同帯の上位
A38: レベル | B38: B1 | C38: B1 | D38: B1 | E38: =IF($C38=$D38,"○","≠") -> ○
A39: レベル | B39: B1+ | C39: B1+ | D39: B1+ | E39: =IF($C39=$D39,"○","≠") -> ○ | F39: プラスレベル
A40: レベル | B40: B2 | C40: B2 | D40: B2 | E40: =IF($C40=$D40,"○","≠") -> ○
A41: レベル | B41: B2+ | C41: B2+ | D41: B2+ | E41: =IF($C41=$D41,"○","≠") -> ○ | F41: プラスレベル
A42: レベル | B42: C1 | C42: C1 | D42: C1 | E42: =IF($C42=$D42,"○","≠") -> ○
A43: レベル | B43: C2 | C43: C2 | D43: C2 | E43: =IF($C43=$D43,"○","≠") -> ○
A44: スケール | B44: Acting as an intermediary in informal situations (with friends and colleagues) | C44: インフォーマルな場面での橋渡し（友人・同僚間） | D44: 非公式の状況（友人や同僚とのやり取り）での仲介者としての行動 | E44: =IF($C44=$D44,"○","≠") -> ≠
A45: スケール | B45: Adapting language | C45: 言葉づかいの調整 | D45: 言語の適正化 | E45: =IF($C45=$D45,"○","≠") -> ≠
A46: スケール | B46: Addressing audiences | C46: 聴衆への発表（スピーチ） | D46: 聴衆の前での講演 | E46: =IF($C46=$D46,"○","≠") -> ≠
A47: スケール | B47: Amplifying a dense text | C47: 密度の高いテキストの展開・補足 | D47: 密度の高いテクストの解析 | E47: =IF($C47=$D47,"○","≠") -> ≠
A48: スケール | B48: Analysis and criticism of creative texts (including literature) | C48: 創作テキストの分析と批評（文学を含む） | D48: 創作テクスト（文学作品を含む）の分析と批評 | E48: =IF($C48=$D48,"○","≠") -> ≠
A49: スケール | B49: Asking for clarification | C49: 明確化の要求（聞き返し） | D49: 説明を求めること | E49: =IF($C49=$D49,"○","≠") -> ≠
A50: スケール | B50: Breaking down complicated information | C50: 複雑な情報の分解 | D50: 複雑な情報の解析 | E50: =IF($C50=$D50,"○","≠") -> ≠
A51: スケール | B51: Building on pluricultural repertoire | C51: 複文化レパートリーの活用 | D51: 複文化レパートリーの構築 | E51: =IF($C51=$D51,"○","≠") -> ≠
A52: スケール | B52: Building on plurilingual repertoire | C52: 複言語レパートリーの活用 | D52: 複言語レパートリーの構築 | E52: =IF($C52=$D52,"○","≠") -> ≠
A53: スケール | B53: Co-operating | C53: 協力（会話を協調して進める） | D53: 協働 | E53: =IF($C53=$D53,"○","≠") -> ≠
... A59: スケール | B59: Creative writing | C59: 創作の文章 | D59: 創作 | E59: =IF($C59=$D59,"○","≠") -> ≠
A60: スケール | B60: Diagramatical accuracy | C60: 空間文法の正確さ | D60: 手話空間使用の正確さ | E60: =IF($C60=$D60,"○","≠") -> ≠ | F60: 手話
A61: スケール | B61: Encouraging conceptual talk | C61: 概念的な対話の促進 | D61: 思考・概念に関する話し合いの奨め | E61: =IF($C61=$D61,"○","≠") -> ≠
A62: スケール | B62: Explaining data in speech or sign | C62: データの説明（口頭・手話） | D62: データの音声言語または手話による説明 | E62: =IF($C62=$D62,"○","≠") -> ≠ | F62: 図表→ことば
A63: スケール | B63: Explaining data in writing | C63: データの説明（文章） | D63: データの文字言語による説明 | E63: =IF($C63=$D63,"○","≠") -> ≠ | F63: 図表→ことば
A64: スケール | B64: Expressing a personal response to creative texts (including literature) | C64: 創作テキストへの個人的な反応の表現 | D64: 創作テクスト（文学作品を含む）に対する個人的な反応の表明 | E64: =IF($C64=$D64,"○","≠") -> ≠
A65: スケール | B65: Facilitating collaborative interaction with peers | C65: 仲間との協働的やりとりの促進 | D65: 仲間との協働的やり取りを進める | E65: =IF($C65=$D65,"○","≠") -> ≠ | F65: 原文末尾にスペース
A66: スケール | B66: Facilitating communication in delicate situations and disagreements | C66: デリケートな状況・対立の場でのコミュニケーション促進 | D66: 微妙な状況や非合意の状況でのコミュニケーションの潤滑化 | E66: =IF($C66=$D66,"○","≠") -> ≠
A67: スケール | B67: Facilitating pluricultural space | C67: 複文化的な場の醸成 | D67: 複文化的空間の構築の促進 | E67: =IF($C67=$D67,"○","≠") -> ≠
A68: スケール | B68: Flexibility | C68: 柔軟さ（言い回しの融通） | D68: 柔軟さ | E68: =IF($C68=$D68,"○","≠") -> ≠
A69: スケール | B69: Fluency | C69: 流暢さ | D69: 流暢さ | E69: =IF($C69=$D69,"○","≠") -> ○
A70: スケール | B70: Formal discussion (meetings) | C70: フォーマルな議論（会議） | D70: 公式の議論（ミーティング/会議） | E70: =IF($C70=$D70,"○","≠") -> ≠
A71: スケール | B71: General linguistic range | C71: 言語レパートリー全般の幅 | D71: 一般的な使用可能言語の範囲 | E71: =IF($C71=$D71,"○","≠") -> ≠
A72: スケール | B72: Goal-oriented co-operation (cooking together, discussing a document, organising an event, etc.) | C72: 目標のある共同作業（料理・文書検討・イベント準備など） | D72: 目的のある協働作業 | E72: =IF($C72=$D72,"○","≠") -> ≠
A73: スケール | B73: Goal-oriented online transactions and collaboration | C73: 目的のあるオンライン取引・協働 | D73: 目的のあるオンラインでの交渉と協働作業 | E73: =IF($C73=$D73,"○","≠") -> ≠
A74: スケール | B74: Grammatical accuracy | C74: 文法的正確さ | D74: 文法的正確さ | E74: =IF($C74=$D74,"○","≠") -> ○
A75: スケール | B75: Identifying cues and inferring (spoken, signed and written) | C75: 手がかりの特定と推論 | D75: 手がかりの発見と推論（話し言葉、手話、書き言葉） | E75: =IF($C75=$D75,"○","≠") -> ≠
A76: スケール | B76: Informal discussion (with friends) | C76: インフォーマルな議論（友人と） | D76: 非公式の議論（友人たちとの） | E76: =IF($C76=$D76,"○","≠") -> ≠ | F76: 原文末尾にスペース
A77: スケール | B77: Information exchange | C77: 情報交換 | D77: 情報の交換 | E77: =IF($C77=$D77,"○","≠") -> ≠
A78: スケール | B78: Interviewing and being interviewed | C78: 面接する・面接を受ける | D78: インタビューをする、受ける | E78: =IF($C78=$D78,"○","≠") -> ≠
A79: スケール | B79: Language awareness and interpretation | C79: 言語への気づきと解釈 | D79: 言語への気づき（言語意識）と解釈 | E79: =IF($C79=$D79,"○","≠") -> ≠ | F79: 手話
A80: スケール | B80: Linking to previous knowledge | C80: 既有知識への結びつけ | D80: 既知の知識への関連付け | E80: =IF($C80=$D80,"○","≠") -> ≠
A81: スケール | B81: Managing interaction | C81: やりとりの運営（進行管理） | D81: やり取りの調整 | E81: =IF($C81=$D81,"○","≠") -> ≠
A82: スケール | B82: Monitoring and repair | C82: モニタリングと修復（言い直し） | D82: モニタリングと修正 | E82: =IF($C82=$D82,"○","≠") -> ≠
A83: スケール | B83: Note-taking (lectures, seminars, meetings, etc.) | C83: ノートテイキング（講義・会議など） | D83: ノートを取ること（講義、セミナー、会議、など） | E83: =IF($C83=$D83,"○","≠") -> ≠
A84: スケール | B84: Notes, messages and forms | C84: メモ・伝言・記入用紙 | D84: メモ、メッセージ、書類 | E84: =IF($C84=$D84,"○","≠") -> ≠
A85: スケール | B85: Obtaining goods and services | C85: 物・サービスの取引 | D85: 製品やサービスの取得 | E85: =IF($C85=$D85,"○","≠") -> ≠ | F85: 提案書の索引では「物・サービスを得る取引」
A86: スケール | B86: Online conversation and discussion | C86: オンラインの会話と議論 | D86: オンラインでの会話と議論 | E86: =IF($C86=$D86,"○","≠") -> ≠
A87: スケール | B87: Orthographic control | C87: 正書法（綴り・表記）の運用 | D87: 正書法の把握 | E87: =IF($C87=$D87,"○","≠") -> ≠
A88: スケール | B88: Overall mediation | C88: 仲介（総合） | D88: 仲介全般 | E88: =IF($C88=$D88,"○","≠") -> ≠
A89: スケール | B89: Overall oral comprehension | C89: 口頭理解（総合） | D89: 聴解全般 | E89: =IF($C89=$D89,"○","≠") -> ≠
A90: スケール | B90: Overall oral interaction | C90: 口頭相互行為（総合） | D90: 口頭でのやり取り全般 | E90: =IF($C90=$D90,"○","≠") -> ≠
A91: スケール | B91: Overall oral production | C91: 口頭産出（総合） | D91: 口頭での産出活動全般 | E91: =IF($C91=$D91,"○","≠") -> ≠
A92: スケール | B92: Overall phonological control | C92: 音韻の運用（総合） | D92: 音声面の制御全般 | E92: =IF($C92=$D92,"○","≠") -> ≠ | F92: いわゆる発音
A93: スケール | B93: Overall reading comprehension | C93: 読解（総合） | D93: 読解全般 | E93: =IF($C93=$D93,"○","≠") -> ≠
A94: スケール | B94: Overall written interaction | C94: 筆記相互行為（総合） | D94: 文書によるやり取り全般 | E94: =IF($C94=$D94,"○","≠") -> ≠
A95: スケール | B95: Overall written production | C95: 記述産出（総合） | D95: 書く活動全般 | E95: =IF($C95=$D95,"○","≠") -> ≠
A96: スケール | B96: Planning | C96: 計画（発話の設計） | D96: 計画 | E96: =IF($C96=$D96,"○","≠") -> ≠
A97: スケール | B97: Plurilingual comprehension | C97: 複言語理解 | D97: 複言語的理解 | E97: =IF($C97=$D97,"○","≠") -> ≠
A98: スケール | B98: Presence and effect | C98: 存在感と効果 | D98: 風貌/風体と与える印象 | E98: =IF($C98=$D98,"○","≠") -> ≠ | F98: 手話
A99: スケール | B99: Processing speed | C99: 処理速度 | D99: 手話処理の速度 | E99: =IF($C99=$D99,"○","≠") -> ≠ | F99: 手話
A100: スケール | B100: Processing text in speech or sign | C100: テキストの加工・要約（口頭・手話） | D100: 口頭言語または手話テクストの処理 | E100: =IF($C100=$D100,"○","≠") -> ≠
A101: スケール | B101: Processing text in writing | C101: テキストの加工・要約（文章） | D101: 文書テクストの処理 | E101: =IF($C101=$D101,"○","≠") -> ≠
A102: スケール | B102: Propositional precision | C102: 命題の精密さ（言いたいことの精度） | D102: 叙述の正確さ | E102: =IF($C102=$D102,"○","≠") -> ≠
A103: スケール | B103: Prosodic features | C103: 韻律（プロソディ） | D103: プロソディー面の習熟 | E103: =IF($C103=$D103,"○","≠") -> ≠ | F103: 原文末尾にスペース
A104: スケール | B104: Public announcements | C104: 公共のアナウンス | D104: 公共アナウンス | E104: =IF($C104=$D104,"○","≠") -> ≠
A105: スケール | B105: Reading as a leisure activity | C105: 娯楽としての読書 | D105: 余暇活動として読む | E105: =IF($C105=$D105,"○","≠") -> ≠
A106: スケール | B106: Reading correspondence | C106: 手紙・メールを読む | D106: 通信文を読む | E106: =IF($C106=$D106,"○","≠") -> ≠
A107: スケール | B107: Reading for information and argument | C107: 情報・論旨の読み取り | D107: 情報や論拠を求めて読む | E107: =IF($C107=$D107,"○","≠") -> ≠
A108: スケール | B108: Reading for orientation | C108: 目当ての情報を探す読み（拾い読み） | D108: 方向付けのために読む | E108: =IF($C108=$D108,"○","≠") -> ≠
...

Sheet スケール別集計
A1: スキーム | B1: モード | C1: 活動・方略・能力の種別 | D1: スケール（作業訳） | E1: Scale（原文） | F1: Pre-A1 | G1: A1 | H1: A2 | I1: A2+ | J1: B1 | K1: B1+ | L1: B2 | M1: B2+ | N1: C1 | O1: C2 | P1: 計 | Q1: EN:Scheme | R1: EN:Mode | S1: EN:Activity
A2: =IFERROR(INDEX(対訳マスタ!$C$2:$C$136,MATCH($Q2,対訳マスタ!$B$2:$B$136,0)),$Q2) -> コミュニケーション言語活動 | B2: =IF($R2="—","—",IFERROR(INDEX(対訳マスタ!$C$2:$C$136,MATCH($R2,対訳マスタ!$B$2:$B$136,0)),$R2)) -> 受容 | C2: =IF($S2="—","—",IFERROR(INDEX(対訳マスタ!$C$2:$C$136,MATCH($S2,対訳マスタ!$B$2:$B$136,0)),$S2)) -> 口頭理解（聞くこと） | D2: =IFERROR(INDEX(対訳マスタ!$C$2:$C$136,MATCH($E2,対訳マスタ!$B$2:$B$136,0)),$E2) -> 口頭理解（総合） | E2: Overall oral comprehension | F2: =COUNTIFS(Data!$B$2:$B$1833,$Q2,Data!$C$2:$C$1833,$R2,Data!$D$2:$D$1833,$S2,Data!$E$2:$E$1833,$E2,Data!$F$2:$F$1833,F$1,Data!$H$2:$H$1833,1) -> 3 | G2: =COUNTIFS(Data!$B$2:$B$1833,$Q2,Data!$C$2:$C$1833,$R2,Data!$D$2:$D$1833,$S2,Data!$E$2:$E$1833,$E2,Data!$F$2:$F$1833,G$1,Data!$H$2:$H$1833,1) -> 2 | H2: =COUNTIFS(Data!$B$2:$B$1833,$Q2,Data!$C$2:$C$1833,$R2,Data!$D$2:$D$1833,$S2,Data!$E$2:$E$1833,$E2,Data!$F$2:$F$1833,H$1,Data!$H$2:$H$1833,1) -> 1 | I2: =COUNTIFS(Data!$B$2:$B$1833,$Q2,Data!$C$2:$C$1833,$R2,Data!$D$2:$D$1833,$S2,Data!$E$2:$E$1833,$E2,Data!$F$2:$F$1833,I$1,Data!$H$2:$H$1833,1) -> 1 | J2: =COUNTIFS(Data!$B$2:$B$1833,$Q2,Data!$C$2:$C$1833,$R2,Data!$D$2:$D$1833,$S2,Data!$E$2:$E$1833,$E2,Data!$F$2:$F$1833,J$1,Data!$H$2:$H$1833,1) -> 1 | K2: =COUNTIFS(Data!$B$2:$B$1833,$Q2,Data!$C$2:$C$1833,$R2,Data!$D$2:$D$1833,$S2,Data!$E$2:$E$1833,$E2,Data!$F$2:$F$1833,K$1,Data!$H$2:$H$1833,1) -> 1 | L2: =COUNTIFS(Data!$B$2:$B$1833,$Q2,Data!$C$2:$C$1833,$R2,Data!$D$2:$D$1833,$S2,Data!$E$2:$E$1833,$E2,Data!$F$2:$F$1833,L$1,Data!$H$2:$H$1833,1) -> 2 | M2: =COUNTIFS(Data!$B$2:$B$1833,$Q2,Data!$C$2:$C$1833,$R2,Data!$D$2:$D$1833,$S2,Data!$E$2:$E$1833,$E2,Data!$F$2:$F$1833,M$1,Data!$H$2:$H$1833,1) -> 1 | ... O2: =COUNTIFS(Data!$B$2:$B$1833,$Q2,Data!$C$2:$C$1833,$R2,Data!$D$2:$D$1833,$S2,Data!$E$2:$E$1833,$E2,Data!$F$2:$F$1833,O$1,Data!$H$2:$H$1833,1) -> 1 | P2: =SUM(F2:O2) -> 16 | Q2: Communicative language activities | R2: Reception | S2: Oral comprehension
A3: =IFERROR(INDEX(対訳マスタ!$C$2:$C$136,MATCH($Q3,対訳マスタ!$B$2:$B$136,0)),$Q3) -> コミュニケーション言語活動 | B3: =IF($R3="—","—",IFERROR(INDEX(対訳マスタ!$C$2:$C$136,MATCH($R3,対訳マスタ!$B$2:$B$136,0)),$R3)) -> 受容 | C3: =IF($S3="—","—",IFERROR(INDEX(対訳マスタ!$C$2:$C$136,MATCH($S3,対訳マスタ!$B$2:$B$136,0)),$S3)) -> 口頭理解（聞くこと） | D3: =IFERROR(INDEX(対訳マスタ!$C$2:$C$136,MATCH($E3,対訳マスタ!$B$2:$B$136,0)),$E3) -> 第三者どうしの会話の聞き取り | E3: Understanding conversation between other people | F3: =COUNTIFS(Data!$B$2:$B$1833,$Q3,Data!$C$2:$C$1833,$R3,Data!$D$2:$D$1833,$S3,Data!$E$2:$E$1833,$E3,Data!$F$2:$F$1833,F$1,Data!$H$2:$H$1833,1) -> 0 | G3: =COUNTIFS(Data!$B$2:$B$1833,$Q3,Data!$C$2:$C$1833,$R3,Data!$D$2:$D$1833,$S3,Data!$E$2:$E$1833,$E3,Data!$F$2:$F$1833,G$1,Data!$H$2:$H$1833,1) -> 2 | H3: =COUNTIFS(Data!$B$2:$B$1833,$Q3,Data!$C$2:$C$1833,$R3,Data!$D$2:$D$1833,$S3,Data!$E$2:$E$1833,$E3,Data!$F$2:$F$1833,H$1,Data!$H$2:$H$1833,1) -> 1 | I3: =COUNTIFS(Data!$B$2:$B$1833,$Q3,Data!$C$2:$C$1833,$R3,Data!$D$2:$D$1833,$S3,Data!$E$2:$E$1833,$E3,Data!$F$2:$F$1833,I$1,Data!$H$2:$H$1833,1) -> 2 | J3: =COUNTIFS(Data!$B$2:$B$1833,$Q3,Data!$C$2:$C$1833,$R3,Data!$D$2:$D$1833,$S3,Data!$E$2:$E$1833,$E3,Data!$F$2:$F$1833,J$1,Data!$H$2:$H$1833,1) -> 1 | K3: =COUNTIFS(Data!$B$2:$B$1833,$Q3,Data!$C$2:$C$1833,$R3,Data!$D$2:$D$1833,$S3,Data!$E$2:$E$1833,$E3,Data!$F$2:$F$1833,K$1,Data!$H$2:$H$1833,1) -> 1 | L3: =COUNTIFS(Data!$B$2:$B$1833,$Q3,Data!$C$2:$C$1833,$R3,Data!$D$2:$D$1833,$S3,Data!$E$2:$E$1833,$E3,Data!$F$2:$F$1833,L$1,Data!$H$2:$H$1833,1) -> 3 | M3: =COUNTIFS(Data!$B$2:$B$1833,$Q3,Data!$C$2:$C$1833,$R3,Data!$D$2:$D$1833,$S3,Data!$E$2:$E$1833,$E3,Data!$F$2:$F$1833,M$1,Data!$H$2:$H$1833,1) -> 1 | ... O3: =COUNTIFS(Data!$B$2:$B$1833,$Q3,Data!$C$2:$C$1833,$R3,Data!$D$2:$D$1833,$S3,Data!$E$2:$E$1833,$E3,Data!$F$2:$F$1833,O$1,Data!$H$2:$H$1833,1) -> 1 | P3: =SUM(F3:O3) -> 14 | Q3: Communicative language activities | R3: Reception | S3: Oral comprehension
A4: =IFERROR(INDEX(対訳マスタ!$C$2:$C$136,MATCH($Q4,対訳マスタ!$B$2:$B$136,0)),$Q4) -> コミュニケーション言語活動 | B4: =IF($R4="—","—",IFERROR(INDEX(対訳マスタ!$C$2:$C$136,MATCH($R4,対訳マスタ!$B$2:$B$136,0)),$R4)) -> 受容 | C4: =IF($S4="—","—",IFERROR(INDEX(対訳マスタ!$C$2:$C$136,MATCH($S4,対訳マスタ!$B$2:$B$136,0)),$S4)) -> 口頭理解（聞くこと） | D4: =IFERROR(INDEX(対訳マスタ!$C$2:$C$136,MATCH($E4,対訳マスタ!$B$2:$B$136,0)),$E4) -> 聴衆としての聞き取り（講演など） | E4: Understanding as a member of a live audience | F4: =COUNTIFS(Data!$B$2:$B$1833,$Q4,Data!$C$2:$C$1833,$R4,Data!$D$2:$D$1833,$S4,Data!$E$2:$E$1833,$E4,Data!$F$2:$F$1833,F$1,Data!$H$2:$H$1833,1) -> 0 | G4: =COUNTIFS(Data!$B$2:$B$1833,$Q4,Data!$C$2:$C$1833,$R4,Data!$D$2:$D$1833,$S4,Data!$E$2:$E$1833,$E4,Data!$F$2:$F$1833,G$1,Data!$H$2:$H$1833,1) -> 1 | H4: =COUNTIFS(Data!$B$2:$B$1833,$Q4,Data!$C$2:$C$1833,$R4,Data!$D$2:$D$1833,$S4,Data!$E$2:$E$1833,$E4,Data!$F$2:$F$1833,H$1,Data!$H$2:$H$1833,1) -> 2 | I4: =COUNTIFS(Data!$B$2:$B$1833,$Q4,Data!$C$2:$C$1833,$R4,Data!$D$2:$D$1833,$S4,Data!$E$2:$E$1833,$E4,Data!$F$2:$F$1833,I$1,Data!$H$2:$H$1833,1) -> 1 | J4: =COUNTIFS(Data!$B$2:$B$1833,$Q4,Data!$C$2:$C$1833,$R4,Data!$D$2:$D$1833,$S4,Data!$E$2:$E$1833,$E4,Data!$F$2:$F$1833,J$1,Data!$H$2:$H$1833,1) -> 3 | K4: =COUNTIFS(Data!$B$2:$B$1833,$Q4,Data!$C$2:$C$1833,$R4,Data!$D$2:$D$1833,$S4,Data!$E$2:$E$1833,$E4,Data!$F$2:$F$1833,K$1,Data!$H$2:$H$1833,1) -> 2 | L4: =COUNTIFS(Data!$B$2:$B$1833,$Q4,Data!$C$2:$C$1833,$R4,Data!$D$2:$D$1833,$S4,Data!$E$2:$E$1833,$E4,Data!$F$2:$F$1833,L$1,Data!$H$2:$H$1833,1) -> 3 | M4: =COUNTIFS(Data!$B$2:$B$1833,$Q4,Data!$C$2:$C$1833,$R4,Data!$D$2:$D$1833,$S4,Data!$E$2:$E$1833,$E4,Data!$F$2:$F$1833,M$1,Data!$H$2:$H$1833,1) -> 2 | ... O4: =COUNTIFS(Data!$B$2:$B$1833,$Q4,Data!$C$2:$C$1833,$R4,Data!$D$2:$D$1833,$S4,Data!$E$2:$E$1833,$E4,Data!$F$2:$F$1833,O$1,Data!$H$2:$H$1833,1) -> 3 | P4: =SUM(F4:O4) -> 18 | Q4: Communicative language activities | R4: Reception | S4: Oral comprehension
A5: =IFERROR(INDEX(対訳マスタ!$C$2:$C$136,MATCH($Q5,対訳マスタ!$B$2:$B$136,0)),$Q5) -> コミュニケーション言語活動 | B5: =IF($R5="—","—",IFERROR(INDEX(対訳マスタ!$C$2:$C$136,MATCH($R5,対訳マスタ!$B$2:$B$136,0)),$R5)) -> 受容 | C5: =IF($S5="—","—",IFERROR(INDEX(対訳マスタ!$C$2:$C$136,MATCH($S5,対訳マスタ!$B$2:$B$136,0)),$S5)) -> 口頭理解（聞くこと） | D5: =IFERROR(INDEX(対訳マスタ!$C$2:$C$136,MATCH($E5,対訳マスタ!$B$2:$B$136,0)),$E5) -> アナウンス・指示の聞き取り | E5: Understanding announcements and instructions | F5: =COUNTIFS(Data!$B$2:$B$1833,$Q5,Data!$C$2:$C$1833,$R5,Data!$D$2:$D$1833,$S5,Data!$E$2:$E$1833,$E5,Data!$F$2:$F$1833,F$1,Data!$H$2:$H$1833,1) -> 1 | G5: =COUNTIFS(Data!$B$2:$B$1833,$Q5,Data!$C$2:$C$1833,$R5,Data!$D$2:$D$1833,$S5,Data!$E$2:$E$1833,$E5,Data!$F$2:$F$1833,G$1,Data!$H$2:$H$1833,1) -> 3 | H5: =COUNTIFS(Data!$B$2:$B$1833,$Q5,Data!$C$2:$C$1833,$R5,Data!$D$2:$D$1833,$S5,Data!$E$2:$E$1833,$E5,Data!$F$2:$F$1833,H$1,Data!$H$2:$H$1833,1) -> 3 | I5: =COUNTIFS(Data!$B$2:$B$1833,$Q5,Data!$C$2:$C$1833,$R5,Data!$D$2:$D$1833,$S5,Data!$E$2:$E$1833,$E5,Data!$F$2:$F$1833,I$1,Data!$H$2:$H$1833,1) -> 2 | J5: =COUNTIFS(Data!$B$2:$B$1833,$Q5,Data!$C$2:$C$1833,$R5,Data!$D$2:$D$1833,$S5,Data!$E$2:$E$1833,$E5,Data!$F$2:$F$1833,J$1,Data!$H$2:$H$1833,1) -> 3 | K5: =COUNTIFS(Data!$B$2:$B$1833,$Q5,Data!$C$2:$C$1833,$R5,Data!$D$2:$D$1833,$S5,Data!$E$2:$E$1833,$E5,Data!$F$2:$F$1833,K$1,Data!$H$2:$H$1833,1) -> 0 | L5: =COUNTIFS(Data!$B$2:$B$1833,$Q5,Data!$C$2:$C$1833,$R5,Data!$D$2:$D$1833,$S5,Data!$E$2:$E$1833,$E5,Data!$F$2:$F$1833,L$1,Data!$H$2:$H$1833,1) -> 2 | M5: =COUNTIFS(Data!$B$2:$B$1833,$Q5,Data!$C$2:$C$1833,$R5,Data!$D$2:$D$1833,$S5,Data!$E$2:$E$1833,$E5,Data!$F$2:$F$1833,M$1,Data!$H$2:$H$1833,1) -> 0 | ... O5: =COUNTIFS(Data!$B$2:$B$1833,$Q5,Data!$C$2:$C$1833,$R5,Data!$D$2:$D$1833,$S5,Data!$E$2:$E$1833,$E5,Data!$F$2:$F$1833,O$1,Data!$H$2:$H$1833,1) -> 0 | P5: =SUM(F5:O5) -> 16 | Q5: Communicative language activities | R5: Reception | S5: Oral comprehension
A6: =IFERROR(INDEX(対訳マスタ!$C$2:$C$136,MATCH($Q6,対訳マスタ!$B$2:$B$136,0)),$Q6) -> コミュニケーション言語活動 | B6: =IF($R6="—","—",IFERROR(INDEX(対訳マスタ!$C$2:$C$136,MATCH($R6,対訳マスタ!$B$2:$B$136,0)),$R6)) -> 受容 | C6: =IF($S6="—","—",IFERROR(INDEX(対訳マスタ!$C$2:$C$136,MATCH($S6,対訳マスタ!$B$2:$B$136,0)),$S6)) -> 口頭理解（聞くこと） | D6: =IFERROR(INDEX(対訳マスタ!$C$2:$C$136,MATCH($E6,対訳マスタ!$B$2:$B$136,0)),$E6) -> 音声メディア・録音の聞き取り | E6: Understanding audio (or signed) media and recordings | F6: =COUNTIFS(Data!$B$2:$B$1833,$Q6,Data!$C$2:$C$1833,$R6,Data!$D$2:$D$1833,$S6,Data!$E$2:$E$1833,$E6,Data!$F$2:$F$1833,F$1,Data!$H$2:$H$1833,1) -> 1 | G6: =COUNTIFS(Data!$B$2:$B$1833,$Q6,Data!$C$2:$C$1833,$R6,Data!$D$2:$D$1833,$S6,Data!$E$2:$E$1833,$E6,Data!$F$2:$F$1833,G$1,Data!$H$2:$H$1833,1) -> 1 | H6: =COUNTIFS(Data!$B$2:$B$1833,$Q6,Data!$C$2:$C$1833,$R6,Data!$D$2:$D$1833,$S6,Data!$E$2:$E$1833,$E6,Data!$F$2:$F$1833,H$1,Data!$H$2:$H$1833,1) -> 3 | I6: =COUNTIFS(Data!$B$2:$B$1833,$Q6,Data!$C$2:$C$1833,$R6,Data!$D$2:$D$1833,$S6,Data!$E$2:$E$1833,$E6,Data!$F$2:$F$1833,I$1,Data!$H$2:$H$1833,1) -> 2 | J6: =COUNTIFS(Data!$B$2:$B$1833,$Q6,Data!$C$2:$C$1833,$R6,Data!$D$2:$D$1833,$S6,Data!$E$2:$E$1833,$E6,Data!$F$2:$F$1833,J$1,Data!$H$2:$H$1833,1) -> 2 | K6: =COUNTIFS(Data!$B$2:$B$1833,$Q6,Data!$C$2:$C$1833,$R6,Data!$D$2:$D$1833,$S6,Data!$E$2:$E$1833,$E6,Data!$F$2:$F$1833,K$1,Data!$H$2:$H$1833,1) -> 1 | L6: =COUNTIFS(Data!$B$2:$B$1833,$Q6,Data!$C$2:$C$1833,$R6,Data!$D$2:$D$1833,$S6,Data!$E$2:$E$1833,$E6,Data!$F$2:$F$1833,L$1,Data!$H$2:$H$1833,1) -> 1 | M6: =COUNTIFS(Data!$B$2:$B$1833,$Q6,Data!$C$2:$C$1833,$R6,Data!$D$2:$D$1833,$S6,Data!$E$2:$E$1833,$E6,Data!$F$2:$F$1833,M$1,Data!$H$2:$H$1833,1) -> 1 | ... O6: =COUNTIFS(Data!$B$2:$B$1833,$Q6,Data!$C$2:$C$1833,$R6,Data!$D$2:$D$1833,$S6,Data!$E$2:$E$1833,$E6,Data!$F$2:$F$1833,O$1,Data!$H$2:$H$1833,1) -> 0 | P6: =SUM(F6:O6) -> 13 | Q6: Communicative language activities | R6: Reception | S6: Oral comprehension
A7: =IFERROR(INDEX(対訳マスタ!$C$2:$C$136,MATCH($Q7,対訳マスタ!$B$2:$B$136,0)),$Q7) -> コミュニケーション言語活動 | B7: =IF($R7="—","—",IFERROR(INDEX(対訳マスタ!$C$2:$C$136,MATCH($R7,対訳マスタ!$B$2:$B$136,0)),$R7)) -> 受容 | C7: =IF($S7="—","—",IFERROR(INDEX(対訳マスタ!$C$2:$C$136,MATCH($S7,対訳マスタ!$B$2:$B$136,0)),$S7)) -> 視聴覚理解 | D7: =IFERROR(INDEX(対訳マスタ!$C$2:$C$136,MATCH($E7,対訳マスタ!$B$2:$B$136,0)),$E7) -> テレビ・映画・動画の視聴 | E7: Watching TV, film and video | F7: =COUNTIFS(Data!$B$2:$B$1833,$Q7,Data!$C$2:$C$1833,$R7,Data!$D$2:$D$1833,$S7,Data!$E$2:$E$1833,$E7,Data!$F$2:$F$1833,F$1,Data!$H$2:$H$1833,1) -> 1 | G7: =COUNTIFS(Data!$B$2:$B$1833,$Q7,Data!$C$2:$C$1833,$R7,Data!$D$2:$D$1833,$S7,Data!$E$2:$E$1833,$E7,Data!$F$2:$F$1833,G$1,Data!$H$2:$H$1833,1) -> 1 | H7: =COUNTIFS(Data!$B$2:$B$1833,$Q7,Data!$C$2:$C$1833,$R7,Data!$D$2:$D$1833,$S7,Data!$E$2:$E$1833,$E7,Data!$F$2:$F$1833,H$1,Data!$H$2:$H$1833,1) -> 1 | I7: =COUNTIFS(Data!$B$2:$B$1833,$Q7,Data!$C$2:$C$1833,$R7,Data!$D$2:$D$1833,$S7,Data!$E$2:$E$1833,$E7,Data!$F$2:$F$1833,I$1,Data!$H$2:$H$1833,1) -> 2 | J7: =COUNTIFS(Data!$B$2:$B$1833,$Q7,Data!$C$2:$C$1833,$R7,Data!$D$2:$D$1833,$S7,Data!$E$2:$E$1833,$E7,Data!$F$2:$F$1833,J$1,Data!$H$2:$H$1833,1) -> 2 | K7: =COUNTIFS(Data!$B$2:$B$1833,$Q7,Data!$C$2:$C$1833,$R7,Data!$D$2:$D$1833,$S7,Data!$E$2:$E$1833,$E7,Data!$F$2:$F$1833,K$1,Data!$H$2:$H$1833,1) -> 1 | L7: =COUNTIFS(Data!$B$2:$B$1833,$Q7,Data!$C$2:$C$1833,$R7,Data!$D$2:$D$1833,$S7,Data!$E$2:$E$1833,$E7,Data!$F$2:$F$1833,L$1,Data!$H$2:$H$1833,1) -> 2 | M7: =COUNTIFS(Data!$B$2:$B$1833,$Q7,Data!$C$2:$C$1833,$R7,Data!$D$2:$D$1833,$S7,Data!$E$2:$E$1833,$E7,Data!$F$2:$F$1833,M$1,Data!$H$2:$H$1833,1) -> 1 | ... O7: =COUNTIFS(Data!$B$2:$B$1833,$Q7,Data!$C$2:$C$1833,$R7,Data!$D$2:$D$1833,$S7,Data!$E$2:$E$1833,$E7,Data!$F$2:$F$1833,O$1,Data!$H$2:$H$1833,1) -> 0 | P7: =SUM(F7:O7) -> 14 | Q7: Communicative language activities | R7: Reception | S7: Audio-visual comprehension
A8: =IFERROR(INDEX(対訳マスタ!$C$2:$C$136,MATCH($Q8,対訳マスタ!$B$2:$B$136,0)),$Q8) -> コミュニケーション言語活動 | B8: =IF($R8="—","—",IFERROR(INDEX(対訳マスタ!$C$2:$C$136,MATCH($R8,対訳マスタ!$B$2:$B$136,0)),$R8)) -> 受容 | C8: =IF($S8="—","—",IFERROR(INDEX(対訳マスタ!$C$2:$C$136,MATCH($S8,対訳マスタ!$B$2:$B$136,0)),$S8)) -> 読解（読むこと） | D8: =IFERROR(INDEX(対訳マスタ!$C$2:$C$136,MATCH($E8,対訳マスタ!$B$2:$B$136,0)),$E8) -> 読解（総合） | E8: Overall reading comprehension | F8: =COUNTIFS(Data!$B$2:$B$1833,$Q8,Data!$C$2:$C$1833,$R8,Data!$D$2:$D$1833,$S8,Data!$E$2:$E$1833,$E8,Data!$F$2:$F$1833,F$1,Data!$H$2:$H$1833,1) -> 1 | G8: =COUNTIFS(Data!$B$2:$B$1833,$Q8,Data!$C$2:$C$1833,$R8,Data!$D$2:$D$1833,$S8,Data!$E$2:$E$1833,$E8,Data!$F$2:$F$1833,G$1,Data!$H$2:$H$1833,1) -> 1 | H8: =COUNTIFS(Data!$B$2:$B$1833,$Q8,Data!$C$2:$C$1833,$R8,Data!$D$2:$D$1833,$S8,Data!$E$2:$E$1833,$E8,Data!$F$2:$F$1833,H$1,Data!$H$2:$H$1833,1) -> 1 | I8: =COUNTIFS(Data!$B$2:$B$1833,$Q8,Data!$C$2:$C$1833,$R8,Data!$D$2:$D$1833,$S8,Data!$E$2:$E$1833,$E8,Data!$F$2:$F$1833,I$1,Data!$H$2:$H$1833,1) -> 1 | J8: =COUNTIFS(Data!$B$2:$B$1833,$Q8,Data!$C$2:$C$1833,$R8,Data!$D$2:$D$1833,$S8,Data!$E$2:$E$1833,$E8,Data!$F$2:$F$1833,J$1,Data!$H$2:$H$1833,1) -> 1 | K8: =COUNTIFS(Data!$B$2:$B$1833,$Q8,Data!$C$2:$C$1833,$R8,Data!$D$2:$D$1833,$S8,Data!$E$2:$E$1833,$E8,Data!$F$2:$F$1833,K$1,Data!$H$2:$H$1833,1) -> 0 | L8: =COUNTIFS(Data!$B$2:$B$1833,$Q8,Data!$C$2:$C$1833,$R8,Data!$D$2:$D$1833,$S8,Data!$E$2:$E$1833,$E8,Data!$F$2:$F$1833,L$1,Data!$H$2:$H$1833,1) -> 1 | M8: =COUNTIFS(Data!$B$2:$B$1833,$Q8,Data!$C$2:$C$1833,$R8,Data!$D$2:$D$1833,$S8,Data!$E$2:$E$1833,$E8,Data!$F$2:$F$1833,M$1,Data!$H$2:$H$1833,1) -> 0 | ... O8: =COUNTIFS(Data!$B$2:$B$1833,$Q8,Data!$C$2:$C$1833,$R8,Data!$D$2:$D$1833,$S8,Data!$E$2:$E$1833,$E8,Data!$F$2:$F$1833,O$1,Data!$H$2:$H$1833,1) -> 2 | P8: =SUM(F8:O8) -> 10 | Q8: Communicative language activities | R8: Reception | S8: Reading comprehension
A9: =IFERROR(INDEX(対訳マスタ!$C$2:$C$136,MATCH($Q9,対訳マスタ!$B$2:$B$136,0)),$Q9) -> コミュニケーション言語活動 | B9: =IF($R9="—","—",IFERROR(INDEX(対訳マスタ!$C$2:$C$136,MATCH($R9,対訳マスタ!$B$2:$B$136,0)),$R9)) -> 受容 | C9: =IF($S9="—","—",IFERROR(INDEX(対訳マスタ!$C$2:$C$136,MATCH($S9,対訳マスタ!$B$2:$B$136,0)),$S9)) -> 読解（読むこと） | D9: =IFERROR(INDEX(対訳マスタ!$C$2:$C$136,MATCH($E9,対訳マスタ!$B$2:$B$136,0)),$E9) -> 手紙・メールを読む | E9: Reading correspondence | F9: =COUNTIFS(Data!$B$2:$B$1833,$Q9,Data!$C$2:$C$1833,$R9,Data!$D$2:$D$1833,$S9,Data!$E$2:$E$1833,$E9,Data!$F$2:$F$1833,F$1,Data!$H$2:$H$1833,1) -> 2 | G9: =COUNTIFS(Data!$B$2:$B$1833,$Q9,Data!$C$2:$C$1833,$R9,Data!$D$2:$D$1833,$S9,Data!$E$2:$E$1833,$E9,Data!$F$2:$F$1833,G$1,Data!$H$2:$H$1833,1) -> 2 | H9: =COUNTIFS(Data!$B$2:$B$1833,$Q9,Data!$C$2:$C$1833,$R9,Data!$D$2:$D$1833,$S9,Data!$E$2:$E$1833,$E9,Data!$F$2:$F$1833,H$1,Data!$H$2:$H$1833,1) -> 2 | I9: =COUNTIFS(Data!$B$2:$B$1833,$Q9,Data!$C$2:$C$1833,$R9,Data!$D$2:$D$1833,$S9,Data!$E$2:$E$1833,$E9,Data!$F$2:$F$1833,I$1,Data!$H$2:$H$1833,1) -> 2 | J9: =COUNTIFS(Data!$B$2:$B$1833,$Q9,Data!$C$2:$C$1833,$R9,Data!$D$2:$D$1833,$S9,Data!$E$2:$E$1833,$E9,Data!$F$2:$F$1833,J$1,Data!$H$2:$H$1833,1) -> 3 | K9: =COUNTIFS(Data!$B$2:$B$1833,$Q9,Data!$C$2:$C$1833,$R9,Data!$D$2:$D$1833,$S9,Data!$E$2:$E$1833,$E9,Data!$F$2:$F$1833,K$1,Data!$H$2:$H$1833,1) -> 1 | L9: =COUNTIFS(Data!$B$2:$B$1833,$Q9,Data!$C$2:$C$1833,$R9,Data!$D$2:$D$1833,$S9,Data!$E$2:$E$1833,$E9,Data!$F$2:$F$1833,L$1,Data!$H$2:$H$1833,1) -> 2 | M9: =COUNTIFS(Data!$B$2:$B$1833,$Q9,Data!$C$2:$C$1833,$R9,Data!$D$2:$D$1833,$S9,Data!$E$2:$E$1833,$E9,Data!$F$2:$F$1833,M$1,Data!$H$2:$H$1833,1) -> 0 | ... O9: =COUNTIFS(Data!$B$2:$B$1833,$Q9,Data!$C$2:$C$1833,$R9,Data!$D$2:$D$1833,$S9,Data!$E$2:$E$1833,$E9,Data!$F$2:$F$1833,O$1,Data!$H$2:$H$1833,1) -> 1 | P9: =SUM(F9:O9) -> 18 | Q9: Communicative language activities | R9: Reception | S9: Reading comprehension
A10: =IFERROR(INDEX(対訳マスタ!$C$2:$C$136,MATCH($Q10,対訳マスタ!$B$2:$B$136,0)),$Q10) -> コミュニケーション言語活動 | B10: =IF($R10="—","—",IFERROR(INDEX(対訳マスタ!$C$2:$C$136,MATCH($R10,対訳マスタ!$B$2:$B$136,0)),$R10)) -> 受容 | C10: =IF($S10="—","—",IFERROR(INDEX(対訳マスタ!$C$2:$C$136,MATCH($S10,対訳マスタ!$B$2:$B$136,0)),$S10)) -> 読解（読むこと） | D10: =IFERROR(INDEX(対訳マスタ!$C$2:$C$136,MATCH($E10,対訳マスタ!$B$2:$B$136,0)),$E10) -> 目当ての情報を探す読み（拾い読み） | E10: Reading for orientation | F10: =COUNTIFS(Data!$B$2:$B$1833,$Q10,Data!$C$2:$C$1833,$R10,Data!$D$2:$D$1833,$S10,Data!$E$2:$E$1833,$E10,Data!$F$2:$F$1833,F$1,Data!$H$2:$H$1833,1) -> 2 | G10: =COUNTIFS(Data!$B$2:$B$1833,$Q10,Data!$C$2:$C$1833,$R10,Data!$D$2:$D$1833,$S10,Data!$E$2:$E$1833,$E10,Data!$F$2:$F$1833,G$1,Data!$H$2:$H$1833,1) -> 4 | H10: =COUNTIFS(Data!$B$2:$B$1833,$Q10,Data!$C$2:$C$1833,$R10,Data!$D$2:$D$1833,$S10,Data!$E$2:$E$1833,$E10,Data!$F$2:$F$1833,H$1,Data!$H$2:$H$1833,1) -> 3 | I10: =COUNTIFS(Data!$B$2:$B$1833,$Q10,Data!$C$2:$C$1833,$R10,Data!$D$2:$D$1833,$S10,Data!$E$2:$E$1833,$E10,Data!$F$2:$F$1833,I$1,Data!$H$2:$H$1833,1) -> 2 | J10: =COUNTIFS(Data!$B$2:$B$1833,$Q10,Data!$C$2:$C$1833,$R10,Data!$D$2:$D$1833,$S10,Data!$E$2:$E$1833,$E10,Data!$F$2:$F$1833,J$1,Data!$H$2:$H$1833,1) -> 4 | K10: =COUNTIFS(Data!$B$2:$B$1833,$Q10,Data!$C$2:$C$1833,$R10,Data!$D$2:$D$1833,$S10,Data!$E$2:$E$1833,$E10,Data!$F$2:$F$1833,K$1,Data!$H$2:$H$1833,1) -> 2 | L10: =COUNTIFS(Data!$B$2:$B$1833,$Q10,Data!$C$2:$C$1833,$R10,Data!$D$2:$D$1833,$S10,Data!$E$2:$E$1833,$E10,Data!$F$2:$F$1833,L$1,Data!$H$2:$H$1833,1) -> 2 | M10: =COUNTIFS(Data!$B$2:$B$1833,$Q10,Data!$C$2:$C$1833,$R10,Data!$D$2:$D$1833,$S10,Data!$E$2:$E$1833,$E10,Data!$F$2:$F$1833,M$1,Data!$H$2:$H$1833,1) -> 1 | ... O10: =COUNTIFS(Data!$B$2:$B$1833,$Q10,Data!$C$2:$C$1833,$R10,Data!$D$2:$D$1833,$S10,Data!$E$2:$E$1833,$E10,Data!$F$2:$F$1833,O$1,Data!$H$2:$H$1833,1) -> 0 | P10: =SUM(F10:O10) -> 20 | Q10: Communicative language activities | R10: Reception | S10: Reading comprehension
A11: =IFERROR(INDEX(対訳マスタ!$C$2:$C$136,MATCH($Q11,対訳マスタ!$B$2:$B$136,0)),$Q11) -> コミュニケーション言語活動 | B11: =IF($R11="—","—",IFERROR(INDEX(対訳マスタ!$C$2:$C$136,MATCH($R11,対訳マスタ!$B$2:$B$136,0)),$R11)) -> 受容 | C11: =IF($S11="—","—",IFERROR(INDEX(対訳マスタ!$C$2:$C$136,MATCH($S11,対訳マスタ!$B$2:$B$136,0)),$S11)) -> 読解（読むこと） | D11: =IFERROR(INDEX(対訳マスタ!$C$2:$C$136,MATCH($E11,対訳マスタ!$B$2:$B$136,0)),$E11) -> 情報・論旨の読み取り | E11: Reading for information and argument | F11: =COUNTIFS(Data!$B$2:$B$1833,$Q11,Data!$C$2:$C$1833,$R11,Data!$D$2:$D$1833,$S11,Data!$E$2:$E$1833,$E11,Data!$F$2:$F$1833,F$1,Data!$H$2:$H$1833,1) -> 1 | G11: =COUNTIFS(Data!$B$2:$B$1833,$Q11,Data!$C$2:$C$1833,$R11,Data!$D$2:$D$1833,$S11,Data!$E$2:$E$1833,$E11,Data!$F$2:$F$1833,G$1,Data!$H$2:$H$1833,1) -> 2 | H11: =COUNTIFS(Data!$B$2:$B$1833,$Q11,Data!$C$2:$C$1833,$R11,Data!$D$2:$D$1833,$S11,Data!$E$2:$E$1833,$E11,Data!$F$2:$F$1833,H$1,Data!$H$2:$H$1833,1) -> 5 | I11: =COUNTIFS(Data!$B$2:$B$1833,$Q11,Data!$C$2:$C$1833,$R11,Data!$D$2:$D$1833,$S11,Data!$E$2:$E$1833,$E11,Data!$F$2:$F$1833,I$1,Data!$H$2:$H$1833,1) -> 4 | J11: =COUNTIFS(Data!$B$2:$B$1833,$Q11,Data!$C$2:$C$1833,$R11,Data!$D$2:$D$1833,$S11,Data!$E$2:$E$1833,$E11,Data!$F$2:$F$1833,J$1,Data!$H$2:$H$1833,1) -> 3 | K11: =COUNTIFS(Data!$B$2:$B$1833,$Q11,Data!$C$2:$C$1833,$R11,Data!$D$2:$D$1833,$S11,Data!$E$2:$E$1833,$E11,Data!$F$2:$F$1833,K$1,Data!$H$2:$H$1833,1) -> 4 | L11: =COUNTIFS(Data!$B$2:$B$1833,$Q11,Data!$C$2:$C$1833,$R11,Data!$D$2:$D$1833,$S11,Data!$E$2:$E$1833,$E11,Data!$F$2:$F$1833,L$1,Data!$H$2:$H$1833,1) -> 3 | M11: =COUNTIFS(Data!$B$2:$B$1833,$Q11,Data!$C$2:$C$1833,$R11,Data!$D$2:$D$1833,$S11,Data!$E$2:$E$1833,$E11,Data!$F$2:$F$1833,M$1,Data!$H$2:$H$1833,1) -> 2 | ... O11: =COUNTIFS(Data!$B$2:$B$1833,$Q11,Data!$C$2:$C$1833,$R11,Data!$D$2:$D$1833,$S11,Data!$E$2:$E$1833,$E11,Data!$F$2:$F$1833,O$1,Data!$H$2:$H$1833,1) -> 1 | P11: =SUM(F11:O11) -> 26 | Q11: Communicative language activities | R11: Reception | S11: Reading comprehension
A12: =IFERROR(INDEX(対訳マスタ!$C$2:$C$136,MATCH($Q12,対訳マスタ!$B$2:$B$136,0)),$Q12) -> コミュニケーション言語活動 | B12: =IF($R12="—","—",IFERROR(INDEX(対訳マスタ!$C$2:$C$136,MATCH($R12,対訳マスタ!$B$2:$B$136,0)),$R12)) -> 受容 | C12: =IF($S12="—","—",IFERROR(INDEX(対訳マスタ!$C$2:$C$136,MATCH($S12,対訳マスタ!$B$2:$B$136,0)),$S12)) -> 読解（読むこと） | D12: =IFERROR(INDEX(対訳マスタ!$C$2:$C$136,MATCH($E12,対訳マスタ!$B$2:$B$136,0)),$E12) -> 説明書・指示を読む | E12: Reading instructions | F12: =COUNTIFS(Data!$B$2:$B$1833,$Q12,Data!$C$2:$C$1833,$R12,Data!$D$2:$D$1833,$S12,Data!$E$2:$E$1833,$E12,Data!$F$2:$F$1833,F$1,Data!$H$2:$H$1833,1) -> 1 | G12: =COUNTIFS(Data!$B$2:$B$1833,$Q12,Data!$C$2:$C$1833,$R12,Data!$D$2:$D$1833,$S12,Data!$E$2:$E$1833,$E12,Data!$F$2:$F$1833,G$1,Data!$H$2:$H$1833,1) -> 1 | H12: =COUNTIFS(Data!$B$2:$B$1833,$Q12,Data!$C$2:$C$1833,$R12,Data!$D$2:$D$1833,$S12,Data!$E$2:$E$1833,$E12,Data!$F$2:$F$1833,H$1,Data!$H$2:$H$1833,1) -> 4 | I12: =COUNTIFS(Data!$B$2:$B$1833,$Q12,Data!$C$2:$C$1833,$R12,Data!$D$2:$D$1833,$S12,Data!$E$2:$E$1833,$E12,Data!$F$2:$F$1833,I$1,Data!$H$2:$H$1833,1) -> 2 | J12: =COUNTIFS(Data!$B$2:$B$1833,$Q12,Data!$C$2:$C$1833,$R12,Data!$D$2:$D$1833,$S12,Data!$E$2:$E$1833,$E12,Data!$F$2:$F$1833,J$1,Data!$H$2:$H$1833,1) -> 3 | K12: =COUNTIFS(Data!$B$2:$B$1833,$Q12,Data!$C$2:$C$1833,$R12,Data!$D$2:$D$1833,$S12,Data!$E$2:$E$1833,$E12,Data!$F$2:$F$1833,K$1,Data!$H$2:$H$1833,1) -> 1 | L12: =COUNTIFS(Data!$B$2:$B$1833,$Q12,Data!$C$2:$C$1833,$R12,Data!$D$2:$D$1833,$S12,Data!$E$2:$E$1833,$E12,Data!$F$2:$F$1833,L$1,Data!$H$2:$H$1833,1) -> 1 | M12: =COUNTIFS(Data!$B$2:$B$1833,$Q12,Data!$C$2:$C$1833,$R12,Data!$D$2:$D$1833,$S12,Data!$E$2:$E$1833,$E12,Data!$F$2:$F$1833,M$1,Data!$H$2:$H$1833,1) -> 0 | ... O12: =COUNTIFS(Data!$B$2:$B$1833,$Q12,Data!$C$2:$C$1833,$R12,Data!$D$2:$D$1833,$S12,Data!$E$2:$E$1833,$E12,Data!$F$2:$F$1833,O$1,Data!$H$2:$H$1833,1) -> 0 | P12: =SUM(F12:O12) -> 14 | Q12: Communicative language activities | R12: Reception | S12: Reading comprehension
A13: =IFERROR(INDEX(対訳マスタ!$C$2:$C$136,MATCH($Q13,対訳マスタ!$B$2:$B$136,0)),$Q13) -> コミュニケーション言語活動 | B13: =IF($R13="—","—",IFERROR(INDEX(対訳マスタ!$C$2:$C$136,MATCH($R13,対訳マスタ!$B$2:$B$136,0)),$R13)) -> 受容 | C13: =IF($S13="—","—",IFERROR(INDEX(対訳マスタ!$C$2:$C$136,MATCH($S13,対訳マスタ!$B$2:$B$136,0)),$S13)) -> 読解（読むこと） | D13: =IFERROR(INDEX(対訳マスタ!$C$2:$C$136,MATCH($E13,対訳マスタ!$B$2:$B$136,0)),$E13) -> 娯楽としての読書 | E13: Reading as a leisure activity | F13: =COUNTIFS(Data!$B$2:$B$1833,$Q13,Data!$C$2:$C$1833,$R13,Data!$D$2:$D$1833,$S13,Data!$E$2:$E$1833,$E13,Data!$F$2:$F$1833,F$1,Data!$H$2:$H$1833,1) -> 0 | G13: =COUNTIFS(Data!$B$2:$B$1833,$Q13,Data!$C$2:$C$1833,$R13,Data!$D$2:$D$1833,$S13,Data!$E$2:$E$1833,$E13,Data!$F$2:$F$1833,G$1,Data!$H$2:$H$1833,1) -> 2 | H13: =COUNTIFS(Data!$B$2:$B$1833,$Q13,Data!$C$2:$C$1833,$R13,Data!$D$2:$D$1833,$S13,Data!$E$2:$E$1833,$E13,Data!$F$2:$F$1833,H$1,Data!$H$2:$H$1833,1) -> 4 | I13: =COUNTIFS(Data!$B$2:$B$1833,$Q13,Data!$C$2:$C$1833,$R13,Data!$D$2:$D$1833,$S13,Data!$E$2:$E$1833,$E13,Data!$F$2:$F$1833,I$1,Data!$H$2:$H$1833,1) -> 2 | J13: =COUNTIFS(Data!$B$2:$B$1833,$Q13,Data!$C$2:$C$1833,$R13,Data!$D$2:$D$1833,$S13,Data!$E$2:$E$1833,$E13,Data!$F$2:$F$1833,J$1,Data!$H$2:$H$1833,1) -> 3 | K13: =COUNTIFS(Data!$B$2:$B$1833,$Q13,Data!$C$2:$C$1833,$R13,Data!$D$2:$D$1833,$S13,Data!$E$2:$E$1833,$E13,Data!$F$2:$F$1833,K$1,Data!$H$2:$H$1833,1) -> 2 | L13: =COUNTIFS(Data!$B$2:$B$1833,$Q13,Data!$C$2:$C$1833,$R13,Data!$D$2:$D$1833,$S13,Data!$E$2:$E$1833,$E13,Data!$F$2:$F$1833,L$1,Data!$H$2:$H$1833,1) -> 2 | M13: =COUNTIFS(Data!$B$2:$B$1833,$Q13,Data!$C$2:$C$1833,$R13,Data!$D$2:$D$1833,$S13,Data!$E$2:$E$1833,$E13,Data!$F$2:$F$1833,M$1,Data!$H$2:$H$1833,1) -> 0 | ... O13: =COUNTIFS(Data!$B$2:$B$1833,$Q13,Data!$C$2:$C$1833,$R13,Data!$D$2:$D$1833,$S13,Data!$E$2:$E$1833,$E13,Data!$F$2:$F$1833,O$1,Data!$H$2:$H$1833,1) -> 1 | P13: =SUM(F13:O13) -> 18 | Q13: Communicative language activities | R13: Reception | S13: Reading comprehension
... A100: =IFERROR(INDEX(対訳マスタ!$C$2:$C$136,MATCH($Q100,対訳マスタ!$B$2:$B$136,0)),$Q100) -> 手話能力 | B100: =IF($R100="—","—",IFERROR(INDEX(対訳マスタ!$C$2:$C$136,MATCH($R100,対訳マスタ!$B$2:$B$136,0)),$R100)) -> — | C100: =IF($S100="—","—",IFERROR(INDEX(対訳マスタ!$C$2:$C$136,MATCH($S100,対訳マスタ!$B$2:$B$136,0)),$S100)) -> 語用能力 | D100: =IFERROR(INDEX(対訳マスタ!$C$2:$C$136,MATCH($E100,対訳マスタ!$B$2:$B$136,0)),$E100) -> 手話の流暢さ | E100: Signing fluency | F100: =COUNTIFS(Data!$B$2:$B$1833,$Q100,Data!$C$2:$C$1833,$R100,Data!$D$2:$D$1833,$S100,Data!$E$2:$E$1833,$E100,Data!$F$2:$F$1833,F$1,Data!$H$2:$H$1833,1) -> 0 | G100: =COUNTIFS(Data!$B$2:$B$1833,$Q100,Data!$C$2:$C$1833,$R100,Data!$D$2:$D$1833,$S100,Data!$E$2:$E$1833,$E100,Data!$F$2:$F$1833,G$1,Data!$H$2:$H$1833,1) -> 0 | H100: =COUNTIFS(Data!$B$2:$B$1833,$Q100,Data!$C$2:$C$1833,$R100,Data!$D$2:$D$1833,$S100,Data!$E$2:$E$1833,$E100,Data!$F$2:$F$1833,H$1,Data!$H$2:$H$1833,1) -> 1 | I100: =COUNTIFS(Data!$B$2:$B$1833,$Q100,Data!$C$2:$C$1833,$R100,Data!$D$2:$D$1833,$S100,Data!$E$2:$E$1833,$E100,Data!$F$2:$F$1833,I$1,Data!$H$2:$H$1833,1) -> 1 | J100: =COUNTIFS(Data!$B$2:$B$1833,$Q100,Data!$C$2:$C$1833,$R100,Data!$D$2:$D$1833,$S100,Data!$E$2:$E$1833,$E100,Data!$F$2:$F$1833,J$1,Data!$H$2:$H$1833,1) -> 2 | K100: =COUNTIFS(Data!$B$2:$B$1833,$Q100,Data!$C$2:$C$1833,$R100,Data!$D$2:$D$1833,$S100,Data!$E$2:$E$1833,$E100,Data!$F$2:$F$1833,K$1,Data!$H$2:$H$1833,1) -> 1 | L100: =COUNTIFS(Data!$B$2:$B$1833,$Q100,Data!$C$2:$C$1833,$R100,Data!$D$2:$D$1833,$S100,Data!$E$2:$E$1833,$E100,Data!$F$2:$F$1833,L$1,Data!$H$2:$H$1833,1) -> 4 | M100: =COUNTIFS(Data!$B$2:$B$1833,$Q100,Data!$C$2:$C$1833,$R100,Data!$D$2:$D$1833,$S100,Data!$E$2:$E$1833,$E100,Data!$F$2:$F$1833,M$1,Data!$H$2:$H$1833,1) -> 3 | ... O100: =COUNTIFS(Data!$B$2:$B$1833,$Q100,Data!$C$2:$C$1833,$R100,Data!$D$2:$D$1833,$S100,Data!$E$2:$E$1833,$E100,Data!$F$2:$F$1833,O$1,Data!$H$2:$H$1833,1) -> 0 | P100: =SUM(F100:O100) -> 15 | Q100: Signing competences | R100: — | S100: Pragmatic competence
D101: 総計 | F101: =SUM(F2:F100) -> 47 | G101: =SUM(G2:G100) -> 148 | H101: =SUM(H2:H100) -> 204 | I101: =SUM(I2:I100) -> 143 | J101: =SUM(J2:J100) -> 252 | K101: =SUM(K2:K100) -> 165 | L101: =SUM(L2:L100) -> 254 | M101: =SUM(M2:M100) -> 149 | ... P101: =SUM(P2:P100) -> 1712

Sheet スケール別実例
A1: スキーム | B1: モード | C1: 活動・方略・能力の種別 | D1: スケール（作業訳） | E1: Scale（原文） | F1: レベル | G1: 記述文数 | H1: 例No. | I1: 例：Descriptor（英文） | J1: 例：和訳（作業訳） | L1: EN:Scheme | M1: EN:Mode | N1: EN:Activity | O1: EN:Scale
A2: =IFERROR(INDEX(対訳マスタ!$C$2:$C$136,MATCH($L2,対訳マスタ!$B$2:$B$136,0)),$L2) -> コミュニケーション言語活動 | B2: =IF($M2="—","—",IFERROR(INDEX(対訳マスタ!$C$2:$C$136,MATCH($M2,対訳マスタ!$B$2:$B$136,0)),$M2)) -> 受容 | C2: =IF($N2="—","—",IFERROR(INDEX(対訳マスタ!$C$2:$C$136,MATCH($N2,対訳マスタ!$B$2:$B$136,0)),$N2)) -> 口頭理解（聞くこと） | D2: =IFERROR(INDEX(対訳マスタ!$C$2:$C$136,MATCH($O2,対訳マスタ!$B$2:$B$136,0)),$O2) -> 口頭理解（総合） | E2: Overall oral comprehension | F2: Pre-A1 | G2: =COUNTIFS(Data!$B$2:$B$1833,$L2,Data!$C$2:$C$1833,$M2,Data!$D$2:$D$1833,$N2,Data!$E$2:$E$1833,$O2,Data!$F$2:$F$1833,$F2,Data!$H$2:$H$1833,1) -> 3 | H2: 15 | I2: =INDEX(Data!$G$2:$G$1833,MATCH($H2,Data!$A$2:$A$1833,0)) -> Can recognise everyday, familiar words/signs, provided they are delivered clearly and slowly in a clearly defined, familiar everyday context. | J2: 日常の馴染みのある語であれば、明確に限定された身近な文脈の中で、明瞭にゆっくり示されれば認識できる。 | L2: Communicative language activities | M2: Reception | N2: Oral comprehension | O2: Overall oral comprehension
F3: A1 | G3: =COUNTIFS(Data!$B$2:$B$1833,$L3,Data!$C$2:$C$1833,$M3,Data!$D$2:$D$1833,$N3,Data!$E$2:$E$1833,$O3,Data!$F$2:$F$1833,$F3,Data!$H$2:$H$1833,1) -> 2 | H3: 12 | I3: =INDEX(Data!$G$2:$G$1833,MATCH($H3,Data!$A$2:$A$1833,0)) -> Can follow language which is very slow and carefully articulated, with long pauses for them to assimilate meaning. | J3: 非常にゆっくり注意深く発音され、意味を消化するための長い間が置かれれば、言葉についていける。 | L3: Communicative language activities | M3: Reception | N3: Oral comprehension | O3: Overall oral comprehension
F4: A2 | G4: =COUNTIFS(Data!$B$2:$B$1833,$L4,Data!$C$2:$C$1833,$M4,Data!$D$2:$D$1833,$N4,Data!$E$2:$E$1833,$O4,Data!$F$2:$F$1833,$F4,Data!$H$2:$H$1833,1) -> 1 | H4: 11 | I4: =INDEX(Data!$G$2:$G$1833,MATCH($H4,Data!$A$2:$A$1833,0)) -> Can understand phrases and expressions related to areas of most immediate priority (e.g. very basic personal and family information, shopping, local geography, employment), provided people articulate clearly and slowly. | J4: 最も差し迫った領域（ごく基本的な個人・家族情報、買い物、地元の地理、仕事など）に関わる句や表現を、明瞭にゆっくり話されれば理解できる。 | L4: Communicative language activities | M4: Reception | N4: Oral comprehension | O4: Overall oral comprehension
F5: A2+ | G5: =COUNTIFS(Data!$B$2:$B$1833,$L5,Data!$C$2:$C$1833,$M5,Data!$D$2:$D$1833,$N5,Data!$E$2:$E$1833,$O5,Data!$F$2:$F$1833,$F5,Data!$H$2:$H$1833,1) -> 1 | H5: 10 | I5: =INDEX(Data!$G$2:$G$1833,MATCH($H5,Data!$A$2:$A$1833,0)) -> Can understand enough to be able to meet needs of a concrete type, provided people articulate clearly and slowly. | J5: 明瞭にゆっくり話してもらえれば、具体的な必要を満たせる程度に理解できる。 | L5: Communicative language activities | M5: Reception | N5: Oral comprehension | O5: Overall oral comprehension
F6: B1 | G6: =COUNTIFS(Data!$B$2:$B$1833,$L6,Data!$C$2:$C$1833,$M6,Data!$D$2:$D$1833,$N6,Data!$E$2:$E$1833,$O6,Data!$F$2:$F$1833,$F6,Data!$H$2:$H$1833,1) -> 1 | H6: 9 | I6: =INDEX(Data!$G$2:$G$1833,MATCH($H6,Data!$A$2:$A$1833,0)) -> Can understand the main points made in clear standard language or a familiar variety on familiar matters regularly encountered at work, school, leisure, etc., including short narratives. | J6: 仕事・学校・余暇などで日常的に出会う身近な事柄について、明瞭な標準語か馴染みのある変種で話されれば、短い物語を含め要点を理解できる。 | L6: Communicative language activities | M6: Reception | N6: Oral comprehension | O6: Overall oral comprehension
F7: B1+ | G7: =COUNTIFS(Data!$B$2:$B$1833,$L7,Data!$C$2:$C$1833,$M7,Data!$D$2:$D$1833,$N7,Data!$E$2:$E$1833,$O7,Data!$F$2:$F$1833,$F7,Data!$H$2:$H$1833,1) -> 1 | H7: 8 | I7: =INDEX(Data!$G$2:$G$1833,MATCH($H7,Data!$A$2:$A$1833,0)) -> Can understand straightforward factual information about common everyday or job-related topics, identifying both general messages and specific details, provided people articulate clearly in a generally familiar variety. | J7: 日常や仕事に関わる一般的な話題について、馴染みのある変種で明瞭に発音されていれば、全体の趣旨と具体的詳細の両方を聞き取り、率直な事実情報を理解できる。 | L7: Communicative language activities | M7: Reception | N7: Oral comprehension | O7: Overall oral comprehension
F8: B2 | G8: =COUNTIFS(Data!$B$2:$B$1833,$L8,Data!$C$2:$C$1833,$M8,Data!$D$2:$D$1833,$N8,Data!$E$2:$E$1833,$O8,Data!$F$2:$F$1833,$F8,Data!$H$2:$H$1833,1) -> 2 | H8: 7 | I8: =INDEX(Data!$G$2:$G$1833,MATCH($H8,Data!$A$2:$A$1833,0)) -> Can follow extended discourse and complex lines of argument, provided the topic is reasonably familiar, and the direction of the argument is signposted by explicit markers. | J8: 話題がある程度身近で、議論の方向が明示的な標識で示されていれば、長い談話や複雑な論の展開を追える。 | L8: Communicative language activities | M8: Reception | N8: Oral comprehension | O8: Overall oral comprehension
F9: B2+ | G9: =COUNTIFS(Data!$B$2:$B$1833,$L9,Data!$C$2:$C$1833,$M9,Data!$D$2:$D$1833,$N9,Data!$E$2:$E$1833,$O9,Data!$F$2:$F$1833,$F9,Data!$H$2:$H$1833,1) -> 1 | H9: 5 | I9: =INDEX(Data!$G$2:$G$1833,MATCH($H9,Data!$A$2:$A$1833,0)) -> Can understand standard language or a familiar variety, live or broadcast, on both familiar and unfamiliar topics normally encountered in personal, social, academic or vocational life. Only extreme [auditory/visual] background noise, inadequate discourse structure and/or idiomatic usage influence the ability to understand. | J9: 標準語または馴染みのある変種であれば、個人・社会・学業・職業生活で普通に出会う話題について、身近でも未知でも、生でも放送でも理解できる。極端な雑音、不十分な談話構成、慣用表現の多用だけが理解力に影響する。 | L9: Communicative language activities | M9: Reception | N9: Oral comprehension | O9: Overall oral comprehension
F10: C1 | G10: =COUNTIFS(Data!$B$2:$B$1833,$L10,Data!$C$2:$C$1833,$M10,Data!$D$2:$D$1833,$N10,Data!$E$2:$E$1833,$O10,Data!$F$2:$F$1833,$F10,Data!$H$2:$H$1833,1) -> 3 | H10: 3 | I10: =INDEX(Data!$G$2:$G$1833,MATCH($H10,Data!$A$2:$A$1833,0)) -> Can recognise a wide range of idiomatic expressions and colloquialisms, appreciating register shifts. | J10: 幅広い慣用表現や口語表現を認識し、言語使用域（レジスター）の変化を感じ取れる。 | L10: Communicative language activities | M10: Reception | N10: Oral comprehension | O10: Overall oral comprehension
F11: C2 | G11: =COUNTIFS(Data!$B$2:$B$1833,$L11,Data!$C$2:$C$1833,$M11,Data!$D$2:$D$1833,$N11,Data!$E$2:$E$1833,$O11,Data!$F$2:$F$1833,$F11,Data!$H$2:$H$1833,1) -> 1 | H11: 1 | I11: =INDEX(Data!$G$2:$G$1833,MATCH($H11,Data!$A$2:$A$1833,0)) -> Can understand with ease virtually any kind of language, whether live or broadcast, delivered at fast natural speed. | J11: 生の発話でも放送でも、速い自然な速度で話されるほぼあらゆる種類の言葉を容易に理解できる。 | L11: Communicative language activities | M11: Reception | N11: Oral comprehension | O11: Overall oral comprehension
A12: =IFERROR(INDEX(対訳マスタ!$C$2:$C$136,MATCH($L12,対訳マスタ!$B$2:$B$136,0)),$L12) -> コミュニケーション言語活動 | B12: =IF($M12="—","—",IFERROR(INDEX(対訳マスタ!$C$2:$C$136,MATCH($M12,対訳マスタ!$B$2:$B$136,0)),$M12)) -> 受容 | C12: =IF($N12="—","—",IFERROR(INDEX(対訳マスタ!$C$2:$C$136,MATCH($N12,対訳マスタ!$B$2:$B$136,0)),$N12)) -> 口頭理解（聞くこと） | D12: =IFERROR(INDEX(対訳マスタ!$C$2:$C$136,MATCH($O12,対訳マスタ!$B$2:$B$136,0)),$O12) -> 第三者どうしの会話の聞き取り | E12: Understanding conversation between other people | F12: Pre-A1 | G12: =COUNTIFS(Data!$B$2:$B$1833,$L12,Data!$C$2:$C$1833,$M12,Data!$D$2:$D$1833,$N12,Data!$E$2:$E$1833,$O12,Data!$F$2:$F$1833,$F12,Data!$H$2:$H$1833,1) -> 0 | H12: — | I12: — | J12: — | L12: Communicative language activities | M12: Reception | N12: Oral comprehension | O12: Understanding conversation between other people
F13: A1 | G13: =COUNTIFS(Data!$B$2:$B$1833,$L13,Data!$C$2:$C$1833,$M13,Data!$D$2:$D$1833,$N13,Data!$E$2:$E$1833,$O13,Data!$F$2:$F$1833,$F13,Data!$H$2:$H$1833,1) -> 2 | H13: 29 | I13: =INDEX(Data!$G$2:$G$1833,MATCH($H13,Data!$A$2:$A$1833,0)) -> Can understand some expressions when people are discussing them, family, school, hobbies or surroundings, provided the delivery is slow and clear. | J13: ゆっくり明瞭に話されれば、自分・家族・学校・趣味・身の回りについて話されている表現の一部を理解できる。 | L13: Communicative language activities | M13: Reception | N13: Oral comprehension | O13: Understanding conversation between other people
F14: A2 | G14: =COUNTIFS(Data!$B$2:$B$1833,$L14,Data!$C$2:$C$1833,$M14,Data!$D$2:$D$1833,$N14,Data!$E$2:$E$1833,$O14,Data!$F$2:$F$1833,$F14,Data!$H$2:$H$1833,1) -> 1 | H14: 28 | I14: =INDEX(Data!$G$2:$G$1833,MATCH($H14,Data!$A$2:$A$1833,0)) -> Can follow in outline short, simple social exchanges, conducted very slowly and clearly. | J14: 非常にゆっくり明瞭に行われる短く簡単な社交のやりとりの概略を追える。 | L14: Communicative language activities | M14: Reception | N14: Oral comprehension | O14: Understanding conversation between other people
F15: A2+ | G15: =COUNTIFS(Data!$B$2:$B$1833,$L15,Data!$C$2:$C$1833,$M15,Data!$D$2:$D$1833,$N15,Data!$E$2:$E$1833,$O15,Data!$F$2:$F$1833,$F15,Data!$H$2:$H$1833,1) -> 2 | H15: 27 | I15: =INDEX(Data!$G$2:$G$1833,MATCH($H15,Data!$A$2:$A$1833,0)) -> Can recognise when people agree and disagree in a conversation conducted slowly and clearly. | J15: ゆっくり明瞭に行われる会話の中で、人々が同意しているか反対しているかを認識できる。 | L15: Communicative language activities | M15: Reception | N15: Oral comprehension | O15: Understanding conversation between other people
F16: B1 | G16: =COUNTIFS(Data!$B$2:$B$1833,$L16,Data!$C$2:$C$1833,$M16,Data!$D$2:$D$1833,$N16,Data!$E$2:$E$1833,$O16,Data!$F$2:$F$1833,$F16,Data!$H$2:$H$1833,1) -> 1 | H16: 25 | I16: =INDEX(Data!$G$2:$G$1833,MATCH($H16,Data!$A$2:$A$1833,0)) -> Can generally follow the main points of extended discussion around them, provided it is clearly articulated in standard language or a familiar variety. | J16: 標準語または馴染みのある変種で明瞭に話されていれば、周囲で交わされる長めの議論のおおよその要点を追える。 | L16: Communicative language activities | M16: Reception | N16: Oral comprehension | O16: Understanding conversation between other people
F17: B1+ | G17: =COUNTIFS(Data!$B$2:$B$1833,$L17,Data!$C$2:$C$1833,$M17,Data!$D$2:$D$1833,$N17,Data!$E$2:$E$1833,$O17,Data!$F$2:$F$1833,$F17,Data!$H$2:$H$1833,1) -> 1 | H17: 24 | I17: =INDEX(Data!$G$2:$G$1833,MATCH($H17,Data!$A$2:$A$1833,0)) -> Can follow much of everyday conversation and discussion, provided it is clearly articulated in standard language or in a familiar variety. | J17: 標準語または馴染みのある変種で明瞭に話されていれば、日常会話や議論の大部分を追える。 | L17: Communicative language activities | M17: Reception | N17: Oral comprehension | O17: Understanding conversation between other people
F18: B2 | G18: =COUNTIFS(Data!$B$2:$B$1833,$L18,Data!$C$2:$C$1833,$M18,Data!$D$2:$D$1833,$N18,Data!$E$2:$E$1833,$O18,Data!$F$2:$F$1833,$F18,Data!$H$2:$H$1833,1) -> 3 | H18: 23 | I18: =INDEX(Data!$G$2:$G$1833,MATCH($H18,Data!$A$2:$A$1833,0)) -> Can follow chronological sequence in extended informal discourse, e.g. in a story or anecdote. | J18: 物語や逸話など、長めのくだけた談話の時系列を追える。 | L18: Communicative language activities | M18: Reception | N18: Oral comprehension | O18: Understanding conversation between other people
F19: B2+ | G19: =COUNTIFS(Data!$B$2:$B$1833,$L19,Data!$C$2:$C$1833,$M19,Data!$D$2:$D$1833,$N19,Data!$E$2:$E$1833,$O19,Data!$F$2:$F$1833,$F19,Data!$H$2:$H$1833,1) -> 1 | H19: 20 | I19: =INDEX(Data!$G$2:$G$1833,MATCH($H19,Data!$A$2:$A$1833,0)) -> Can keep up with an animated conversation between proficient users of the target language. | J19: 熟達した話者どうしの活発な会話についていける。 | L19: Communicative language activities | M19: Reception | N19: Oral comprehension | O19: Understanding conversation between other people
F20: C1 | G20: =COUNTIFS(Data!$B$2:$B$1833,$L20,Data!$C$2:$C$1833,$M20,Data!$D$2:$D$1833,$N20,Data!$E$2:$E$1833,$O20,Data!$F$2:$F$1833,$F20,Data!$H$2:$H$1833,1) -> 2 | H20: 18 | I20: =INDEX(Data!$G$2:$G$1833,MATCH($H20,Data!$A$2:$A$1833,0)) -> Can easily follow complex interactions between third parties in group discussion and debate, even on abstract, complex, unfamiliar topics. | J20: 抽象的で複雑な未知の話題でも、グループ討議や討論での第三者間の複雑なやりとりを容易に追える。 | L20: Communicative language activities | M20: Reception | N20: Oral comprehension | O20: Understanding conversation between other people
F21: C2 | G21: =COUNTIFS(Data!$B$2:$B$1833,$L21,Data!$C$2:$C$1833,$M21,Data!$D$2:$D$1833,$N21,Data!$E$2:$E$1833,$O21,Data!$F$2:$F$1833,$F21,Data!$H$2:$H$1833,1) -> 1 | H21: 17 | I21: =INDEX(Data!$G$2:$G$1833,MATCH($H21,Data!$A$2:$A$1833,0)) -> Can identify the sociocultural implications of most of the language used in colloquial discussions that take place at a natural speed. | J21: 自然な速度で行われる口語的な議論で使われる言葉の社会文化的含意を、ほとんど特定できる。 | L21: Communicative language activities | M21: Reception | N21: Oral comprehension | O21: Understanding conversation between other people
A22: =IFERROR(INDEX(対訳マスタ!$C$2:$C$136,MATCH($L22,対訳マスタ!$B$2:$B$136,0)),$L22) -> コミュニケーション言語活動 | B22: =IF($M22="—","—",IFERROR(INDEX(対訳マスタ!$C$2:$C$136,MATCH($M22,対訳マスタ!$B$2:$B$136,0)),$M22)) -> 受容 | C22: =IF($N22="—","—",IFERROR(INDEX(対訳マスタ!$C$2:$C$136,MATCH($N22,対訳マスタ!$B$2:$B$136,0)),$N22)) -> 口頭理解（聞くこと） | D22: =IFERROR(INDEX(対訳マスタ!$C$2:$C$136,MATCH($O22,対訳マスタ!$B$2:$B$136,0)),$O22) -> 聴衆としての聞き取り（講演など） | E22: Understanding as a member of a live audience | F22: Pre-A1 | G22: =COUNTIFS(Data!$B$2:$B$1833,$L22,Data!$C$2:$C$1833,$M22,Data!$D$2:$D$1833,$N22,Data!$E$2:$E$1833,$O22,Data!$F$2:$F$1833,$F22,Data!$H$2:$H$1833,1) -> 0 | H22: — | I22: — | J22: — | L22: Communicative language activities | M22: Reception | N22: Oral comprehension | O22: Understanding as a member of a live audience
F23: A1 | G23: =COUNTIFS(Data!$B$2:$B$1833,$L23,Data!$C$2:$C$1833,$M23,Data!$D$2:$D$1833,$N23,Data!$E$2:$E$1833,$O23,Data!$F$2:$F$1833,$F23,Data!$H$2:$H$1833,1) -> 1 | H23: 49 | I23: =INDEX(Data!$G$2:$G$1833,MATCH($H23,Data!$A$2:$A$1833,0)) -> Can understand in outline very simple information being explained in a predictable situation like a guided tour, provided the delivery is very slow and clear and that there are long pauses from time to time. | J23: ガイドツアーのような予測可能な状況で、非常にゆっくり明瞭に説明され、時々長い間が置かれれば、ごく簡単な情報の概略を理解できる。 | L23: Communicative language activities | M23: Reception | N23: Oral comprehension | O23: Understanding as a member of a live audience
F24: A2 | G24: =COUNTIFS(Data!$B$2:$B$1833,$L24,Data!$C$2:$C$1833,$M24,Data!$D$2:$D$1833,$N24,Data!$E$2:$E$1833,$O24,Data!$F$2:$F$1833,$F24,Data!$H$2:$H$1833,1) -> 2 | H24: 48 | I24: =INDEX(Data!$G$2:$G$1833,MATCH($H24,Data!$A$2:$A$1833,0)) -> Can understand the outline of simple information given in a predictable situation, such as on a guided tour (e.g. “This is where the President lives”). | J24: ガイドツアーのような予測可能な状況で与えられる簡単な情報（「ここが大統領官邸です」など）の概略を理解できる。 | L24: Communicative language activities | M24: Reception | N24: Oral comprehension | O24: Understanding as a member of a live audience
F25: A2+ | G25: =COUNTIFS(Data!$B$2:$B$1833,$L25,Data!$C$2:$C$1833,$M25,Data!$D$2:$D$1833,$N25,Data!$E$2:$E$1833,$O25,Data!$F$2:$F$1833,$F25,Data!$H$2:$H$1833,1) -> 1 | H25: 46 | I25: =INDEX(Data!$G$2:$G$1833,MATCH($H25,Data!$A$2:$A$1833,0)) -> Can follow the general outline of a demonstration or presentation on a familiar or predictable topic, where the message is expressed slowly and clearly in simple language and there is visual support (e.g. slides, handouts). | J25: 身近で予測可能な話題についての実演やプレゼンテーションで、簡単な言葉でゆっくり明瞭に伝えられ、視覚的補助（スライド・配布資料など）があれば、概略を追える。 | L25: Communicative language activities | M25: Reception | N25: Oral comprehension | O25: Understanding as a member of a live audience
F26: B1 | G26: =COUNTIFS(Data!$B$2:$B$1833,$L26,Data!$C$2:$C$1833,$M26,Data!$D$2:$D$1833,$N26,Data!$E$2:$E$1833,$O26,Data!$F$2:$F$1833,$F26,Data!$H$2:$H$1833,1) -> 3 | H26: 45 | I26: =INDEX(Data!$G$2:$G$1833,MATCH($H26,Data!$A$2:$A$1833,0)) -> Can understand the main points of what is said in a straightforward monologue (e.g. a guided tour), provided the delivery is clear and relatively slow. | J26: 明瞭で比較的ゆっくりした話し方であれば、率直な一人語り（ガイドツアーなど）の要点を理解できる。 | L26: Communicative language activities | M26: Reception | N26: Oral comprehension | O26: Understanding as a member of a live audience
F27: B1+ | G27: =COUNTIFS(Data!$B$2:$B$1833,$L27,Data!$C$2:$C$1833,$M27,Data!$D$2:$D$1833,$N27,Data!$E$2:$E$1833,$O27,Data!$F$2:$F$1833,$F27,Data!$H$2:$H$1833,1) -> 2 | H27: 41 | I27: =INDEX(Data!$G$2:$G$1833,MATCH($H27,Data!$A$2:$A$1833,0)) -> Can follow a lecture or talk within their own field, provided the subject matter is familiar and the presentation straightforward and clearly structured. | J27: 主題が身近で、提示が平明で構成が明確なら、自分の分野の講義や講演を追える。 | L27: Communicative language activities | M27: Reception | N27: Oral comprehension | O27: Understanding as a member of a live audience
F28: B2 | G28: =COUNTIFS(Data!$B$2:$B$1833,$L28,Data!$C$2:$C$1833,$M28,Data!$D$2:$D$1833,$N28,Data!$E$2:$E$1833,$O28,Data!$F$2:$F$1833,$F28,Data!$H$2:$H$1833,1) -> 3 | H28: 40 | I28: =INDEX(Data!$G$2:$G$1833,MATCH($H28,Data!$A$2:$A$1833,0)) -> Can recognise the point of view expressed and distinguish this from facts being reporting. | J28: 表明された見解を認識し、報告されている事実と区別できる。 | L28: Communicative language activities | M28: Reception | N28: Oral comprehension | O28: Understanding as a member of a live audience
F29: B2+ | G29: =COUNTIFS(Data!$B$2:$B$1833,$L29,Data!$C$2:$C$1833,$M29,Data!$D$2:$D$1833,$N29,Data!$E$2:$E$1833,$O29,Data!$F$2:$F$1833,$F29,Data!$H$2:$H$1833,1) -> 2 | H29: 36 | I29: =INDEX(Data!$G$2:$G$1833,MATCH($H29,Data!$A$2:$A$1833,0)) -> Can follow the essentials of lectures, talks and reports and other forms of academic/professional presentation which are propositionally and linguistically complex. | J29: 命題的にも言語的にも複雑な講義・講演・報告など、学術的・職業的なプレゼンテーションの要点を追える。 | L29: Communicative language activities | M29: Reception | N29: Oral comprehension | O29: Understanding as a member of a live audience
F30: C1 | G30: =COUNTIFS(Data!$B$2:$B$1833,$L30,Data!$C$2:$C$1833,$M30,Data!$D$2:$D$1833,$N30,Data!$E$2:$E$1833,$O30,Data!$F$2:$F$1833,$F30,Data!$H$2:$H$1833,1) -> 1 | H30: 35 | I30: =INDEX(Data!$G$2:$G$1833,MATCH($H30,Data!$A$2:$A$1833,0)) -> Can follow most lectures, discussions and debates with relative ease. | J30: たいていの講義・討議・討論を比較的容易に追える。 | L30: Communicative language activities | M30: Reception | N30: Oral comprehension | O30: Understanding as a member of a live audience
F31: C2 | G31: =COUNTIFS(Data!$B$2:$B$1833,$L31,Data!$C$2:$C$1833,$M31,Data!$D$2:$D$1833,$N31,Data!$E$2:$E$1833,$O31,Data!$F$2:$F$1833,$F31,Data!$H$2:$H$1833,1) -> 3 | H31: 34 | I31: =INDEX(Data!$G$2:$G$1833,MATCH($H31,Data!$A$2:$A$1833,0)) -> Can get the point of jokes or allusions in a presentation. | J31: プレゼンテーションの中の冗談やほのめかしの意図をつかめる。 | L31: Communicative language activities | M31: Reception | N31: Oral comprehension | O31: Understanding as a member of a live audience
A32: =IFERROR(INDEX(対訳マスタ!$C$2:$C$136,MATCH($L32,対訳マスタ!$B$2:$B$136,0)),$L32) -> コミュニケーション言語活動 | B32: =IF($M32="—","—",IFERROR(INDEX(対訳マスタ!$C$2:$C$136,MATCH($M32,対訳マスタ!$B$2:$B$136,0)),$M32)) -> 受容 | C32: =IF($N32="—","—",IFERROR(INDEX(対訳マスタ!$C$2:$C$136,MATCH($N32,対訳マスタ!$B$2:$B$136,0)),$N32)) -> 口頭理解（聞くこと） | D32: =IFERROR(INDEX(対訳マスタ!$C$2:$C$136,MATCH($O32,対訳マスタ!$B$2:$B$136,0)),$O32) -> アナウンス・指示の聞き取り | E32: Understanding announcements and instructions | F32: Pre-A1 | G32: =COUNTIFS(Data!$B$2:$B$1833,$L32,Data!$C$2:$C$1833,$M32,Data!$D$2:$D$1833,$N32,Data!$E$2:$E$1833,$O32,Data!$F$2:$F$1833,$F32,Data!$H$2:$H$1833,1) -> 1 | H32: 67 | I32: =INDEX(Data!$G$2:$G$1833,MATCH($H32,Data!$A$2:$A$1833,0)) -> Can understand short, simple instructions for actions such as “Stop”, “Close the door”, etc., provided they are delivered slowly face-to-face, accompanied by pictures or manual gestures and repeated if necessary. | J32: 「止まって」「ドアを閉めて」などの短く簡単な指示を、対面でゆっくり伝えられ、絵や身振りが添えられ、必要なら繰り返されれば理解できる。 | L32: Communicative language activities | M32: Reception | N32: Oral comprehension | O32: Understanding announcements and instructions
F33: A1 | G33: =COUNTIFS(Data!$B$2:$B$1833,$L33,Data!$C$2:$C$1833,$M33,Data!$D$2:$D$1833,$N33,Data!$E$2:$E$1833,$O33,Data!$F$2:$F$1833,$F33,Data!$H$2:$H$1833,1) -> 3 | H33: 64 | I33: =INDEX(Data!$G$2:$G$1833,MATCH($H33,Data!$A$2:$A$1833,0)) -> Can understand instructions addressed carefully and slowly to them and follow short, simple directions. | J33: 注意深くゆっくり自分に向けられた指示を理解し、短く簡単な道順の指示に従える。 | L33: Communicative language activities | M33: Reception | N33: Oral comprehension | O33: Understanding announcements and instructions
F34: A2 | G34: =COUNTIFS(Data!$B$2:$B$1833,$L34,Data!$C$2:$C$1833,$M34,Data!$D$2:$D$1833,$N34,Data!$E$2:$E$1833,$O34,Data!$F$2:$F$1833,$F34,Data!$H$2:$H$1833,1) -> 3 | H34: 61 | I34: =INDEX(Data!$G$2:$G$1833,MATCH($H34,Data!$A$2:$A$1833,0)) -> Can catch the main point in short, clear, simple messages and announcements. | J34: 短く明瞭で簡単なメッセージやアナウンスの要点をつかめる。 | L34: Communicative language activities | M34: Reception | N34: Oral comprehension | O34: Understanding announcements and instructions
F35: A2+ | G35: =COUNTIFS(Data!$B$2:$B$1833,$L35,Data!$C$2:$C$1833,$M35,Data!$D$2:$D$1833,$N35,Data!$E$2:$E$1833,$O35,Data!$F$2:$F$1833,$F35,Data!$H$2:$H$1833,1) -> 2 | H35: 60 | I35: =INDEX(Data!$G$2:$G$1833,MATCH($H35,Data!$A$2:$A$1833,0)) -> Can understand straightforward announcements (e.g. of a cinema programme or sports event, that a train has been delayed), provided the delivery is slow and clear. | J35: ゆっくり明瞭に伝えられれば、率直なアナウンス（映画の上映案内、スポーツの試合、列車の遅延など）を理解できる。 | L35: Communicative language activities | M35: Reception | N35: Oral comprehension | O35: Understanding announcements and instructions
F36: B1 | G36: =COUNTIFS(Data!$B$2:$B$1833,$L36,Data!$C$2:$C$1833,$M36,Data!$D$2:$D$1833,$N36,Data!$E$2:$E$1833,$O36,Data!$F$2:$F$1833,$F36,Data!$H$2:$H$1833,1) -> 3 | H36: 57 | I36: =INDEX(Data!$G$2:$G$1833,MATCH($H36,Data!$A$2:$A$1833,0)) -> Can follow detailed directions. | J36: 詳細な道順の指示を追える。 | L36: Communicative language activities | M36: Reception | N36: Oral comprehension | O36: Understanding announcements and instructions
F37: B1+ | G37: =COUNTIFS(Data!$B$2:$B$1833,$L37,Data!$C$2:$C$1833,$M37,Data!$D$2:$D$1833,$N37,Data!$E$2:$E$1833,$O37,Data!$F$2:$F$1833,$F37,Data!$H$2:$H$1833,1) -> 0 | H37: — | I37: — | J37: — | L37: Communicative language activities | M37: Reception | N37: Oral comprehension | O37: Understanding announcements and instructions
F38: B2 | G38: =COUNTIFS(Data!$B$2:$B$1833,$L38,Data!$C$2:$C$1833,$M38,Data!$D$2:$D$1833,$N38,Data!$E$2:$E$1833,$O38,Data!$F$2:$F$1833,$F38,Data!$H$2:$H$1833,1) -> 2 | H38: 55 | I38: =INDEX(Data!$G$2:$G$1833,MATCH($H38,Data!$A$2:$A$1833,0)) -> Can understand detailed instructions well enough to be able to follow them successfully. | J38: 詳細な指示を、それに従って実行できる程度に十分理解できる。 | L38: Communicative language activities | M38: Reception | N38: Oral comprehension | O38: Understanding announcements and instructions
F39: B2+ | G39: =COUNTIFS(Data!$B$2:$B$1833,$L39,Data!$C$2:$C$1833,$M39,Data!$D$2:$D$1833,$N39,Data!$E$2:$E$1833,$O39,Data!$F$2:$F$1833,$F39,Data!$H$2:$H$1833,1) -> 0 | H39: — | I39: — | J39: — | L39: Communicative language activities | M39: Reception | N39: Oral comprehension | O39: Understanding announcements and instructions
F40: C1 | G40: =COUNTIFS(Data!$B$2:$B$1833,$L40,Data!$C$2:$C$1833,$M40,Data!$D$2:$D$1833,$N40,Data!$E$2:$E$1833,$O40,Data!$F$2:$F$1833,$F40,Data!$H$2:$H$1833,1) -> 2 | H40: 53 | I40: =INDEX(Data!$G$2:$G$1833,MATCH($H40,Data!$A$2:$A$1833,0)) -> Can understand complex technical information, such as operating instructions or specifications for familiar products and services. | J40: 操作説明書や馴染みのある製品・サービスの仕様書など、複雑な技術情報を理解できる。 | L40: Communicative language activities | M40: Reception | N40: Oral comprehension | O40: Understanding announcements and instructions
F41: C2 | G41: =COUNTIFS(Data!$B$2:$B$1833,$L41,Data!$C$2:$C$1833,$M41,Data!$D$2:$D$1833,$N41,Data!$E$2:$E$1833,$O41,Data!$F$2:$F$1833,$F41,Data!$H$2:$H$1833,1) -> 0 | H41: — | I41: — | J41: — | L41: Communicative language activities | M41: Reception | N41: Oral comprehension | O41: Understanding announcements and instructions
A42: =IFERROR(INDEX(対訳マスタ!$C$2:$C$136,MATCH($L42,対訳マスタ!$B$2:$B$136,0)),$L42) -> コミュニケーション言語活動 | B42: =IF($M42="—","—",IFERROR(INDEX(対訳マスタ!$C$2:$C$136,MATCH($M42,対訳マスタ!$B$2:$B$136,0)),$M42)) -> 受容 | C42: =IF($N42="—","—",IFERROR(INDEX(対訳マスタ!$C$2:$C$136,MATCH($N42,対訳マスタ!$B$2:$B$136,0)),$N42)) -> 口頭理解（聞くこと） | D42: =IFERROR(INDEX(対訳マスタ!$C$2:$C$136,MATCH($O42,対訳マスタ!$B$2:$B$136,0)),$O42) -> 音声メディア・録音の聞き取り | E42: Understanding audio (or signed) media and recordings | F42: Pre-A1 | G42: =COUNTIFS(Data!$B$2:$B$1833,$L42,Data!$C$2:$C$1833,$M42,Data!$D$2:$D$1833,$N42,Data!$E$2:$E$1833,$O42,Data!$F$2:$F$1833,$F42,Data!$H$2:$H$1833,1) -> 1 | H42: 81 | I42: =INDEX(Data!$G$2:$G$1833,MATCH($H42,Data!$A$2:$A$1833,0)) -> Can recognise words/signs, names and numbers that they already know in simple, short recordings, provided these are delivered very slowly and clearly. | J42: 非常にゆっくり明瞭であれば、簡単で短い録音の中の既知の語・名前・数字を認識できる。 | L42: Communicative language activities | M42: Reception | N42: Oral comprehension | O42: Understanding audio (or signed) media and recordings
F43: A1 | G43: =COUNTIFS(Data!$B$2:$B$1833,$L43,Data!$C$2:$C$1833,$M43,Data!$D$2:$D$1833,$N43,Data!$E$2:$E$1833,$O43,Data!$F$2:$F$1833,$F43,Data!$H$2:$H$1833,1) -> 1 | H43: 80 | I43: =INDEX(Data!$G$2:$G$1833,MATCH($H43,Data!$A$2:$A$1833,0)) -> Can pick out concrete information (e.g. places and times) from short recordings on familiar everyday topics, provided they are delivered very slowly and clearly. | J43: 非常にゆっくり明瞭に伝えられれば、身近な日常の話題の短い録音から具体的情報（場所や時刻など）を拾える。 | L43: Communicative language activities | M43: Reception | N43: Oral comprehension | O43: Understanding audio (or signed) media and recordings
F44: A2 | G44: =COUNTIFS(Data!$B$2:$B$1833,$L44,Data!$C$2:$C$1833,$M44,Data!$D$2:$D$1833,$N44,Data!$E$2:$E$1833,$O44,Data!$F$2:$F$1833,$F44,Data!$H$2:$H$1833,1) -> 3 | H44: 79 | I44: =INDEX(Data!$G$2:$G$1833,MATCH($H44,Data!$A$2:$A$1833,0)) -> Can understand the important points of a story and manage to follow the plot, provided the story is told slowly and clearly. | J44: ゆっくり明瞭に語られれば、物語の重要な点を理解し、筋を追える。 | L44: Communicative language activities | M44: Reception | N44: Oral comprehension | O44: Understanding audio (or signed) media and recordings
F45: A2+ | G45: =COUNTIFS(Data!$B$2:$B$1833,$L45,Data!$C$2:$C$1833,$M45,Data!$D$2:$D$1833,$N45,Data!$E$2:$E$1833,$O45,Data!$F$2:$F$1833,$F45,Data!$H$2:$H$1833,1) -> 2 | H45: 75 | I45: =INDEX(Data!$G$2:$G$1833,MATCH($H45,Data!$A$2:$A$1833,0)) -> Can understand the most important information contained in short commercials concerning goods and services of interest (e.g. CDs, video games, travel). | J45: 関心のある商品やサービス（CD、ゲーム、旅行など）の短いコマーシャルに含まれる最重要情報を理解できる。 | L45: Communicative language activities | M45: Reception | N45: Oral comprehension | O45: Understanding audio (or signed) media and recordings
F46: B1 | G46: =COUNTIFS(Data!$B$2:$B$1833,$L46,Data!$C$2:$C$1833,$M46,Data!$D$2:$D$1833,$N46,Data!$E$2:$E$1833,$O46,Data!$F$2:$F$1833,$F46,Data!$H$2:$H$1833,1) -> 2 | H46: 73 | I46: =INDEX(Data!$G$2:$G$1833,MATCH($H46,Data!$A$2:$A$1833,0)) -> Can understand the main points of news bulletins and simpler recorded material about familiar subjects delivered relatively slowly and clearly. | J46: 比較的ゆっくり明瞭に伝えられれば、ニュースや身近な題材の簡単な録音素材の要点を理解できる。 | L46: Communicative language activities | M46: Reception | N46: Oral comprehension | O46: Understanding audio (or signed) media and recordings
F47: B1+ | G47: =COUNTIFS(Data!$B$2:$B$1833,$L47,Data!$C$2:$C$1833,$M47,Data!$D$2:$D$1833,$N47,Data!$E$2:$E$1833,$O47,Data!$F$2:$F$1833,$F47,Data!$H$2:$H$1833,1) -> 1 | H47: 72 | I47: =INDEX(Data!$G$2:$G$1833,MATCH($H47,Data!$A$2:$A$1833,0)) -> Can understand the information content of the majority of recorded or broadcast material on topics of personal interest delivered in clear standard language. | J47: 明瞭な標準語で伝えられる、個人的関心のある話題の録音・放送素材の大部分の情報内容を理解できる。 | L47: Communicative language activities | M47: Reception | N47: Oral comprehension | O47: Understanding audio (or signed) media and recordings
F48: B2 | G48: =COUNTIFS(Data!$B$2:$B$1833,$L48,Data!$C$2:$C$1833,$M48,Data!$D$2:$D$1833,$N48,Data!$E$2:$E$1833,$O48,Data!$F$2:$F$1833,$F48,Data!$H$2:$H$1833,1) -> 1 | H48: 71 | I48: =INDEX(Data!$G$2:$G$1833,MATCH($H48,Data!$A$2:$A$1833,0)) -> Can understand most documentaries and most other recorded or broadcast material delivered in the standard form of the language and can identify mood, attitude, etc. | J48: 標準語で伝えられるドキュメンタリーその他の録音・放送素材の大半を理解し、気分・態度などを特定できる。 | L48: Communicative language activities | M48: Reception | N48: Oral comprehension | O48: Understanding audio (or signed) media and recordings
F49: B2+ | G49: =COUNTIFS(Data!$B$2:$B$1833,$L49,Data!$C$2:$C$1833,$M49,Data!$D$2:$D$1833,$N49,Data!$E$2:$E$1833,$O49,Data!$F$2:$F$1833,$F49,Data!$H$2:$H$1833,1) -> 1 | H49: 70 | I49: =INDEX(Data!$G$2:$G$1833,MATCH($H49,Data!$A$2:$A$1833,0)) -> Can understand recordings in the standard form of the language likely to be encountered in social, professional or academic life and identify viewpoints and attitudes as well as the information content. | J49: 社会・職業・学術生活で出会いそうな標準語の録音を理解し、情報内容だけでなく視点や態度も特定できる。 | L49: Communicative language activities | M49: Reception | N49: Oral comprehension | O49: Understanding audio (or signed) media and recordings
F50: C1 | G50: =COUNTIFS(Data!$B$2:$B$1833,$L50,Data!$C$2:$C$1833,$M50,Data!$D$2:$D$1833,$N50,Data!$E$2:$E$1833,$O50,Data!$F$2:$F$1833,$F50,Data!$H$2:$H$1833,1) -> 1 | H50: 69 | I50: =INDEX(Data!$G$2:$G$1833,MATCH($H50,Data!$A$2:$A$1833,0)) -> Can understand a wide range of recorded and broadcast material, including some non-standard usage, and identify finer points of detail including implicit attitudes and relationships between people. | J50: 一部の非標準的な語法を含む幅広い録音・放送素材を理解し、暗黙の態度や人間関係を含む細かな点を特定できる。 | L50: Communicative language activities | M50: Reception | N50: Oral comprehension | O50: Understanding audio (or signed) media and recordings
F51: C2 | G51: =COUNTIFS(Data!$B$2:$B$1833,$L51,Data!$C$2:$C$1833,$M51,Data!$D$2:$D$1833,$N51,Data!$E$2:$E$1833,$O51,Data!$F$2:$F$1833,$F51,Data!$H$2:$H$1833,1) -> 0 | H51: — | I51: — | J51: — | L51: Communicative language activities | M51: Reception | N51: Oral comprehension | O51: Understanding audio (or signed) media and recordings
A52: =IFERROR(INDEX(対訳マスタ!$C$2:$C$136,MATCH($L52,対訳マスタ!$B$2:$B$136,0)),$L52) -> コミュニケーション言語活動 | B52: =IF($M52="—","—",IFERROR(INDEX(対訳マスタ!$C$2:$C$136,MATCH($M52,対訳マスタ!$B$2:$B$136,0)),$M52)) -> 受容 | C52: =IF($N52="—","—",IFERROR(INDEX(対訳マスタ!$C$2:$C$136,MATCH($N52,対訳マスタ!$B$2:$B$136,0)),$N52)) -> 視聴覚理解 | D52: =IFERROR(INDEX(対訳マスタ!$C$2:$C$136,MATCH($O52,対訳マスタ!$B$2:$B$136,0)),$O52) -> テレビ・映画・動画の視聴 | E52: Watching TV, film and video | F52: Pre-A1 | G52: =COUNTIFS(Data!$B$2:$B$1833,$L52,Data!$C$2:$C$1833,$M52,Data!$D$2:$D$1833,$N52,Data!$E$2:$E$1833,$O52,Data!$F$2:$F$1833,$F52,Data!$H$2:$H$1833,1) -> 1 | H52: 96 | I52: =INDEX(Data!$G$2:$G$1833,MATCH($H52,Data!$A$2:$A$1833,0)) -> Can identify the subject of a video document on the basis of visual information and previous knowledge. | J52: 視覚情報と既有知識から、映像資料の主題を特定できる。 | L52: Communicative language activities | M52: Reception | N52: Audio-visual comprehension | O52: Watching TV, film and video
F53: A1 | G53: =COUNTIFS(Data!$B$2:$B$1833,$L53,Data!$C$2:$C$1833,$M53,Data!$D$2:$D$1833,$N53,Data!$E$2:$E$1833,$O53,Data!$F$2:$F$1833,$F53,Data!$H$2:$H$1833,1) -> 1 | H53: 95 | I53: =INDEX(Data!$G$2:$G$1833,MATCH($H53,Data!$A$2:$A$1833,0)) -> Can recognise familiar words/signs and phrases and identify the topics in headline news summaries and many of the products in advertisements, by exploiting visual information and general knowledge. | J53: 視覚情報と一般知識を手がかりに、ニュースの見出しの話題や広告の多くの商品について、既知の語句を認識し特定できる。 | L53: Communicative language activities | M53: Reception | N53: Audio-visual comprehension | O53: Watching TV, film and video
F54: A2 | G54: =COUNTIFS(Data!$B$2:$B$1833,$L54,Data!$C$2:$C$1833,$M54,Data!$D$2:$D$1833,$N54,Data!$E$2:$E$1833,$O54,Data!$F$2:$F$1833,$F54,Data!$H$2:$H$1833,1) -> 1 | H54: 94 | I54: =INDEX(Data!$G$2:$G$1833,MATCH($H54,Data!$A$2:$A$1833,0)) -> Can follow changes of topic of factual TV news items, and form an idea of the main content. | J54: 事実を伝えるテレビニュースの話題の切り替わりを追い、主な内容の見当をつけられる。 | L54: Communicative language activities | M54: Reception | N54: Audio-visual comprehension | O54: Watching TV, film and video
F55: A2+ | G55: =COUNTIFS(Data!$B$2:$B$1833,$L55,Data!$C$2:$C$1833,$M55,Data!$D$2:$D$1833,$N55,Data!$E$2:$E$1833,$O55,Data!$F$2:$F$1833,$F55,Data!$H$2:$H$1833,1) -> 2 | H55: 92 | I55: =INDEX(Data!$G$2:$G$1833,MATCH($H55,Data!$A$2:$A$1833,0)) -> Can identify the main point of TV news items reporting events, accidents, etc. where the visuals support the commentary. | J55: 映像が解説を補っていれば、事件・事故などを報じるテレビニュースの要点を特定できる。 | L55: Communicative language activities | M55: Reception | N55: Audio-visual comprehension | O55: Watching TV, film and video
F56: B1 | G56: =COUNTIFS(Data!$B$2:$B$1833,$L56,Data!$C$2:$C$1833,$M56,Data!$D$2:$D$1833,$N56,Data!$E$2:$E$1833,$O56,Data!$F$2:$F$1833,$F56,Data!$H$2:$H$1833,1) -> 2 | H56: 91 | I56: =INDEX(Data!$G$2:$G$1833,MATCH($H56,Data!$A$2:$A$1833,0)) -> Can catch the main points in TV programmes on familiar topics when the delivery is relatively slow and clear. | J56: 比較的ゆっくり明瞭であれば、身近な話題のテレビ番組の要点をつかめる。 | L56: Communicative language activities | M56: Reception | N56: Audio-visual comprehension | O56: Watching TV, film and video
F57: B1+ | G57: =COUNTIFS(Data!$B$2:$B$1833,$L57,Data!$C$2:$C$1833,$M57,Data!$D$2:$D$1833,$N57,Data!$E$2:$E$1833,$O57,Data!$F$2:$F$1833,$F57,Data!$H$2:$H$1833,1) -> 1 | H57: 89 | I57: =INDEX(Data!$G$2:$G$1833,MATCH($H57,Data!$A$2:$A$1833,0)) -> Can understand a large part of many TV programmes on topics of personal interest such as interviews, short lectures and news reports when the delivery is relatively slow and clear. | J57: 比較的ゆっくり明瞭であれば、インタビュー、短い講演、ニュースなど個人的関心のある話題のテレビ番組の大部分を理解できる。 | L57: Communicative language activities | M57: Reception | N57: Audio-visual comprehension | O57: Watching TV, film and video
F58: B2 | G58: =COUNTIFS(Data!$B$2:$B$1833,$L58,Data!$C$2:$C$1833,$M58,Data!$D$2:$D$1833,$N58,Data!$E$2:$E$1833,$O58,Data!$F$2:$F$1833,$F58,Data!$H$2:$H$1833,1) -> 2 | H58: 87 | I58: =INDEX(Data!$G$2:$G$1833,MATCH($H58,Data!$A$2:$A$1833,0)) -> Can understand most TV news and current affairs programmes. | J58: テレビのニュースや時事番組の大半を理解できる。 | L58: Communicative language activities | M58: Reception | N58: Audio-visual comprehension | O58: Watching TV, film and video
F59: B2+ | G59: =COUNTIFS(Data!$B$2:$B$1833,$L59,Data!$C$2:$C$1833,$M59,Data!$D$2:$D$1833,$N59,Data!$E$2:$E$1833,$O59,Data!$F$2:$F$1833,$F59,Data!$H$2:$H$1833,1) -> 1 | H59: 86 | I59: =INDEX(Data!$G$2:$G$1833,MATCH($H59,Data!$A$2:$A$1833,0)) -> Can extract the main points from the arguments and discussions in news and current affairs programmes. | J59: ニュースや時事番組の議論から要点を抽出できる。 | L59: Communicative language activities | M59: Reception | N59: Audio-visual comprehension | O59: Watching TV, film and video
F60: C1 | G60: =COUNTIFS(Data!$B$2:$B$1833,$L60,Data!$C$2:$C$1833,$M60,Data!$D$2:$D$1833,$N60,Data!$E$2:$E$1833,$O60,Data!$F$2:$F$1833,$F60,Data!$H$2:$H$1833,1) -> 3 | H60: 83 | I60: =INDEX(Data!$G$2:$G$1833,MATCH($H60,Data!$A$2:$A$1833,0)) -> Can follow films employing a considerable degree of slang and idiomatic usage. | J60: かなりの俗語や慣用表現を使う映画を追える。 | L60: Communicative language activities | M60: Reception | N60: Audio-visual comprehension | O60: Watching TV, film and video
F61: C2 | G61: =COUNTIFS(Data!$B$2:$B$1833,$L61,Data!$C$2:$C$1833,$M61,Data!$D$2:$D$1833,$N61,Data!$E$2:$E$1833,$O61,Data!$F$2:$F$1833,$F61,Data!$H$2:$H$1833,1) -> 0 | H61: — | I61: — | J61: — | L61: Communicative language activities | M61: Reception | N61: Audio-visual comprehension | O61: Watching TV, film and video
A62: =IFERROR(INDEX(対訳マスタ!$C$2:$C$136,MATCH($L62,対訳マスタ!$B$2:$B$136,0)),$L62) -> コミュニケーション言語活動 | B62: =IF($M62="—","—",IFERROR(INDEX(対訳マスタ!$C$2:$C$136,MATCH($M62,対訳マスタ!$B$2:$B$136,0)),$M62)) -> 受容 | C62: =IF($N62="—","—",IFERROR(INDEX(対訳マスタ!$C$2:$C$136,MATCH($N62,対訳マスタ!$B$2:$B$136,0)),$N62)) -> 読解（読むこと） | D62: =IFERROR(INDEX(対訳マスタ!$C$2:$C$136,MATCH($O62,対訳マスタ!$B$2:$B$136,0)),$O62) -> 読解（総合） | E62: Overall reading comprehension | F62: Pre-A1 | G62: =COUNTIFS(Data!$B$2:$B$1833,$L62,Data!$C$2:$C$1833,$M62,Data!$D$2:$D$1833,$N62,Data!$E$2:$E$1833,$O62,Data!$F$2:$F$1833,$F62,Data!$H$2:$H$1833,1) -> 1 | H62: 106 | I62: =INDEX(Data!$G$2:$G$1833,MATCH($H62,Data!$A$2:$A$1833,0)) -> Can recognise familiar words/signs accompanied by pictures, such as a fast-food restaurant menu illustrated with photos or a picture book using familiar vocabulary. | J62: 写真つきのファストフード店のメニューや馴染みの語彙を使った絵本など、絵に添えられた既知の語を認識できる。 | L62: Communicative language activities | M62: Reception | N62: Reading comprehension | O62: Overall reading comprehension
F63: A1 | G63: =COUNTIFS(Data!$B$2:$B$1833,$L63,Data!$C$2:$C$1833,$M63,Data!$D$2:$D$1833,$N63,Data!$E$2:$E$1833,$O63,Data!$F$2:$F$1833,$F63,Data!$H$2:$H$1833,1) -> 1 | H63: 105 | I63: =INDEX(Data!$G$2:$G$1833,MATCH($H63,Data!$A$2:$A$1833,0)) -> Can understand very short, simple texts a single phrase at a time, picking up familiar names, words and basic phrases and rereading as required. | J63: ごく短い簡単なテキストを、一句ずつ、既知の名前・語・基本的な句を拾い、必要に応じて読み返しながら理解できる。 | L63: Communicative language activities | M63: Reception | N63: Reading comprehension | O63: Overall reading comprehension
F64: A2 | G64: =COUNTIFS(Data!$B$2:$B$1833,$L64,Data!$C$2:$C$1833,$M64,Data!$D$2:$D$1833,$N64,Data!$E$2:$E$1833,$O64,Data!$F$2:$F$1833,$F64,Data!$H$2:$H$1833,1) -> 1 | H64: 104 | I64: =INDEX(Data!$G$2:$G$1833,MATCH($H64,Data!$A$2:$A$1833,0)) -> Can understand short, simple texts containing the highest frequency vocabulary, including a proportion of shared international vocabulary items. | J64: 最高頻度の語彙と一部の国際共通語彙を含む、短く簡単なテキストを理解できる。 | L64: Communicative language activities | M64: Reception | N64: Reading comprehension | O64: Overall reading comprehension
F65: A2+ | G65: =COUNTIFS(Data!$B$2:$B$1833,$L65,Data!$C$2:$C$1833,$M65,Data!$D$2:$D$1833,$N65,Data!$E$2:$E$1833,$O65,Data!$F$2:$F$1833,$F65,Data!$H$2:$H$1833,1) -> 1 | H65: 103 | I65: =INDEX(Data!$G$2:$G$1833,MATCH($H65,Data!$A$2:$A$1833,0)) -> Can understand short, simple texts on familiar matters of a concrete type which consist of high frequency everyday or job-related language. | J65: 高頻度の日常語や仕事関連の言葉で書かれた、具体的で身近な事柄の短く簡単なテキストを理解できる。 | L65: Communicative language activities | M65: Reception | N65: Reading comprehension | O65: Overall reading comprehension
F66: B1 | G66: =COUNTIFS(Data!$B$2:$B$1833,$L66,Data!$C$2:$C$1833,$M66,Data!$D$2:$D$1833,$N66,Data!$E$2:$E$1833,$O66,Data!$F$2:$F$1833,$F66,Data!$H$2:$H$1833,1) -> 1 | H66: 102 | I66: =INDEX(Data!$G$2:$G$1833,MATCH($H66,Data!$A$2:$A$1833,0)) -> Can read straightforward factual texts on subjects related to their field of interest with a satisfactory level of comprehension. | J66: 関心分野に関わる率直な事実的テキストを、満足のいく理解度で読める。 | L66: Communicative language activities | M66: Reception | N66: Reading comprehension | O66: Overall reading comprehension
F67: B1+ | G67: =COUNTIFS(Data!$B$2:$B$1833,$L67,Data!$C$2:$C$1833,$M67,Data!$D$2:$D$1833,$N67,Data!$E$2:$E$1833,$O67,Data!$F$2:$F$1833,$F67,Data!$H$2:$H$1833,1) -> 0 | H67: — | I67: — | J67: — | L67: Communicative language activities | M67: Reception | N67: Reading comprehension | O67: Overall reading comprehension
F68: B2 | G68: =COUNTIFS(Data!$B$2:$B$1833,$L68,Data!$C$2:$C$1833,$M68,Data!$D$2:$D$1833,$N68,Data!$E$2:$E$1833,$O68,Data!$F$2:$F$1833,$F68,Data!$H$2:$H$1833,1) -> 1 | H68: 101 | I68: =INDEX(Data!$G$2:$G$1833,MATCH($H68,Data!$A$2:$A$1833,0)) -> Can read with a large degree of independence, adapting style and speed of reading to different texts and purposes, and using appropriate reference sources selectively. Has a broad active reading vocabulary, but may experience some difficulty with low-frequency idioms. | J68: 高い自立性をもって読め、テキストと目的に応じて読み方や速度を調整し、適切な参考資料を選んで使える。活発な読解語彙は幅広いが、低頻度の慣用句には苦労することがある。 | L68: Communicative language activities | M68: Reception | N68: Reading comprehension | O68: Overall reading comprehension
F69: B2+ | G69: =COUNTIFS(Data!$B$2:$B$1833,$L69,Data!$C$2:$C$1833,$M69,Data!$D$2:$D$1833,$N69,Data!$E$2:$E$1833,$O69,Data!$F$2:$F$1833,$F69,Data!$H$2:$H$1833,1) -> 0 | H69: — | I69: — | J69: — | L69: Communicative language activities | M69: Reception | N69: Reading comprehension | O69: Overall reading comprehension
F70: C1 | G70: =COUNTIFS(Data!$B$2:$B$1833,$L70,Data!$C$2:$C$1833,$M70,Data!$D$2:$D$1833,$N70,Data!$E$2:$E$1833,$O70,Data!$F$2:$F$1833,$F70,Data!$H$2:$H$1833,1) -> 2 | H70: 99 | I70: =INDEX(Data!$G$2:$G$1833,MATCH($H70,Data!$A$2:$A$1833,0)) -> Can understand in detail lengthy, complex texts, whether or not these relate to their own area of speciality, provided they can reread difficult sections. | J70: 難しい箇所を読み返せるなら、自分の専門分野かどうかに関わらず、長く複雑なテキストを詳細に理解できる。 | L70: Communicative language activities | M70: Reception | N70: Reading comprehension | O70: Overall reading comprehension
F71: C2 | G71: =COUNTIFS(Data!$B$2:$B$1833,$L71,Data!$C$2:$C$1833,$M71,Data!$D$2:$D$1833,$N71,Data!$E$2:$E$1833,$O71,Data!$F$2:$F$1833,$F71,Data!$H$2:$H$1833,1) -> 2 | H71: 98 | I71: =INDEX(Data!$G$2:$G$1833,MATCH($H71,Data!$A$2:$A$1833,0)) -> Can understand a wide range of long and complex texts, appreciating subtle distinctions of style and implicit as well as explicit meaning. | J71: 長く複雑な多様なテキストを理解し、文体の微妙な違いや、明示的・暗示的な意味を味わえる。 | L71: Communicative language activities | M71: Reception | N71: Reading comprehension | O71: Overall reading comprehension
A72: =IFERROR(INDEX(対訳マスタ!$C$2:$C$136,MATCH($L72,対訳マスタ!$B$2:$B$136,0)),$L72) -> コミュニケーション言語活動 | B72: =IF($M72="—","—",IFERROR(INDEX(対訳マスタ!$C$2:$C$136,MATCH($M72,対訳マスタ!$B$2:$B$136,0)),$M72)) -> 受容 | C72: =IF($N72="—","—",IFERROR(INDEX(対訳マスタ!$C$2:$C$136,MATCH($N72,対訳マスタ!$B$2:$B$136,0)),$N72)) -> 読解（読むこと） | D72: =IFERROR(INDEX(対訳マスタ!$C$2:$C$136,MATCH($O72,対訳マスタ!$B$2:$B$136,0)),$O72) -> 手紙・メールを読む | E72: Reading correspondence | F72: Pre-A1 | G72: =COUNTIFS(Data!$B$2:$B$1833,$L72,Data!$C$2:$C$1833,$M72,Data!$D$2:$D$1833,$N72,Data!$E$2:$E$1833,$O72,Data!$F$2:$F$1833,$F72,Data!$H$2:$H$1833,1) -> 2 | H72: 123 | I72: =INDEX(Data!$G$2:$G$1833,MATCH($H72,Data!$A$2:$A$1833,0)) -> Can understand from a letter, card or e-mail the event to which they are being invited and the information given about day, time and location. | J72: 手紙・カード・メールから、招待されている行事と、日時・場所についての情報を理解できる。 | L72: Communicative language activities | M72: Reception | N72: Reading comprehension | O72: Reading correspondence
F73: A1 | G73: =COUNTIFS(Data!$B$2:$B$1833,$L73,Data!$C$2:$C$1833,$M73,Data!$D$2:$D$1833,$N73,Data!$E$2:$E$1833,$O73,Data!$F$2:$F$1833,$F73,Data!$H$2:$H$1833,1) -> 2 | H73: 121 | I73: =INDEX(Data!$G$2:$G$1833,MATCH($H73,Data!$A$2:$A$1833,0)) -> Can understand short, simple messages on postcards. | J73: はがきの短く簡単なメッセージを理解できる。 | L73: Communicative language activities | M73: Reception | N73: Reading comprehension | O73: Reading correspondence
F74: A2 | G74: =COUNTIFS(Data!$B$2:$B$1833,$L74,Data!$C$2:$C$1833,$M74,Data!$D$2:$D$1833,$N74,Data!$E$2:$E$1833,$O74,Data!$F$2:$F$1833,$F74,Data!$H$2:$H$1833,1) -> 2 | H74: 119 | I74: =INDEX(Data!$G$2:$G$1833,MATCH($H74,Data!$A$2:$A$1833,0)) -> Can understand short, simple personal letters. | J74: 短く簡単な個人的な手紙を理解できる。 | L74: Communicative language activities | M74: Reception | N74: Reading comprehension | O74: Reading correspondence
F75: A2+ | G75: =COUNTIFS(Data!$B$2:$B$1833,$L75,Data!$C$2:$C$1833,$M75,Data!$D$2:$D$1833,$N75,Data!$E$2:$E$1833,$O75,Data!$F$2:$F$1833,$F75,Data!$H$2:$H$1833,1) -> 2 | H75: 118 | I75: =INDEX(Data!$G$2:$G$1833,MATCH($H75,Data!$A$2:$A$1833,0)) -> Can understand basic types of standard routine letters and faxes (enquiries, orders, letters of confirmation, etc.) on familiar topics. | J75: 身近な話題についての標準的・定型的な手紙やファクス（問い合わせ、注文、確認状など）の基本的な種類を理解できる。 | L75: Communicative language activities | M75: Reception | N75: Reading comprehension | O75: Reading correspondence
F76: B1 | G76: =COUNTIFS(Data!$B$2:$B$1833,$L76,Data!$C$2:$C$1833,$M76,Data!$D$2:$D$1833,$N76,Data!$E$2:$E$1833,$O76,Data!$F$2:$F$1833,$F76,Data!$H$2:$H$1833,1) -> 3 | H76: 116 | I76: =INDEX(Data!$G$2:$G$1833,MATCH($H76,Data!$A$2:$A$1833,0)) -> Can understand standard formal correspondence and online postings in their area of professional interest. | J76: 自分の職業的関心領域の標準的な公式通信文やオンライン投稿を理解できる。 | L76: Communicative language activities | M76: Reception | N76: Reading comprehension | O76: Reading correspondence
F77: B1+ | G77: =COUNTIFS(Data!$B$2:$B$1833,$L77,Data!$C$2:$C$1833,$M77,Data!$D$2:$D$1833,$N77,Data!$E$2:$E$1833,$O77,Data!$F$2:$F$1833,$F77,Data!$H$2:$H$1833,1) -> 1 | H77: 113 | I77: =INDEX(Data!$G$2:$G$1833,MATCH($H77,Data!$A$2:$A$1833,0)) -> Can understand formal correspondence on less familiar subjects well enough to redirect it to someone else. | J77: あまり馴染みのない主題の公式な通信文を、他の人に回すべきか判断できる程度に理解できる。 | L77: Communicative language activities | M77: Reception | N77: Reading comprehension | O77: Reading correspondence
F78: B2 | G78: =COUNTIFS(Data!$B$2:$B$1833,$L78,Data!$C$2:$C$1833,$M78,Data!$D$2:$D$1833,$N78,Data!$E$2:$E$1833,$O78,Data!$F$2:$F$1833,$F78,Data!$H$2:$H$1833,1) -> 2 | H78: 111 | I78: =INDEX(Data!$G$2:$G$1833,MATCH($H78,Data!$A$2:$A$1833,0)) -> Can read correspondence relating to their field of interest and readily grasp the essential meaning. | J78: 関心分野に関わる通信文を読み、本質的な意味を容易につかめる。 | L78: Communicative language activities | M78: Reception | N78: Reading comprehension | O78: Reading correspondence
F79: B2+ | G79: =COUNTIFS(Data!$B$2:$B$1833,$L79,Data!$C$2:$C$1833,$M79,Data!$D$2:$D$1833,$N79,Data!$E$2:$E$1833,$O79,Data!$F$2:$F$1833,$F79,Data!$H$2:$H$1833,1) -> 0 | H79: — | I79: — | J79: — | L79: Communicative language activities | M79: Reception | N79: Reading comprehension | O79: Reading correspondence
F80: C1 | G80: =COUNTIFS(Data!$B$2:$B$1833,$L80,Data!$C$2:$C$1833,$M80,Data!$D$2:$D$1833,$N80,Data!$E$2:$E$1833,$O80,Data!$F$2:$F$1833,$F80,Data!$H$2:$H$1833,1) -> 3 | H80: 108 | I80: =INDEX(Data!$G$2:$G$1833,MATCH($H80,Data!$A$2:$A$1833,0)) -> Can understand any correspondence given the occasional use of a dictionary. | J80: 時々辞書を使えば、どんな通信文でも理解できる。 | L80: Communicative language activities | M80: Reception | N80: Reading comprehension | O80: Reading correspondence
F81: C2 | G81: =COUNTIFS(Data!$B$2:$B$1833,$L81,Data!$C$2:$C$1833,$M81,Data!$D$2:$D$1833,$N81,Data!$E$2:$E$1833,$O81,Data!$F$2:$F$1833,$F81,Data!$H$2:$H$1833,1) -> 1 | H81: 107 | I81: =INDEX(Data!$G$2:$G$1833,MATCH($H81,Data!$A$2:$A$1833,0)) -> Can understand specialised, formal correspondence on a complex topic. | J81: 複雑な話題の専門的・公式な通信文を理解できる。 | L81: Communicative language activities | M81: Reception | N81: Reading comprehension | O81: Reading correspondence
A82: =IFERROR(INDEX(対訳マスタ!$C$2:$C$136,MATCH($L82,対訳マスタ!$B$2:$B$136,0)),$L82) -> コミュニケーション言語活動 | B82: =IF($M82="—","—",IFERROR(INDEX(対訳マスタ!$C$2:$C$136,MATCH($M82,対訳マスタ!$B$2:$B$136,0)),$M82)) -> 受容 | C82: =IF($N82="—","—",IFERROR(INDEX(対訳マスタ!$C$2:$C$136,MATCH($N82,対訳マスタ!$B$2:$B$136,0)),$N82)) -> 読解（読むこと） | D82: =IFERROR(INDEX(対訳マスタ!$C$2:$C$136,MATCH($O82,対訳マスタ!$B$2:$B$136,0)),$O82) -> 目当ての情報を探す読み（拾い読み） | E82: Reading for orientation | F82: Pre-A1 | G82: =COUNTIFS(Data!$B$2:$B$1833,$L82,Data!$C$2:$C$1833,$M82,Data!$D$2:$D$1833,$N82,Data!$E$2:$E$1833,$O82,Data!$F$2:$F$1833,$F82,Data!$H$2:$H$1833,1) -> 2 | H82: 146 | I82: =INDEX(Data!$G$2:$G$1833,MATCH($H82,Data!$A$2:$A$1833,0)) -> Can find information about places, times and prices on posters, flyers and notices. | J82: ポスター・チラシ・掲示から、場所・時間・価格についての情報を見つけられる。 | L82: Communicative language activities | M82: Reception | N82: Reading comprehension | O82: Reading for orientation
F83: A1 | G83: =COUNTIFS(Data!$B$2:$B$1833,$L83,Data!$C$2:$C$1833,$M83,Data!$D$2:$D$1833,$N83,Data!$E$2:$E$1833,$O83,Data!$F$2:$F$1833,$F83,Data!$H$2:$H$1833,1) -> 4 | H83: 143 | I83: =INDEX(Data!$G$2:$G$1833,MATCH($H83,Data!$A$2:$A$1833,0)) -> Can understand basic hotel information (e.g. times when meals are served). | J83: ホテルの基本情報（食事の時間など）を理解できる。 | L83: Communicative language activities | M83: Reception | N83: Reading comprehension | O83: Reading for orientation
F84: A2 | G84: =COUNTIFS(Data!$B$2:$B$1833,$L84,Data!$C$2:$C$1833,$M84,Data!$D$2:$D$1833,$N84,Data!$E$2:$E$1833,$O84,Data!$F$2:$F$1833,$F84,Data!$H$2:$H$1833,1) -> 3 | H84: 139 | I84: =INDEX(Data!$G$2:$G$1833,MATCH($H84,Data!$A$2:$A$1833,0)) -> Can locate specific information in lists and isolate the information required (e.g. use the Yellow Pages to find a service or tradesman). | J84: リストの中から特定の情報を探し出し、必要な情報を選び出せる（例：職業別電話帳で業者を探す）。 | L84: Communicative language activities | M84: Reception | N84: Reading comprehension | O84: Reading for orientation
F85: A2+ | G85: =COUNTIFS(Data!$B$2:$B$1833,$L85,Data!$C$2:$C$1833,$M85,Data!$D$2:$D$1833,$N85,Data!$E$2:$E$1833,$O85,Data!$F$2:$F$1833,$F85,Data!$H$2:$H$1833,1) -> 2 | H85: 137 | I85: =INDEX(Data!$G$2:$G$1833,MATCH($H85,Data!$A$2:$A$1833,0)) -> Can understand the main information in short and simple descriptions of goods in brochures and websites (e.g. portable digital devices, cameras). | J85: パンフレットやウェブサイトの商品（携帯情報端末、カメラなど）の短く簡単な説明の主要情報を理解できる。 | L85: Communicative language activities | M85: Reception | N85: Reading comprehension | O85: Reading for orientation
F86: B1 | G86: =COUNTIFS(Data!$B$2:$B$1833,$L86,Data!$C$2:$C$1833,$M86,Data!$D$2:$D$1833,$N86,Data!$E$2:$E$1833,$O86,Data!$F$2:$F$1833,$F86,Data!$H$2:$H$1833,1) -> 4 | H86: 134 | I86: =INDEX(Data!$G$2:$G$1833,MATCH($H86,Data!$A$2:$A$1833,0)) -> Can assess whether an article, report or review is on the required topic. | J86: 記事・報告・レビューが求めている話題を扱っているかどうか判断できる。 | L86: Communicative language activities | M86: Reception | N86: Reading comprehension | O86: Reading for orientation
F87: B1+ | G87: =COUNTIFS(Data!$B$2:$B$1833,$L87,Data!$C$2:$C$1833,$M87,Data!$D$2:$D$1833,$N87,Data!$E$2:$E$1833,$O87,Data!$F$2:$F$1833,$F87,Data!$H$2:$H$1833,1) -> 2 | H87: 130 | I87: =INDEX(Data!$G$2:$G$1833,MATCH($H87,Data!$A$2:$A$1833,0)) -> Can scan longer texts in order to locate desired information, and gather information from different parts of a text, or from different texts in order to fulfil a specific task. | J87: 長めのテキストを走査して必要な情報を探し出し、特定の課題を果たすためにテキストの各部や複数のテキストから情報を集められる。 | L87: Communicative language activities | M87: Reception | N87: Reading comprehension | O87: Reading for orientation
F88: B2 | G88: =COUNTIFS(Data!$B$2:$B$1833,$L88,Data!$C$2:$C$1833,$M88,Data!$D$2:$D$1833,$N88,Data!$E$2:$E$1833,$O88,Data!$F$2:$F$1833,$F88,Data!$H$2:$H$1833,1) -> 2 | H88: 128 | I88: =INDEX(Data!$G$2:$G$1833,MATCH($H88,Data!$A$2:$A$1833,0)) -> Can scan quickly through long and complex texts, locating relevant details. | J88: 長く複雑なテキストを素早く走査し、関連する詳細を見つけられる。 | L88: Communicative language activities | M88: Reception | N88: Reading comprehension | O88: Reading for orientation
F89: B2+ | G89: =COUNTIFS(Data!$B$2:$B$1833,$L89,Data!$C$2:$C$1833,$M89,Data!$D$2:$D$1833,$N89,Data!$E$2:$E$1833,$O89,Data!$F$2:$F$1833,$F89,Data!$H$2:$H$1833,1) -> 1 | H89: 127 | I89: =INDEX(Data!$G$2:$G$1833,MATCH($H89,Data!$A$2:$A$1833,0)) -> Can scan quickly through several sources (articles, reports, websites, books, etc.) in parallel, in both their own field and in related fields, and can identify the relevance and usefulness of particular sections for the task at hand. | J89: 自分の分野と関連分野の複数の情報源（記事、報告書、ウェブサイト、書籍など）を並行して素早く走査し、目下の課題に対する各部分の関連性と有用性を特定できる。 | L89: Communicative language activities | M89: Reception | N89: Reading comprehension | O89: Reading for orientation
F90: C1 | G90: =COUNTIFS(Data!$B$2:$B$1833,$L90,Data!$C$2:$C$1833,$M90,Data!$D$2:$D$1833,$N90,Data!$E$2:$E$1833,$O90,Data!$F$2:$F$1833,$F90,Data!$H$2:$H$1833,1) -> 0 | H90: — | I90: — | J90: — | L90: Communicative language activities | M90: Reception | N90: Reading comprehension | O90: Reading for orientation
F91: C2 | G91: =COUNTIFS(Data!$B$2:$B$1833,$L91,Data!$C$2:$C$1833,$M91,Data!$D$2:$D$1833,$N91,Data!$E$2:$E$1833,$O91,Data!$F$2:$F$1833,$F91,Data!$H$2:$H$1833,1) -> 0 | H91: — | I91: — | J91: — | L91: Communicative language activities | M91: Reception | N91: Reading comprehension | O91: Reading for orientation
A92: =IFERROR(INDEX(対訳マスタ!$C$2:$C$136,MATCH($L92,対訳マスタ!$B$2:$B$136,0)),$L92) -> コミュニケーション言語活動 | B92: =IF($M92="—","—",IFERROR(INDEX(対訳マスタ!$C$2:$C$136,MATCH($M92,対訳マスタ!$B$2:$B$136,0)),$M92)) -> 受容 | C92: =IF($N92="—","—",IFERROR(INDEX(対訳マスタ!$C$2:$C$136,MATCH($N92,対訳マスタ!$B$2:$B$136,0)),$N92)) -> 読解（読むこと） | D92: =IFERROR(INDEX(対訳マスタ!$C$2:$C$136,MATCH($O92,対訳マスタ!$B$2:$B$136,0)),$O92) -> 情報・論旨の読み取り | E92: Reading for information and argument | F92: Pre-A1 | G92: =COUNTIFS(Data!$B$2:$B$1833,$L92,Data!$C$2:$C$1833,$M92,Data!$D$2:$D$1833,$N92,Data!$E$2:$E$1833,$O92,Data!$F$2:$F$1833,$F92,Data!$H$2:$H$1833,1) -> 1 | H92: 172 | I92: =INDEX(Data!$G$2:$G$1833,MATCH($H92,Data!$A$2:$A$1833,0)) -> Can understand the simplest informational material such as a fast-food restaurant menu illustrated with photos or an illustrated story formulated in very simple everyday words/signs. | J92: 写真つきのファストフード店のメニューや、ごく簡単な日常語で書かれた絵物語のような、最も簡単な案内資料を理解できる。 | L92: Communicative language activities | M92: Reception | N92: Reading comprehension | O92: Reading for information and argument
F93: A1 | G93: =COUNTIFS(Data!$B$2:$B$1833,$L93,Data!$C$2:$C$1833,$M93,Data!$D$2:$D$1833,$N93,Data!$E$2:$E$1833,$O93,Data!$F$2:$F$1833,$F93,Data!$H$2:$H$1833,1) -> 2 | H93: 170 | I93: =INDEX(Data!$G$2:$G$1833,MATCH($H93,Data!$A$2:$A$1833,0)) -> Can get an idea of the content of simpler informational material and short, simple descriptions, especially if there is visual support. | J93: 特に視覚的補助があれば、簡単な案内資料や短く簡単な説明の内容の見当をつけられる。 | L93: Communicative language activities | M93: Reception | N93: Reading comprehension | O93: Reading for information and argument
F94: A2 | G94: =COUNTIFS(Data!$B$2:$B$1833,$L94,Data!$C$2:$C$1833,$M94,Data!$D$2:$D$1833,$N94,Data!$E$2:$E$1833,$O94,Data!$F$2:$F$1833,$F94,Data!$H$2:$H$1833,1) -> 5 | H94: 166 | I94: =INDEX(Data!$G$2:$G$1833,MATCH($H94,Data!$A$2:$A$1833,0)) -> Can understand information given in illustrated brochures and maps (e.g. the principal attractions of a city). | J94: 絵入りのパンフレットや地図の情報（都市の主要な見どころなど）を理解できる。 | L94: Communicative language activities | M94: Reception | N94: Reading comprehension | O94: Reading for information and argument
F95: A2+ | G95: =COUNTIFS(Data!$B$2:$B$1833,$L95,Data!$C$2:$C$1833,$M95,Data!$D$2:$D$1833,$N95,Data!$E$2:$E$1833,$O95,Data!$F$2:$F$1833,$F95,Data!$H$2:$H$1833,1) -> 4 | H95: 164 | I95: =INDEX(Data!$G$2:$G$1833,MATCH($H95,Data!$A$2:$A$1833,0)) -> Can understand the main points of short texts dealing with everyday topics (e.g. lifestyle, hobbies, sports, weather). | J95: 日常の話題（生活様式、趣味、スポーツ、天気など）を扱う短いテキストの要点を理解できる。 | L95: Communicative language activities | M95: Reception | N95: Reading comprehension | O95: Reading for information and argument
F96: B1 | G96: =COUNTIFS(Data!$B$2:$B$1833,$L96,Data!$C$2:$C$1833,$M96,Data!$D$2:$D$1833,$N96,Data!$E$2:$E$1833,$O96,Data!$F$2:$F$1833,$F96,Data!$H$2:$H$1833,1) -> 3 | H96: 158 | I96: =INDEX(Data!$G$2:$G$1833,MATCH($H96,Data!$A$2:$A$1833,0)) -> Can recognise significant points in straightforward news articles on familiar subjects. | J96: 身近な主題の率直な新聞記事の重要な点を認識できる。 | L96: Communicative language activities | M96: Reception | N96: Reading comprehension | O96: Reading for information and argument
F97: B1+ | G97: =COUNTIFS(Data!$B$2:$B$1833,$L97,Data!$C$2:$C$1833,$M97,Data!$D$2:$D$1833,$N97,Data!$E$2:$E$1833,$O97,Data!$F$2:$F$1833,$F97,Data!$H$2:$H$1833,1) -> 4 | H97: 156 | I97: =INDEX(Data!$G$2:$G$1833,MATCH($H97,Data!$A$2:$A$1833,0)) -> Can identify the main conclusions in clearly signalled argumentative texts. | J97: 論の構成が明示された論説文の主な結論を特定できる。 | L97: Communicative language activities | M97: Reception | N97: Reading comprehension | O97: Reading for information and argument
F98: B2 | G98: =COUNTIFS(Data!$B$2:$B$1833,$L98,Data!$C$2:$C$1833,$M98,Data!$D$2:$D$1833,$N98,Data!$E$2:$E$1833,$O98,Data!$F$2:$F$1833,$F98,Data!$H$2:$H$1833,1) -> 3 | H98: 152 | I98: =INDEX(Data!$G$2:$G$1833,MATCH($H98,Data!$A$2:$A$1833,0)) -> Can recognise when a text provides factual information and when it seeks to convince readers of something. | J98: テキストが事実情報を提供しているのか、読者を説得しようとしているのかを見分けられる。 | L98: Communicative language activities | M98: Reception | N98: Reading comprehension | O98: Reading for information and argument
F99: B2+ | G99: =COUNTIFS(Data!$B$2:$B$1833,$L99,Data!$C$2:$C$1833,$M99,Data!$D$2:$D$1833,$N99,Data!$E$2:$E$1833,$O99,Data!$F$2:$F$1833,$F99,Data!$H$2:$H$1833,1) -> 2 | H99: 149 | I99: =INDEX(Data!$G$2:$G$1833,MATCH($H99,Data!$A$2:$A$1833,0)) -> Can obtain information, ideas and opinions from highly specialised sources within their field. | J99: 自分の分野の高度に専門的な情報源から、情報・アイディア・意見を得られる。 | L99: Communicative language activities | M99: Reception | N99: Reading comprehension | O99: Reading for information and argument
F100: C1 | G100: =COUNTIFS(Data!$B$2:$B$1833,$L100,Data!$C$2:$C$1833,$M100,Data!$D$2:$D$1833,$N100,Data!$E$2:$E$1833,$O100,Data!$F$2:$F$1833,$F100,Data!$H$2:$H$1833,1) -> 1 | H100: 148 | I100: =INDEX(Data!$G$2:$G$1833,MATCH($H100,Data!$A$2:$A$1833,0)) -> Can understand in detail a wide range of lengthy, complex texts likely to be encountered in social, professional or academic life, identifying finer points of detail including attitudes and implied as well as stated opinions. | J100: 社会・職業・学術生活で出会いそうな長く複雑な幅広いテキストを詳細に理解し、態度や、明示された意見だけでなく暗示された意見も含め、細かな点を特定できる。 | L100: Communicative language activities | M100: Reception | N100: Reading comprehension | O100: Reading for information and argument
...

Sheet Data（日本語訳）
A1: No | B1: スキーム | C1: モード | D1: 活動・方略・能力の種別 | E1: スケール（作業訳） | F1: レベル | G1: 記述文（英文） | H1: 記述文（和訳・作業訳） | I1: 訳出状況
A2: =Data!A2 -> 1 | B2: =IFERROR(INDEX(対訳マスタ!$C$2:$C$136,MATCH(Data!B2,対訳マスタ!$B$2:$B$136,0)),Data!B2) -> コミュニケーション言語活動 | C2: =IF(Data!C2="—","—",IFERROR(INDEX(対訳マスタ!$C$2:$C$136,MATCH(Data!C2,対訳マスタ!$B$2:$B$136,0)),Data!C2)) -> 受容 | D2: =IF(Data!D2="—","—",IFERROR(INDEX(対訳マスタ!$C$2:$C$136,MATCH(Data!D2,対訳マスタ!$B$2:$B$136,0)),Data!D2)) -> 口頭理解（聞くこと） | E2: =IFERROR(INDEX(対訳マスタ!$C$2:$C$136,MATCH(Data!E2,対訳マスタ!$B$2:$B$136,0)),Data!E2) -> 口頭理解（総合） | F2: =Data!F2 -> C2 | G2: =Data!G2 -> Can understand with ease virtually any kind of language, whether live or broadcast, delivered at fast natural speed. | H2: 生の発話でも放送でも、速い自然な速度で話されるほぼあらゆる種類の言葉を容易に理解できる。 | I2: 済
A3: =Data!A3 -> 2 | B3: =IFERROR(INDEX(対訳マスタ!$C$2:$C$136,MATCH(Data!B3,対訳マスタ!$B$2:$B$136,0)),Data!B3) -> コミュニケーション言語活動 | C3: =IF(Data!C3="—","—",IFERROR(INDEX(対訳マスタ!$C$2:$C$136,MATCH(Data!C3,対訳マスタ!$B$2:$B$136,0)),Data!C3)) -> 受容 | D3: =IF(Data!D3="—","—",IFERROR(INDEX(対訳マスタ!$C$2:$C$136,MATCH(Data!D3,対訳マスタ!$B$2:$B$136,0)),Data!D3)) -> 口頭理解（聞くこと） | E3: =IFERROR(INDEX(対訳マスタ!$C$2:$C$136,MATCH(Data!E3,対訳マスタ!$B$2:$B$136,0)),Data!E3) -> 口頭理解（総合） | F3: =Data!F3 -> C1 | G3: =Data!G3 -> Can understand enough to follow extended discourse on abstract and complex topics beyond their own field, though they may need to confirm occasional details, especially if the variety is unfamiliar. | H3: あまり馴染みのない変種の場合は特に、時折細部の確認が必要なことはあっても、自分の分野を超えた抽象的で複雑な話題の長い談話を追える程度に理解できる。 | I3: 済
A4: =Data!A4 -> 3 | B4: =IFERROR(INDEX(対訳マスタ!$C$2:$C$136,MATCH(Data!B4,対訳マスタ!$B$2:$B$136,0)),Data!B4) -> コミュニケーション言語活動 | C4: =IF(Data!C4="—","—",IFERROR(INDEX(対訳マスタ!$C$2:$C$136,MATCH(Data!C4,対訳マスタ!$B$2:$B$136,0)),Data!C4)) -> 受容 | D4: =IF(Data!D4="—","—",IFERROR(INDEX(対訳マスタ!$C$2:$C$136,MATCH(Data!D4,対訳マスタ!$B$2:$B$136,0)),Data!D4)) -> 口頭理解（聞くこと） | E4: =IFERROR(INDEX(対訳マスタ!$C$2:$C$136,MATCH(Data!E4,対訳マスタ!$B$2:$B$136,0)),Data!E4) -> 口頭理解（総合） | F4: =Data!F4 -> C1 | G4: =Data!G4 -> Can recognise a wide range of idiomatic expressions and colloquialisms, appreciating register shifts. | H4: 幅広い慣用表現や口語表現を認識し、言語使用域（レジスター）の変化を感じ取れる。 | I4: 済
A5: =Data!A5 -> 4 | B5: =IFERROR(INDEX(対訳マスタ!$C$2:$C$136,MATCH(Data!B5,対訳マスタ!$B$2:$B$136,0)),Data!B5) -> コミュニケーション言語活動 | C5: =IF(Data!C5="—","—",IFERROR(INDEX(対訳マスタ!$C$2:$C$136,MATCH(Data!C5,対訳マスタ!$B$2:$B$136,0)),Data!C5)) -> 受容 | D5: =IF(Data!D5="—","—",IFERROR(INDEX(対訳マスタ!$C$2:$C$136,MATCH(Data!D5,対訳マスタ!$B$2:$B$136,0)),Data!D5)) -> 口頭理解（聞くこと） | E5: =IFERROR(INDEX(対訳マスタ!$C$2:$C$136,MATCH(Data!E5,対訳マスタ!$B$2:$B$136,0)),Data!E5) -> 口頭理解（総合） | F5: =Data!F5 -> C1 | G5: =Data!G5 -> Can follow extended discourse even when it is not clearly structured and when relationships are only implied and not signalled explicitly. | H5: 明確に構成されておらず、関係が明示されず暗示されるだけであっても、長い談話を追える。 | I5: 済
A6: =Data!A6 -> 5 | B6: =IFERROR(INDEX(対訳マスタ!$C$2:$C$136,MATCH(Data!B6,対訳マスタ!$B$2:$B$136,0)),Data!B6) -> コミュニケーション言語活動 | C6: =IF(Data!C6="—","—",IFERROR(INDEX(対訳マスタ!$C$2:$C$136,MATCH(Data!C6,対訳マスタ!$B$2:$B$136,0)),Data!C6)) -> 受容 | D6: =IF(Data!D6="—","—",IFERROR(INDEX(対訳マスタ!$C$2:$C$136,MATCH(Data!D6,対訳マスタ!$B$2:$B$136,0)),Data!D6)) -> 口頭理解（聞くこと） | E6: =IFERROR(INDEX(対訳マスタ!$C$2:$C$136,MATCH(Data!E6,対訳マスタ!$B$2:$B$136,0)),Data!E6) -> 口頭理解（総合） | F6: =Data!F6 -> B2+ | G6: =Data!G6 -> Can understand standard language or a familiar variety, live or broadcast, on both familiar and unfamiliar topics normally encountered in personal, social, academic or vocational life. Only extreme [auditory/visual] background noise, inadequate discourse structure and/or idiomatic usage influence the ability to understand. | H6: 標準語または馴染みのある変種であれば、個人・社会・学業・職業生活で普通に出会う話題について、身近でも未知でも、生でも放送でも理解できる。極端な雑音、不十分な談話構成、慣用表現の多用だけが理解力に影響する。 | I6: 済
A7: =Data!A7 -> 6 | B7: =IFERROR(INDEX(対訳マスタ!$C$2:$C$136,MATCH(Data!B7,対訳マスタ!$B$2:$B$136,0)),Data!B7) -> コミュニケーション言語活動 | C7: =IF(Data!C7="—","—",IFERROR(INDEX(対訳マスタ!$C$2:$C$136,MATCH(Data!C7,対訳マスタ!$B$2:$B$136,0)),Data!C7)) -> 受容 | D7: =IF(Data!D7="—","—",IFERROR(INDEX(対訳マスタ!$C$2:$C$136,MATCH(Data!D7,対訳マスタ!$B$2:$B$136,0)),Data!D7)) -> 口頭理解（聞くこと） | E7: =IFERROR(INDEX(対訳マスタ!$C$2:$C$136,MATCH(Data!E7,対訳マスタ!$B$2:$B$136,0)),Data!E7) -> 口頭理解（総合） | F7: =Data!F7 -> B2 | G7: =Data!G7 -> Can understand the main ideas of propositionally and linguistically complex discourse on both concrete and abstract topics delivered in standard language or a familiar variety, including technical discussions in their field of specialisation. | H7: 標準語または馴染みのある変種で話されれば、自分の専門分野の技術的議論を含め、具体的・抽象的な話題の命題的・言語的に複雑な談話の主旨を理解できる。 | I7: 済
A8: =Data!A8 -> 7 | B8: =IFERROR(INDEX(対訳マスタ!$C$2:$C$136,MATCH(Data!B8,対訳マスタ!$B$2:$B$136,0)),Data!B8) -> コミュニケーション言語活動 | C8: =IF(Data!C8="—","—",IFERROR(INDEX(対訳マスタ!$C$2:$C$136,MATCH(Data!C8,対訳マスタ!$B$2:$B$136,0)),Data!C8)) -> 受容 | D8: =IF(Data!D8="—","—",IFERROR(INDEX(対訳マスタ!$C$2:$C$136,MATCH(Data!D8,対訳マスタ!$B$2:$B$136,0)),Data!D8)) -> 口頭理解（聞くこと） | E8: =IFERROR(INDEX(対訳マスタ!$C$2:$C$136,MATCH(Data!E8,対訳マスタ!$B$2:$B$136,0)),Data!E8) -> 口頭理解（総合） | F8: =Data!F8 -> B2 | G8: =Data!G8 -> Can follow extended discourse and complex lines of argument, provided the topic is reasonably familiar, and the direction of the argument is signposted by explicit markers. | H8: 話題がある程度身近で、議論の方向が明示的な標識で示されていれば、長い談話や複雑な論の展開を追える。 | I8: 済
A9: =Data!A9 -> 8 | B9: =IFERROR(INDEX(対訳マスタ!$C$2:$C$136,MATCH(Data!B9,対訳マスタ!$B$2:$B$136,0)),Data!B9) -> コミュニケーション言語活動 | C9: =IF(Data!C9="—","—",IFERROR(INDEX(対訳マスタ!$C$2:$C$136,MATCH(Data!C9,対訳マスタ!$B$2:$B$136,0)),Data!C9)) -> 受容 | D9: =IF(Data!D9="—","—",IFERROR(INDEX(対訳マスタ!$C$2:$C$136,MATCH(Data!D9,対訳マスタ!$B$2:$B$136,0)),Data!D9)) -> 口頭理解（聞くこと） | E9: =IFERROR(INDEX(対訳マスタ!$C$2:$C$136,MATCH(Data!E9,対訳マスタ!$B$2:$B$136,0)),Data!E9) -> 口頭理解（総合） | F9: =Data!F9 -> B1+ | G9: =Data!G9 -> Can understand straightforward factual information about common everyday or job-related topics, identifying both general messages and specific details, provided people articulate clearly in a generally familiar variety. | H9: 日常や仕事に関わる一般的な話題について、馴染みのある変種で明瞭に発音されていれば、全体の趣旨と具体的詳細の両方を聞き取り、率直な事実情報を理解できる。 | I9: 済
A10: =Data!A10 -> 9 | B10: =IFERROR(INDEX(対訳マスタ!$C$2:$C$136,MATCH(Data!B10,対訳マスタ!$B$2:$B$136,0)),Data!B10) -> コミュニケーション言語活動 | C10: =IF(Data!C10="—","—",IFERROR(INDEX(対訳マスタ!$C$2:$C$136,MATCH(Data!C10,対訳マスタ!$B$2:$B$136,0)),Data!C10)) -> 受容 | D10: =IF(Data!D10="—","—",IFERROR(INDEX(対訳マスタ!$C$2:$C$136,MATCH(Data!D10,対訳マスタ!$B$2:$B$136,0)),Data!D10)) -> 口頭理解（聞くこと） | E10: =IFERROR(INDEX(対訳マスタ!$C$2:$C$136,MATCH(Data!E10,対訳マスタ!$B$2:$B$136,0)),Data!E10) -> 口頭理解（総合） | F10: =Data!F10 -> B1 | G10: =Data!G10 -> Can understand the main points made in clear standard language or a familiar variety on familiar matters regularly encountered at work, school, leisure, etc., including short narratives. | H10: 仕事・学校・余暇などで日常的に出会う身近な事柄について、明瞭な標準語か馴染みのある変種で話されれば、短い物語を含め要点を理解できる。 | I10: 済
A11: =Data!A11 -> 10 | B11: =IFERROR(INDEX(対訳マスタ!$C$2:$C$136,MATCH(Data!B11,対訳マスタ!$B$2:$B$136,0)),Data!B11) -> コミュニケーション言語活動 | C11: =IF(Data!C11="—","—",IFERROR(INDEX(対訳マスタ!$C$2:$C$136,MATCH(Data!C11,対訳マスタ!$B$2:$B$136,0)),Data!C11)) -> 受容 | D11: =IF(Data!D11="—","—",IFERROR(INDEX(対訳マスタ!$C$2:$C$136,MATCH(Data!D11,対訳マスタ!$B$2:$B$136,0)),Data!D11)) -> 口頭理解（聞くこと） | E11: =IFERROR(INDEX(対訳マスタ!$C$2:$C$136,MATCH(Data!E11,対訳マスタ!$B$2:$B$136,0)),Data!E11) -> 口頭理解（総合） | F11: =Data!F11 -> A2+ | G11: =Data!G11 -> Can understand enough to be able to meet needs of a concrete type, provided people articulate clearly and slowly. | H11: 明瞭にゆっくり話してもらえれば、具体的な必要を満たせる程度に理解できる。 | I11: 済
A12: =Data!A12 -> 11 | B12: =IFERROR(INDEX(対訳マスタ!$C$2:$C$136,MATCH(Data!B12,対訳マスタ!$B$2:$B$136,0)),Data!B12) -> コミュニケーション言語活動 | C12: =IF(Data!C12="—","—",IFERROR(INDEX(対訳マスタ!$C$2:$C$136,MATCH(Data!C12,対訳マスタ!$B$2:$B$136,0)),Data!C12)) -> 受容 | D12: =IF(Data!D12="—","—",IFERROR(INDEX(対訳マスタ!$C$2:$C$136,MATCH(Data!D12,対訳マスタ!$B$2:$B$136,0)),Data!D12)) -> 口頭理解（聞くこと） | E12: =IFERROR(INDEX(対訳マスタ!$C$2:$C$136,MATCH(Data!E12,対訳マスタ!$B$2:$B$136,0)),Data!E12) -> 口頭理解（総合） | F12: =Data!F12 -> A2 | G12: =Data!G12 -> Can understand phrases and expressions related to areas of most immediate priority (e.g. very basic personal and family information, shopping, local geography, employment), provided people articulate clearly and slowly. | H12: 最も差し迫った領域（ごく基本的な個人・家族情報、買い物、地元の地理、仕事など）に関わる句や表現を、明瞭にゆっくり話されれば理解できる。 | I12: 済
A13: =Data!A13 -> 12 | B13: =IFERROR(INDEX(対訳マスタ!$C$2:$C$136,MATCH(Data!B13,対訳マスタ!$B$2:$B$136,0)),Data!B13) -> コミュニケーション言語活動 | C13: =IF(Data!C13="—","—",IFERROR(INDEX(対訳マスタ!$C$2:$C$136,MATCH(Data!C13,対訳マスタ!$B$2:$B$136,0)),Data!C13)) -> 受容 | D13: =IF(Data!D13="—","—",IFERROR(INDEX(対訳マスタ!$C$2:$C$136,MATCH(Data!D13,対訳マスタ!$B$2:$B$136,0)),Data!D13)) -> 口頭理解（聞くこと） | E13: =IFERROR(INDEX(対訳マスタ!$C$2:$C$136,MATCH(Data!E13,対訳マスタ!$B$2:$B$136,0)),Data!E13) -> 口頭理解（総合） | F13: =Data!F13 -> A1 | G13: =Data!G13 -> Can follow language which is very slow and carefully articulated, with long pauses for them to assimilate meaning. | H13: 非常にゆっくり注意深く発音され、意味を消化するための長い間が置かれれば、言葉についていける。 | I13: 済
... A1334: =Data!A1334 -> 1333 | B1334: =IFERROR(INDEX(対訳マスタ!$C$2:$C$136,MATCH(Data!B1334,対訳マスタ!$B$2:$B$136,0)),Data!B1334) -> コミュニケーション言語能力 | C1334: =IF(Data!C1334="—","—",IFERROR(INDEX(対訳マスタ!$C$2:$C$136,MATCH(Data!C1334,対訳マスタ!$B$2:$B$136,0)),Data!C1334)) -> — | D1334: =IF(Data!D1334="—","—",IFERROR(INDEX(対訳マスタ!$C$2:$C$136,MATCH(Data!D1334,対訳マスタ!$B$2:$B$136,0)),Data!D1334)) -> 語用能力 | E1334: =IFERROR(INDEX(対訳マスタ!$C$2:$C$136,MATCH(Data!E1334,対訳マスタ!$B$2:$B$136,0)),Data!E1334) -> 流暢さ | F1334: =Data!F1334 -> Pre-A1 | G1334: =Data!G1334 -> Can manage very short, isolated, rehearsed utterances using gesture and signalled requests for help when necessary. | H1334: 必要に応じて身振りや助けを求める合図を使いながら、ごく短い、孤立した、練習済みの発話を何とか使える。 | I1334: 済
A1335: =Data!A1335 -> 1334 | B1335: =IFERROR(INDEX(対訳マスタ!$C$2:$C$136,MATCH(Data!B1335,対訳マスタ!$B$2:$B$136,0)),Data!B1335) -> 手話能力 | C1335: =IF(Data!C1335="—","—",IFERROR(INDEX(対訳マスタ!$C$2:$C$136,MATCH(Data!C1335,対訳マスタ!$B$2:$B$136,0)),Data!C1335)) -> 受容 | D1335: =IF(Data!D1335="—","—",IFERROR(INDEX(対訳マスタ!$C$2:$C$136,MATCH(Data!D1335,対訳マスタ!$B$2:$B$136,0)),Data!D1335)) -> 言語能力 | E1335: =IFERROR(INDEX(対訳マスタ!$C$2:$C$136,MATCH(Data!E1335,対訳マスタ!$B$2:$B$136,0)),Data!E1335) -> 手話レパートリー | F1335: =Data!F1335 -> C2 | G1335: =Data!G1335 -> Can understand abstract concepts, e.g., from the field of science, and assign them to the appropriate context. | I1335: 対象外
A1336: =Data!A1336 -> 1335 | B1336: =IFERROR(INDEX(対訳マスタ!$C$2:$C$136,MATCH(Data!B1336,対訳マスタ!$B$2:$B$136,0)),Data!B1336) -> 手話能力 | C1336: =IF(Data!C1336="—","—",IFERROR(INDEX(対訳マスタ!$C$2:$C$136,MATCH(Data!C1336,対訳マスタ!$B$2:$B$136,0)),Data!C1336)) -> 受容 | D1336: =IF(Data!D1336="—","—",IFERROR(INDEX(対訳マスタ!$C$2:$C$136,MATCH(Data!D1336,対訳マスタ!$B$2:$B$136,0)),Data!D1336)) -> 言語能力 | E1336: =IFERROR(INDEX(対訳マスタ!$C$2:$C$136,MATCH(Data!E1336,対訳マスタ!$B$2:$B$136,0)),Data!E1336) -> 手話レパートリー | F1336: =Data!F1336 -> C2 | G1336: =Data!G1336 -> Can understand creative or newly coined descriptions of phenomena (e.g. a UFO). | I1336: 対象外
A1337: =Data!A1337 -> 1336 | B1337: =IFERROR(INDEX(対訳マスタ!$C$2:$C$136,MATCH(Data!B1337,対訳マスタ!$B$2:$B$136,0)),Data!B1337) -> 手話能力 | C1337: =IF(Data!C1337="—","—",IFERROR(INDEX(対訳マスタ!$C$2:$C$136,MATCH(Data!C1337,対訳マスタ!$B$2:$B$136,0)),Data!C1337)) -> 受容 | D1337: =IF(Data!D1337="—","—",IFERROR(INDEX(対訳マスタ!$C$2:$C$136,MATCH(Data!D1337,対訳マスタ!$B$2:$B$136,0)),Data!D1337)) -> 言語能力 | E1337: =IFERROR(INDEX(対訳マスタ!$C$2:$C$136,MATCH(Data!E1337,対訳マスタ!$B$2:$B$136,0)),Data!E1337) -> 手話レパートリー | F1337: =Data!F1337 -> C2 | G1337: =Data!G1337 -> Can understand challenging texts on a range of topics and explain what they are about. | I1337: 対象外
A1338: =Data!A1338 -> 1337 | B1338: =IFERROR(INDEX(対訳マスタ!$C$2:$C$136,MATCH(Data!B1338,対訳マスタ!$B$2:$B$136,0)),Data!B1338) -> 手話能力 | C1338: =IF(Data!C1338="—","—",IFERROR(INDEX(対訳マスタ!$C$2:$C$136,MATCH(Data!C1338,対訳マスタ!$B$2:$B$136,0)),Data!C1338)) -> 受容 | D1338: =IF(Data!D1338="—","—",IFERROR(INDEX(対訳マスタ!$C$2:$C$136,MATCH(Data!D1338,対訳マスタ!$B$2:$B$136,0)),Data!D1338)) -> 言語能力 | E1338: =IFERROR(INDEX(対訳マスタ!$C$2:$C$136,MATCH(Data!E1338,対訳マスタ!$B$2:$B$136,0)),Data!E1338) -> 手話レパートリー | F1338: =Data!F1338 -> C1 | G1338: =Data!G1338 -> Can understand the meaning of mouthings in context. | I1338: 対象外
A1339: =Data!A1339 -> 1338 | B1339: =IFERROR(INDEX(対訳マスタ!$C$2:$C$136,MATCH(Data!B1339,対訳マスタ!$B$2:$B$136,0)),Data!B1339) -> 手話能力 | C1339: =IF(Data!C1339="—","—",IFERROR(INDEX(対訳マスタ!$C$2:$C$136,MATCH(Data!C1339,対訳マスタ!$B$2:$B$136,0)),Data!C1339)) -> 受容 | D1339: =IF(Data!D1339="—","—",IFERROR(INDEX(対訳マスタ!$C$2:$C$136,MATCH(Data!D1339,対訳マスタ!$B$2:$B$136,0)),Data!D1339)) -> 言語能力 | E1339: =IFERROR(INDEX(対訳マスタ!$C$2:$C$136,MATCH(Data!E1339,対訳マスタ!$B$2:$B$136,0)),Data!E1339) -> 手話レパートリー | F1339: =Data!F1339 -> C1 | G1339: =Data!G1339 -> Can understand technical texts in their own field and make use of the information, ideas or opinions in them. | I1339: 対象外
A1340: =Data!A1340 -> 1339 | B1340: =IFERROR(INDEX(対訳マスタ!$C$2:$C$136,MATCH(Data!B1340,対訳マスタ!$B$2:$B$136,0)),Data!B1340) -> 手話能力 | C1340: =IF(Data!C1340="—","—",IFERROR(INDEX(対訳マスタ!$C$2:$C$136,MATCH(Data!C1340,対訳マスタ!$B$2:$B$136,0)),Data!C1340)) -> 受容 | D1340: =IF(Data!D1340="—","—",IFERROR(INDEX(対訳マスタ!$C$2:$C$136,MATCH(Data!D1340,対訳マスタ!$B$2:$B$136,0)),Data!D1340)) -> 言語能力 | E1340: =IFERROR(INDEX(対訳マスタ!$C$2:$C$136,MATCH(Data!E1340,対訳マスタ!$B$2:$B$136,0)),Data!E1340) -> 手話レパートリー | F1340: =Data!F1340 -> C1 | G1340: =Data!G1340 -> Can understand specific, precise instructions, wishes, recommendations, etc. | I1340: 対象外
A1341: =Data!A1341 -> 1340 | B1341: =IFERROR(INDEX(対訳マスタ!$C$2:$C$136,MATCH(Data!B1341,対訳マスタ!$B$2:$B$136,0)),Data!B1341) -> 手話能力 | C1341: =IF(Data!C1341="—","—",IFERROR(INDEX(対訳マスタ!$C$2:$C$136,MATCH(Data!C1341,対訳マスタ!$B$2:$B$136,0)),Data!C1341)) -> 受容 | D1341: =IF(Data!D1341="—","—",IFERROR(INDEX(対訳マスタ!$C$2:$C$136,MATCH(Data!D1341,対訳マスタ!$B$2:$B$136,0)),Data!D1341)) -> 言語能力 | E1341: =IFERROR(INDEX(対訳マスタ!$C$2:$C$136,MATCH(Data!E1341,対訳マスタ!$B$2:$B$136,0)),Data!E1341) -> 手話レパートリー | F1341: =Data!F1341 -> B2+ | G1341: =Data!G1341 -> Can understand and correctly attribute signed names for commonly known persons and institutions. | I1341: 対象外
A1342: =Data!A1342 -> 1341 | B1342: =IFERROR(INDEX(対訳マスタ!$C$2:$C$136,MATCH(Data!B1342,対訳マスタ!$B$2:$B$136,0)),Data!B1342) -> 手話能力 | C1342: =IF(Data!C1342="—","—",IFERROR(INDEX(対訳マスタ!$C$2:$C$136,MATCH(Data!C1342,対訳マスタ!$B$2:$B$136,0)),Data!C1342)) -> 受容 | D1342: =IF(Data!D1342="—","—",IFERROR(INDEX(対訳マスタ!$C$2:$C$136,MATCH(Data!D1342,対訳マスタ!$B$2:$B$136,0)),Data!D1342)) -> 言語能力 | E1342: =IFERROR(INDEX(対訳マスタ!$C$2:$C$136,MATCH(Data!E1342,対訳マスタ!$B$2:$B$136,0)),Data!E1342) -> 手話レパートリー | F1342: =Data!F1342 -> B2+ | G1342: =Data!G1342 -> Can differentiate nuances of meaning that are expressed with specific handshapes. | I1342: 対象外
A1343: =Data!A1343 -> 1342 | B1343: =IFERROR(INDEX(対訳マスタ!$C$2:$C$136,MATCH(Data!B1343,対訳マスタ!$B$2:$B$136,0)),Data!B1343) -> 手話能力 | C1343: =IF(Data!C1343="—","—",IFERROR(INDEX(対訳マスタ!$C$2:$C$136,MATCH(Data!C1343,対訳マスタ!$B$2:$B$136,0)),Data!C1343)) -> 受容 | D1343: =IF(Data!D1343="—","—",IFERROR(INDEX(対訳マスタ!$C$2:$C$136,MATCH(Data!D1343,対訳マスタ!$B$2:$B$136,0)),Data!D1343)) -> 言語能力 | E1343: =IFERROR(INDEX(対訳マスタ!$C$2:$C$136,MATCH(Data!E1343,対訳マスタ!$B$2:$B$136,0)),Data!E1343) -> 手話レパートリー | F1343: =Data!F1343 -> B2+ | G1343: =Data!G1343 -> Can understand idioms (and signs particular to the local community). | I1343: 対象外
A1344: =Data!A1344 -> 1343 | B1344: =IFERROR(INDEX(対訳マスタ!$C$2:$C$136,MATCH(Data!B1344,対訳マスタ!$B$2:$B$136,0)),Data!B1344) -> 手話能力 | C1344: =IF(Data!C1344="—","—",IFERROR(INDEX(対訳マスタ!$C$2:$C$136,MATCH(Data!C1344,対訳マスタ!$B$2:$B$136,0)),Data!C1344)) -> 受容 | D1344: =IF(Data!D1344="—","—",IFERROR(INDEX(対訳マスタ!$C$2:$C$136,MATCH(Data!D1344,対訳マスタ!$B$2:$B$136,0)),Data!D1344)) -> 言語能力 | E1344: =IFERROR(INDEX(対訳マスタ!$C$2:$C$136,MATCH(Data!E1344,対訳マスタ!$B$2:$B$136,0)),Data!E1344) -> 手話レパートリー | F1344: =Data!F1344 -> B2+ | G1344: =Data!G1344 -> Can understand what is meant when the signer paraphrases without producing the sign for the concept concerned. | I1344: 対象外
A1345: =Data!A1345 -> 1344 | B1345: =IFERROR(INDEX(対訳マスタ!$C$2:$C$136,MATCH(Data!B1345,対訳マスタ!$B$2:$B$136,0)),Data!B1345) -> 手話能力 | C1345: =IF(Data!C1345="—","—",IFERROR(INDEX(対訳マスタ!$C$2:$C$136,MATCH(Data!C1345,対訳マスタ!$B$2:$B$136,0)),Data!C1345)) -> 受容 | D1345: =IF(Data!D1345="—","—",IFERROR(INDEX(対訳マスタ!$C$2:$C$136,MATCH(Data!D1345,対訳マスタ!$B$2:$B$136,0)),Data!D1345)) -> 言語能力 | E1345: =IFERROR(INDEX(対訳マスタ!$C$2:$C$136,MATCH(Data!E1345,対訳マスタ!$B$2:$B$136,0)),Data!E1345) -> 手話レパートリー | F1345: =Data!F1345 -> B2 | G1345: =Data!G1345 -> Can understand a large number of signs employed in everyday situations. | I1345: 対象外
A1346: =Data!A1346 -> 1345 | B1346: =IFERROR(INDEX(対訳マスタ!$C$2:$C$136,MATCH(Data!B1346,対訳マスタ!$B$2:$B$136,0)),Data!B1346) -> 手話能力 | C1346: =IF(Data!C1346="—","—",IFERROR(INDEX(対訳マスタ!$C$2:$C$136,MATCH(Data!C1346,対訳マスタ!$B$2:$B$136,0)),Data!C1346)) -> 受容 | D1346: =IF(Data!D1346="—","—",IFERROR(INDEX(対訳マスタ!$C$2:$C$136,MATCH(Data!D1346,対訳マスタ!$B$2:$B$136,0)),Data!D1346)) -> 言語能力 | E1346: =IFERROR(INDEX(対訳マスタ!$C$2:$C$136,MATCH(Data!E1346,対訳マスタ!$B$2:$B$136,0)),Data!E1346) -> 手話レパートリー | F1346: =Data!F1346 -> B2 | G1346: =Data!G1346 -> Can deduce the meaning of individual unknown signs through the context of a sentence. | I1346: 対象外
... A1433: =Data!A1433 -> 1432 | B1433: =IFERROR(INDEX(対訳マスタ!$C$2:$C$136,MATCH(Data!B1433,対訳マスタ!$B$2:$B$136,0)),Data!B1433) -> 手話能力 | C1433: =IF(Data!C1433="—","—",IFERROR(INDEX(対訳マスタ!$C$2:$C$136,MATCH(Data!C1433,対訳マスタ!$B$2:$B$136,0)),Data!C1433)) -> 産出 | D1433: =IF(Data!D1433="—","—",IFERROR(INDEX(対訳マスタ!$C$2:$C$136,MATCH(Data!D1433,対訳マスタ!$B$2:$B$136,0)),Data!D1433)) -> 言語能力 | E1433: =IFERROR(INDEX(対訳マスタ!$C$2:$C$136,MATCH(Data!E1433,対訳マスタ!$B$2:$B$136,0)),Data!E1433) -> 手話レパートリー | F1433: =Data!F1433 -> A1 | G1433: =Data!G1433 -> Can state their opinion (agree, disagree). | I1433: 対象外
A1434: =Data!A1434 -> 1433 | B1434: =IFERROR(INDEX(対訳マスタ!$C$2:$C$136,MATCH(Data!B1434,対訳マスタ!$B$2:$B$136,0)),Data!B1434) -> 手話能力 | C1434: =IF(Data!C1434="—","—",IFERROR(INDEX(対訳マスタ!$C$2:$C$136,MATCH(Data!C1434,対訳マスタ!$B$2:$B$136,0)),Data!C1434)) -> 受容 | D1434: =IF(Data!D1434="—","—",IFERROR(INDEX(対訳マスタ!$C$2:$C$136,MATCH(Data!D1434,対訳マスタ!$B$2:$B$136,0)),Data!D1434)) -> 言語能力 | E1434: =IFERROR(INDEX(対訳マスタ!$C$2:$C$136,MATCH(Data!E1434,対訳マスタ!$B$2:$B$136,0)),Data!E1434) -> 空間文法の正確さ | F1434: =Data!F1434 -> C2 | G1434: =Data!G1434 -> No descriptors available; see B2+ | H1434: — | I1434: —
A1435: =Data!A1435 -> 1434 | B1435: =IFERROR(INDEX(対訳マスタ!$C$2:$C$136,MATCH(Data!B1435,対訳マスタ!$B$2:$B$136,0)),Data!B1435) -> 手話能力 | C1435: =IF(Data!C1435="—","—",IFERROR(INDEX(対訳マスタ!$C$2:$C$136,MATCH(Data!C1435,対訳マスタ!$B$2:$B$136,0)),Data!C1435)) -> 受容 | D1435: =IF(Data!D1435="—","—",IFERROR(INDEX(対訳マスタ!$C$2:$C$136,MATCH(Data!D1435,対訳マスタ!$B$2:$B$136,0)),Data!D1435)) -> 言語能力 | E1435: =IFERROR(INDEX(対訳マスタ!$C$2:$C$136,MATCH(Data!E1435,対訳マスタ!$B$2:$B$136,0)),Data!E1435) -> 空間文法の正確さ | F1435: =Data!F1435 -> C1 | G1435: =Data!G1435 -> No descriptors available; see B2+ | H1435: — | I1435: —
A1436: =Data!A1436 -> 1435 | B1436: =IFERROR(INDEX(対訳マスタ!$C$2:$C$136,MATCH(Data!B1436,対訳マスタ!$B$2:$B$136,0)),Data!B1436) -> 手話能力 | C1436: =IF(Data!C1436="—","—",IFERROR(INDEX(対訳マスタ!$C$2:$C$136,MATCH(Data!C1436,対訳マスタ!$B$2:$B$136,0)),Data!C1436)) -> 受容 | D1436: =IF(Data!D1436="—","—",IFERROR(INDEX(対訳マスタ!$C$2:$C$136,MATCH(Data!D1436,対訳マスタ!$B$2:$B$136,0)),Data!D1436)) -> 言語能力 | E1436: =IFERROR(INDEX(対訳マスタ!$C$2:$C$136,MATCH(Data!E1436,対訳マスタ!$B$2:$B$136,0)),Data!E1436) -> 空間文法の正確さ | F1436: =Data!F1436 -> B2+ | G1436: =Data!G1436 -> Can distinguish the various temporal relationships between the actions and events (simultaneous events, previous event, subsequent event). | I1436: 対象外
A1437: =Data!A1437 -> 1436 | B1437: =IFERROR(INDEX(対訳マスタ!$C$2:$C$136,MATCH(Data!B1437,対訳マスタ!$B$2:$B$136,0)),Data!B1437) -> 手話能力 | C1437: =IF(Data!C1437="—","—",IFERROR(INDEX(対訳マスタ!$C$2:$C$136,MATCH(Data!C1437,対訳マスタ!$B$2:$B$136,0)),Data!C1437)) -> 受容 | D1437: =IF(Data!D1437="—","—",IFERROR(INDEX(対訳マスタ!$C$2:$C$136,MATCH(Data!D1437,対訳マスタ!$B$2:$B$136,0)),Data!D1437)) -> 言語能力 | E1437: =IFERROR(INDEX(対訳マスタ!$C$2:$C$136,MATCH(Data!E1437,対訳マスタ!$B$2:$B$136,0)),Data!E1437) -> 空間文法の正確さ | F1437: =Data!F1437 -> B2+ | G1437: =Data!G1437 -> Can distinguish between whether an action involves several people (objects) or many actions involve one person (subject). | I1437: 対象外
A1438: =Data!A1438 -> 1437 | B1438: =IFERROR(INDEX(対訳マスタ!$C$2:$C$136,MATCH(Data!B1438,対訳マスタ!$B$2:$B$136,0)),Data!B1438) -> 手話能力 | C1438: =IF(Data!C1438="—","—",IFERROR(INDEX(対訳マスタ!$C$2:$C$136,MATCH(Data!C1438,対訳マスタ!$B$2:$B$136,0)),Data!C1438)) -> 受容 | D1438: =IF(Data!D1438="—","—",IFERROR(INDEX(対訳マスタ!$C$2:$C$136,MATCH(Data!D1438,対訳マスタ!$B$2:$B$136,0)),Data!D1438)) -> 言語能力 | E1438: =IFERROR(INDEX(対訳マスタ!$C$2:$C$136,MATCH(Data!E1438,対訳マスタ!$B$2:$B$136,0)),Data!E1438) -> 空間文法の正確さ | F1438: =Data!F1438 -> B2+ | G1438: =Data!G1438 -> Can distinguish between direct and indirect speech in signed texts. | I1438: 対象外
A1439: =Data!A1439 -> 1438 | B1439: =IFERROR(INDEX(対訳マスタ!$C$2:$C$136,MATCH(Data!B1439,対訳マスタ!$B$2:$B$136,0)),Data!B1439) -> 手話能力 | C1439: =IF(Data!C1439="—","—",IFERROR(INDEX(対訳マスタ!$C$2:$C$136,MATCH(Data!C1439,対訳マスタ!$B$2:$B$136,0)),Data!C1439)) -> 受容 | D1439: =IF(Data!D1439="—","—",IFERROR(INDEX(対訳マスタ!$C$2:$C$136,MATCH(Data!D1439,対訳マスタ!$B$2:$B$136,0)),Data!D1439)) -> 言語能力 | E1439: =IFERROR(INDEX(対訳マスタ!$C$2:$C$136,MATCH(Data!E1439,対訳マスタ!$B$2:$B$136,0)),Data!E1439) -> 空間文法の正確さ | F1439: =Data!F1439 -> B2+ | G1439: =Data!G1439 -> Can understand statements that contain predicates that take no agent, e.g., “the water is flowing now”. | I1439: 対象外
A1440: =Data!A1440 -> 1439 | B1440: =IFERROR(INDEX(対訳マスタ!$C$2:$C$136,MATCH(Data!B1440,対訳マスタ!$B$2:$B$136,0)),Data!B1440) -> 手話能力 | C1440: =IF(Data!C1440="—","—",IFERROR(INDEX(対訳マスタ!$C$2:$C$136,MATCH(Data!C1440,対訳マスタ!$B$2:$B$136,0)),Data!C1440)) -> 受容 | D1440: =IF(Data!D1440="—","—",IFERROR(INDEX(対訳マスタ!$C$2:$C$136,MATCH(Data!D1440,対訳マスタ!$B$2:$B$136,0)),Data!D1440)) -> 言語能力 | E1440: =IFERROR(INDEX(対訳マスタ!$C$2:$C$136,MATCH(Data!E1440,対訳マスタ!$B$2:$B$136,0)),Data!E1440) -> 空間文法の正確さ | F1440: =Data!F1440 -> B2+ | G1440: =Data!G1440 -> Can recognise rhetorical questions even if linguistically expressed in a very economical way, e.g., by raising the eyebrows. | I1440: 対象外
A1441: =Data!A1441 -> 1440 | B1441: =IFERROR(INDEX(対訳マスタ!$C$2:$C$136,MATCH(Data!B1441,対訳マスタ!$B$2:$B$136,0)),Data!B1441) -> 手話能力 | C1441: =IF(Data!C1441="—","—",IFERROR(INDEX(対訳マスタ!$C$2:$C$136,MATCH(Data!C1441,対訳マスタ!$B$2:$B$136,0)),Data!C1441)) -> 受容 | D1441: =IF(Data!D1441="—","—",IFERROR(INDEX(対訳マスタ!$C$2:$C$136,MATCH(Data!D1441,対訳マスタ!$B$2:$B$136,0)),Data!D1441)) -> 言語能力 | E1441: =IFERROR(INDEX(対訳マスタ!$C$2:$C$136,MATCH(Data!E1441,対訳マスタ!$B$2:$B$136,0)),Data!E1441) -> 空間文法の正確さ | F1441: =Data!F1441 -> B2+ | G1441: =Data!G1441 -> Can assign classifiers to the correct reference object (e.g., animals) through the context. | I1441: 対象外
A1442: =Data!A1442 -> 1441 | B1442: =IFERROR(INDEX(対訳マスタ!$C$2:$C$136,MATCH(Data!B1442,対訳マスタ!$B$2:$B$136,0)),Data!B1442) -> 手話能力 | C1442: =IF(Data!C1442="—","—",IFERROR(INDEX(対訳マスタ!$C$2:$C$136,MATCH(Data!C1442,対訳マスタ!$B$2:$B$136,0)),Data!C1442)) -> 受容 | D1442: =IF(Data!D1442="—","—",IFERROR(INDEX(対訳マスタ!$C$2:$C$136,MATCH(Data!D1442,対訳マスタ!$B$2:$B$136,0)),Data!D1442)) -> 言語能力 | E1442: =IFERROR(INDEX(対訳マスタ!$C$2:$C$136,MATCH(Data!E1442,対訳マスタ!$B$2:$B$136,0)),Data!E1442) -> 空間文法の正確さ | F1442: =Data!F1442 -> B2+ | G1442: =Data!G1442 -> Can understand aspectual modulations (e.g., staggering, fast, creeping or rolling movements). | I1442: 対象外
A1443: =Data!A1443 -> 1442 | B1443: =IFERROR(INDEX(対訳マスタ!$C$2:$C$136,MATCH(Data!B1443,対訳マスタ!$B$2:$B$136,0)),Data!B1443) -> 手話能力 | C1443: =IF(Data!C1443="—","—",IFERROR(INDEX(対訳マスタ!$C$2:$C$136,MATCH(Data!C1443,対訳マスタ!$B$2:$B$136,0)),Data!C1443)) -> 受容 | D1443: =IF(Data!D1443="—","—",IFERROR(INDEX(対訳マスタ!$C$2:$C$136,MATCH(Data!D1443,対訳マスタ!$B$2:$B$136,0)),Data!D1443)) -> 言語能力 | E1443: =IFERROR(INDEX(対訳マスタ!$C$2:$C$136,MATCH(Data!E1443,対訳マスタ!$B$2:$B$136,0)),Data!E1443) -> 空間文法の正確さ | F1443: =Data!F1443 -> B2 | G1443: =Data!G1443 -> Can distinguish on the basis of grammatical signals between statements about real and imaginary events. | I1443: 対象外
A1444: =Data!A1444 -> 1443 | B1444: =IFERROR(INDEX(対訳マスタ!$C$2:$C$136,MATCH(Data!B1444,対訳マスタ!$B$2:$B$136,0)),Data!B1444) -> 手話能力 | C1444: =IF(Data!C1444="—","—",IFERROR(INDEX(対訳マスタ!$C$2:$C$136,MATCH(Data!C1444,対訳マスタ!$B$2:$B$136,0)),Data!C1444)) -> 受容 | D1444: =IF(Data!D1444="—","—",IFERROR(INDEX(対訳マスタ!$C$2:$C$136,MATCH(Data!D1444,対訳マスタ!$B$2:$B$136,0)),Data!D1444)) -> 言語能力 | E1444: =IFERROR(INDEX(対訳マスタ!$C$2:$C$136,MATCH(Data!E1444,対訳マスタ!$B$2:$B$136,0)),Data!E1444) -> 空間文法の正確さ | F1444: =Data!F1444 -> B2 | G1444: =Data!G1444 -> Can keep apart the characters and their actions even in longer texts. | I1444: 対象外
A1445: =Data!A1445 -> 1444 | B1445: =IFERROR(INDEX(対訳マスタ!$C$2:$C$136,MATCH(Data!B1445,対訳マスタ!$B$2:$B$136,0)),Data!B1445) -> 手話能力 | C1445: =IF(Data!C1445="—","—",IFERROR(INDEX(対訳マスタ!$C$2:$C$136,MATCH(Data!C1445,対訳マスタ!$B$2:$B$136,0)),Data!C1445)) -> 受容 | D1445: =IF(Data!D1445="—","—",IFERROR(INDEX(対訳マスタ!$C$2:$C$136,MATCH(Data!D1445,対訳マスタ!$B$2:$B$136,0)),Data!D1445)) -> 言語能力 | E1445: =IFERROR(INDEX(対訳マスタ!$C$2:$C$136,MATCH(Data!E1445,対訳マスタ!$B$2:$B$136,0)),Data!E1445) -> 空間文法の正確さ | F1445: =Data!F1445 -> B2 | G1445: =Data!G1445 -> Can recognise sentences as units and indicate how many sentences a short text contains. | I1445: 対象外
A1446: =Data!A1446 -> 1445 | B1446: =IFERROR(INDEX(対訳マスタ!$C$2:$C$136,MATCH(Data!B1446,対訳マスタ!$B$2:$B$136,0)),Data!B1446) -> 手話能力 | C1446: =IF(Data!C1446="—","—",IFERROR(INDEX(対訳マスタ!$C$2:$C$136,MATCH(Data!C1446,対訳マスタ!$B$2:$B$136,0)),Data!C1446)) -> 受容 | D1446: =IF(Data!D1446="—","—",IFERROR(INDEX(対訳マスタ!$C$2:$C$136,MATCH(Data!D1446,対訳マスタ!$B$2:$B$136,0)),Data!D1446)) -> 言語能力 | E1446: =IFERROR(INDEX(対訳マスタ!$C$2:$C$136,MATCH(Data!E1446,対訳マスタ!$B$2:$B$136,0)),Data!E1446) -> 空間文法の正確さ | F1446: =Data!F1446 -> B2 | G1446: =Data!G1446 -> Can understand verbal aspect (e.g., completion, repetition, continuation, result of actions). | I1446: 対象外
A1447: =Data!A1447 -> 1446 | B1447: =IFERROR(INDEX(対訳マスタ!$C$2:$C$136,MATCH(Data!B1447,対訳マスタ!$B$2:$B$136,0)),Data!B1447) -> 手話能力 | C1447: =IF(Data!C1447="—","—",IFERROR(INDEX(対訳マスタ!$C$2:$C$136,MATCH(Data!C1447,対訳マスタ!$B$2:$B$136,0)),Data!C1447)) -> 受容 | D1447: =IF(Data!D1447="—","—",IFERROR(INDEX(対訳マスタ!$C$2:$C$136,MATCH(Data!D1447,対訳マスタ!$B$2:$B$136,0)),Data!D1447)) -> 言語能力 | E1447: =IFERROR(INDEX(対訳マスタ!$C$2:$C$136,MATCH(Data!E1447,対訳マスタ!$B$2:$B$136,0)),Data!E1447) -> 空間文法の正確さ | F1447: =Data!F1447 -> B1+ | G1447: =Data!G1447 -> Can infer the time, duration or sequence of an event from the timelines employed. | I1447: 対象外
... A1471: =Data!A1471 -> 1470 | B1471: =IFERROR(INDEX(対訳マスタ!$C$2:$C$136,MATCH(Data!B1471,対訳マスタ!$B$2:$B$136,0)),Data!B1471) -> 手話能力 | C1471: =IF(Data!C1471="—","—",IFERROR(INDEX(対訳マスタ!$C$2:$C$136,MATCH(Data!C1471,対訳マスタ!$B$2:$B$136,0)),Data!C1471)) -> 受容 | D1471: =IF(Data!D1471="—","—",IFERROR(INDEX(対訳マスタ!$C$2:$C$136,MATCH(Data!D1471,対訳マスタ!$B$2:$B$136,0)),Data!D1471)) -> 言語能力 | E1471: =IFERROR(INDEX(対訳マスタ!$C$2:$C$136,MATCH(Data!E1471,対訳マスタ!$B$2:$B$136,0)),Data!E1471) -> 空間文法の正確さ | F1471: =Data!F1471 -> A1 | G1471: =Data!G1471 -> Can understand from descriptions of manipulated objects how a signer sets/lays them down or places them. | I1471: 対象外
A1472: =Data!A1472 -> 1471 | B1472: =IFERROR(INDEX(対訳マスタ!$C$2:$C$136,MATCH(Data!B1472,対訳マスタ!$B$2:$B$136,0)),Data!B1472) -> 手話能力 | C1472: =IF(Data!C1472="—","—",IFERROR(INDEX(対訳マスタ!$C$2:$C$136,MATCH(Data!C1472,対訳マスタ!$B$2:$B$136,0)),Data!C1472)) -> 産出 | D1472: =IF(Data!D1472="—","—",IFERROR(INDEX(対訳マスタ!$C$2:$C$136,MATCH(Data!D1472,対訳マスタ!$B$2:$B$136,0)),Data!D1472)) -> 言語能力 | E1472: =IFERROR(INDEX(対訳マスタ!$C$2:$C$136,MATCH(Data!E1472,対訳マスタ!$B$2:$B$136,0)),Data!E1472) -> 空間文法の正確さ | F1472: =Data!F1472 -> C2 | G1472: =Data!G1472 -> No descriptors available; see B2+ | H1472: — | I1472: —
A1473: =Data!A1473 -> 1472 | B1473: =IFERROR(INDEX(対訳マスタ!$C$2:$C$136,MATCH(Data!B1473,対訳マスタ!$B$2:$B$136,0)),Data!B1473) -> 手話能力 | C1473: =IF(Data!C1473="—","—",IFERROR(INDEX(対訳マスタ!$C$2:$C$136,MATCH(Data!C1473,対訳マスタ!$B$2:$B$136,0)),Data!C1473)) -> 産出 | D1473: =IF(Data!D1473="—","—",IFERROR(INDEX(対訳マスタ!$C$2:$C$136,MATCH(Data!D1473,対訳マスタ!$B$2:$B$136,0)),Data!D1473)) -> 言語能力 | E1473: =IFERROR(INDEX(対訳マスタ!$C$2:$C$136,MATCH(Data!E1473,対訳マスタ!$B$2:$B$136,0)),Data!E1473) -> 空間文法の正確さ | F1473: =Data!F1473 -> C1 | G1473: =Data!G1473 -> No descriptors available; see B2+ | H1473: — | I1473: —
A1474: =Data!A1474 -> 1473 | B1474: =IFERROR(INDEX(対訳マスタ!$C$2:$C$136,MATCH(Data!B1474,対訳マスタ!$B$2:$B$136,0)),Data!B1474) -> 手話能力 | C1474: =IF(Data!C1474="—","—",IFERROR(INDEX(対訳マスタ!$C$2:$C$136,MATCH(Data!C1474,対訳マスタ!$B$2:$B$136,0)),Data!C1474)) -> 産出 | D1474: =IF(Data!D1474="—","—",IFERROR(INDEX(対訳マスタ!$C$2:$C$136,MATCH(Data!D1474,対訳マスタ!$B$2:$B$136,0)),Data!D1474)) -> 言語能力 | E1474: =IFERROR(INDEX(対訳マスタ!$C$2:$C$136,MATCH(Data!E1474,対訳マスタ!$B$2:$B$136,0)),Data!E1474) -> 空間文法の正確さ | F1474: =Data!F1474 -> B2+ | G1474: =Data!G1474 -> Can situate the different contents/actions in the text sensibly in the signing space in order to structure the text. | I1474: 対象外
A1475: =Data!A1475 -> 1474 | B1475: =IFERROR(INDEX(対訳マスタ!$C$2:$C$136,MATCH(Data!B1475,対訳マスタ!$B$2:$B$136,0)),Data!B1475) -> 手話能力 | C1475: =IF(Data!C1475="—","—",IFERROR(INDEX(対訳マスタ!$C$2:$C$136,MATCH(Data!C1475,対訳マスタ!$B$2:$B$136,0)),Data!C1475)) -> 産出 | D1475: =IF(Data!D1475="—","—",IFERROR(INDEX(対訳マスタ!$C$2:$C$136,MATCH(Data!D1475,対訳マスタ!$B$2:$B$136,0)),Data!D1475)) -> 言語能力 | E1475: =IFERROR(INDEX(対訳マスタ!$C$2:$C$136,MATCH(Data!E1475,対訳マスタ!$B$2:$B$136,0)),Data!E1475) -> 空間文法の正確さ | F1475: =Data!F1475 -> B2+ | G1475: =Data!G1475 -> Can maintain full consistency in the reference using indexing, productive signs, in short texts. | I1475: 対象外
A1476: =Data!A1476 -> 1475 | B1476: =IFERROR(INDEX(対訳マスタ!$C$2:$C$136,MATCH(Data!B1476,対訳マスタ!$B$2:$B$136,0)),Data!B1476) -> 手話能力 | C1476: =IF(Data!C1476="—","—",IFERROR(INDEX(対訳マスタ!$C$2:$C$136,MATCH(Data!C1476,対訳マスタ!$B$2:$B$136,0)),Data!C1476)) -> 産出 | D1476: =IF(Data!D1476="—","—",IFERROR(INDEX(対訳マスタ!$C$2:$C$136,MATCH(Data!D1476,対訳マスタ!$B$2:$B$136,0)),Data!D1476)) -> 言語能力 | E1476: =IFERROR(INDEX(対訳マスタ!$C$2:$C$136,MATCH(Data!E1476,対訳マスタ!$B$2:$B$136,0)),Data!E1476) -> 空間文法の正確さ | F1476: =Data!F1476 -> B2 | G1476: =Data!G1476 -> Can use the signing space in a conscious manner, e.g. using the right side for <for> and the left side for <against> reasons. | I1476: 対象外
A1477: =Data!A1477 -> 1476 | B1477: =IFERROR(INDEX(対訳マスタ!$C$2:$C$136,MATCH(Data!B1477,対訳マスタ!$B$2:$B$136,0)),Data!B1477) -> 手話能力 | C1477: =IF(Data!C1477="—","—",IFERROR(INDEX(対訳マスタ!$C$2:$C$136,MATCH(Data!C1477,対訳マスタ!$B$2:$B$136,0)),Data!C1477)) -> 産出 | D1477: =IF(Data!D1477="—","—",IFERROR(INDEX(対訳マスタ!$C$2:$C$136,MATCH(Data!D1477,対訳マスタ!$B$2:$B$136,0)),Data!D1477)) -> 言語能力 | E1477: =IFERROR(INDEX(対訳マスタ!$C$2:$C$136,MATCH(Data!E1477,対訳マスタ!$B$2:$B$136,0)),Data!E1477) -> 空間文法の正確さ | F1477: =Data!F1477 -> B2 | G1477: =Data!G1477 -> Can use a large or a small signing space, dependent on the situation. | I1477: 対象外
A1478: =Data!A1478 -> 1477 | B1478: =IFERROR(INDEX(対訳マスタ!$C$2:$C$136,MATCH(Data!B1478,対訳マスタ!$B$2:$B$136,0)),Data!B1478) -> 手話能力 | C1478: =IF(Data!C1478="—","—",IFERROR(INDEX(対訳マスタ!$C$2:$C$136,MATCH(Data!C1478,対訳マスタ!$B$2:$B$136,0)),Data!C1478)) -> 産出 | D1478: =IF(Data!D1478="—","—",IFERROR(INDEX(対訳マスタ!$C$2:$C$136,MATCH(Data!D1478,対訳マスタ!$B$2:$B$136,0)),Data!D1478)) -> 言語能力 | E1478: =IFERROR(INDEX(対訳マスタ!$C$2:$C$136,MATCH(Data!E1478,対訳マスタ!$B$2:$B$136,0)),Data!E1478) -> 空間文法の正確さ | F1478: =Data!F1478 -> B2 | G1478: =Data!G1478 -> Can link productive signing with indicators of time (timelines). | I1478: 対象外
A1479: =Data!A1479 -> 1478 | B1479: =IFERROR(INDEX(対訳マスタ!$C$2:$C$136,MATCH(Data!B1479,対訳マスタ!$B$2:$B$136,0)),Data!B1479) -> 手話能力 | C1479: =IF(Data!C1479="—","—",IFERROR(INDEX(対訳マスタ!$C$2:$C$136,MATCH(Data!C1479,対訳マスタ!$B$2:$B$136,0)),Data!C1479)) -> 産出 | D1479: =IF(Data!D1479="—","—",IFERROR(INDEX(対訳マスタ!$C$2:$C$136,MATCH(Data!D1479,対訳マスタ!$B$2:$B$136,0)),Data!D1479)) -> 言語能力 | E1479: =IFERROR(INDEX(対訳マスタ!$C$2:$C$136,MATCH(Data!E1479,対訳マスタ!$B$2:$B$136,0)),Data!E1479) -> 空間文法の正確さ | F1479: =Data!F1479 -> B2 | G1479: =Data!G1479 -> Can employ appropriate timelines in order to indicate the point in time or the duration of an event (for temporal relations: simultaneously, beforehand/afterwards, after another). | I1479: 対象外
A1480: =Data!A1480 -> 1479 | B1480: =IFERROR(INDEX(対訳マスタ!$C$2:$C$136,MATCH(Data!B1480,対訳マスタ!$B$2:$B$136,0)),Data!B1480) -> 手話能力 | C1480: =IF(Data!C1480="—","—",IFERROR(INDEX(対訳マスタ!$C$2:$C$136,MATCH(Data!C1480,対訳マスタ!$B$2:$B$136,0)),Data!C1480)) -> 産出 | D1480: =IF(Data!D1480="—","—",IFERROR(INDEX(対訳マスタ!$C$2:$C$136,MATCH(Data!D1480,対訳マスタ!$B$2:$B$136,0)),Data!D1480)) -> 言語能力 | E1480: =IFERROR(INDEX(対訳マスタ!$C$2:$C$136,MATCH(Data!E1480,対訳マスタ!$B$2:$B$136,0)),Data!E1480) -> 空間文法の正確さ | F1480: =Data!F1480 -> B2 | G1480: =Data!G1480 -> Can express how one does something; <with X>; <without Y>. | I1480: 対象外
A1481: =Data!A1481 -> 1480 | B1481: =IFERROR(INDEX(対訳マスタ!$C$2:$C$136,MATCH(Data!B1481,対訳マスタ!$B$2:$B$136,0)),Data!B1481) -> 手話能力 | C1481: =IF(Data!C1481="—","—",IFERROR(INDEX(対訳マスタ!$C$2:$C$136,MATCH(Data!C1481,対訳マスタ!$B$2:$B$136,0)),Data!C1481)) -> 産出 | D1481: =IF(Data!D1481="—","—",IFERROR(INDEX(対訳マスタ!$C$2:$C$136,MATCH(Data!D1481,対訳マスタ!$B$2:$B$136,0)),Data!D1481)) -> 言語能力 | E1481: =IFERROR(INDEX(対訳マスタ!$C$2:$C$136,MATCH(Data!E1481,対訳マスタ!$B$2:$B$136,0)),Data!E1481) -> 空間文法の正確さ | F1481: =Data!F1481 -> B2 | G1481: =Data!G1481 -> Can express different temporal relationships (for example, three relationships: simultaneously; before and after; one after another). | I1481: 対象外
A1482: =Data!A1482 -> 1481 | B1482: =IFERROR(INDEX(対訳マスタ!$C$2:$C$136,MATCH(Data!B1482,対訳マスタ!$B$2:$B$136,0)),Data!B1482) -> 手話能力 | C1482: =IF(Data!C1482="—","—",IFERROR(INDEX(対訳マスタ!$C$2:$C$136,MATCH(Data!C1482,対訳マスタ!$B$2:$B$136,0)),Data!C1482)) -> 産出 | D1482: =IF(Data!D1482="—","—",IFERROR(INDEX(対訳マスタ!$C$2:$C$136,MATCH(Data!D1482,対訳マスタ!$B$2:$B$136,0)),Data!D1482)) -> 言語能力 | E1482: =IFERROR(INDEX(対訳マスタ!$C$2:$C$136,MATCH(Data!E1482,対訳マスタ!$B$2:$B$136,0)),Data!E1482) -> 空間文法の正確さ | F1482: =Data!F1482 -> B2 | G1482: =Data!G1482 -> Can employ upper body posture when indicating time reference, e.g. lean forward for future. | I1482: 対象外
A1483: =Data!A1483 -> 1482 | B1483: =IFERROR(INDEX(対訳マスタ!$C$2:$C$136,MATCH(Data!B1483,対訳マスタ!$B$2:$B$136,0)),Data!B1483) -> 手話能力 | C1483: =IF(Data!C1483="—","—",IFERROR(INDEX(対訳マスタ!$C$2:$C$136,MATCH(Data!C1483,対訳マスタ!$B$2:$B$136,0)),Data!C1483)) -> 産出 | D1483: =IF(Data!D1483="—","—",IFERROR(INDEX(対訳マスタ!$C$2:$C$136,MATCH(Data!D1483,対訳マスタ!$B$2:$B$136,0)),Data!D1483)) -> 言語能力 | E1483: =IFERROR(INDEX(対訳マスタ!$C$2:$C$136,MATCH(Data!E1483,対訳マスタ!$B$2:$B$136,0)),Data!E1483) -> 空間文法の正確さ | F1483: =Data!F1483 -> B2 | G1483: =Data!G1483 -> Can exploit an appropriate timeline in order to place past, present and future events in the correct relationship to each other. | I1483: 対象外
A1484: =Data!A1484 -> 1483 | B1484: =IFERROR(INDEX(対訳マスタ!$C$2:$C$136,MATCH(Data!B1484,対訳マスタ!$B$2:$B$136,0)),Data!B1484) -> 手話能力 | C1484: =IF(Data!C1484="—","—",IFERROR(INDEX(対訳マスタ!$C$2:$C$136,MATCH(Data!C1484,対訳マスタ!$B$2:$B$136,0)),Data!C1484)) -> 産出 | D1484: =IF(Data!D1484="—","—",IFERROR(INDEX(対訳マスタ!$C$2:$C$136,MATCH(Data!D1484,対訳マスタ!$B$2:$B$136,0)),Data!D1484)) -> 言語能力 | E1484: =IFERROR(INDEX(対訳マスタ!$C$2:$C$136,MATCH(Data!E1484,対訳マスタ!$B$2:$B$136,0)),Data!E1484) -> 空間文法の正確さ | F1484: =Data!F1484 -> B2 | G1484: =Data!G1484 -> Can exploit variation in the sign order of subject, verb, object in a sentence in order to highlight something (e.g. SVO, SOV, OSV). | I1484: 対象外
A1485: =Data!A1485 -> 1484 | B1485: =IFERROR(INDEX(対訳マスタ!$C$2:$C$136,MATCH(Data!B1485,対訳マスタ!$B$2:$B$136,0)),Data!B1485) -> 手話能力 | C1485: =IF(Data!C1485="—","—",IFERROR(INDEX(対訳マスタ!$C$2:$C$136,MATCH(Data!C1485,対訳マスタ!$B$2:$B$136,0)),Data!C1485)) -> 産出 | D1485: =IF(Data!D1485="—","—",IFERROR(INDEX(対訳マスタ!$C$2:$C$136,MATCH(Data!D1485,対訳マスタ!$B$2:$B$136,0)),Data!D1485)) -> 言語能力 | E1485: =IFERROR(INDEX(対訳マスタ!$C$2:$C$136,MATCH(Data!E1485,対訳マスタ!$B$2:$B$136,0)),Data!E1485) -> 空間文法の正確さ | F1485: =Data!F1485 -> B1+ | G1485: =Data!G1485 -> Can express rhetorical questions in an economical manner, e.g. using just the eyebrows. | I1485: 対象外
... A1540: =Data!A1540 -> 1539 | B1540: =IFERROR(INDEX(対訳マスタ!$C$2:$C$136,MATCH(Data!B1540,対訳マスタ!$B$2:$B$136,0)),Data!B1540) -> 手話能力 | C1540: =IF(Data!C1540="—","—",IFERROR(INDEX(対訳マスタ!$C$2:$C$136,MATCH(Data!C1540,対訳マスタ!$B$2:$B$136,0)),Data!C1540)) -> 受容 | D1540: =IF(Data!D1540="—","—",IFERROR(INDEX(対訳マスタ!$C$2:$C$136,MATCH(Data!D1540,対訳マスタ!$B$2:$B$136,0)),Data!D1540)) -> 社会言語能力 | E1540: =IFERROR(INDEX(対訳マスタ!$C$2:$C$136,MATCH(Data!E1540,対訳マスタ!$B$2:$B$136,0)),Data!E1540) -> 社会言語的適切さと文化レパートリー | F1540: =Data!F1540 -> A1 | G1540: =Data!G1540 -> Can maintain appropriate eye contact with a signer in a dialogue. | I1540: 対象外
A1541: =Data!A1541 -> 1540 | B1541: =IFERROR(INDEX(対訳マスタ!$C$2:$C$136,MATCH(Data!B1541,対訳マスタ!$B$2:$B$136,0)),Data!B1541) -> 手話能力 | C1541: =IF(Data!C1541="—","—",IFERROR(INDEX(対訳マスタ!$C$2:$C$136,MATCH(Data!C1541,対訳マスタ!$B$2:$B$136,0)),Data!C1541)) -> 産出 | D1541: =IF(Data!D1541="—","—",IFERROR(INDEX(対訳マスタ!$C$2:$C$136,MATCH(Data!D1541,対訳マスタ!$B$2:$B$136,0)),Data!D1541)) -> 社会言語能力 | E1541: =IFERROR(INDEX(対訳マスタ!$C$2:$C$136,MATCH(Data!E1541,対訳マスタ!$B$2:$B$136,0)),Data!E1541) -> 社会言語的適切さと文化レパートリー | F1541: =Data!F1541 -> C2 | G1541: =Data!G1541 -> No descriptors available; see C1 | H1541: — | I1541: —
A1542: =Data!A1542 -> 1541 | B1542: =IFERROR(INDEX(対訳マスタ!$C$2:$C$136,MATCH(Data!B1542,対訳マスタ!$B$2:$B$136,0)),Data!B1542) -> 手話能力 | C1542: =IF(Data!C1542="—","—",IFERROR(INDEX(対訳マスタ!$C$2:$C$136,MATCH(Data!C1542,対訳マスタ!$B$2:$B$136,0)),Data!C1542)) -> 産出 | D1542: =IF(Data!D1542="—","—",IFERROR(INDEX(対訳マスタ!$C$2:$C$136,MATCH(Data!D1542,対訳マスタ!$B$2:$B$136,0)),Data!D1542)) -> 社会言語能力 | E1542: =IFERROR(INDEX(対訳マスタ!$C$2:$C$136,MATCH(Data!E1542,対訳マスタ!$B$2:$B$136,0)),Data!E1542) -> 社会言語的適切さと文化レパートリー | F1542: =Data!F1542 -> C1 | G1542: =Data!G1542 -> Can respect sociocultural norms in producing texts (e.g. appropriate register, forms of politeness, status, taboos). | I1542: 対象外
A1543: =Data!A1543 -> 1542 | B1543: =IFERROR(INDEX(対訳マスタ!$C$2:$C$136,MATCH(Data!B1543,対訳マスタ!$B$2:$B$136,0)),Data!B1543) -> 手話能力 | C1543: =IF(Data!C1543="—","—",IFERROR(INDEX(対訳マスタ!$C$2:$C$136,MATCH(Data!C1543,対訳マスタ!$B$2:$B$136,0)),Data!C1543)) -> 産出 | D1543: =IF(Data!D1543="—","—",IFERROR(INDEX(対訳マスタ!$C$2:$C$136,MATCH(Data!D1543,対訳マスタ!$B$2:$B$136,0)),Data!D1543)) -> 社会言語能力 | E1543: =IFERROR(INDEX(対訳マスタ!$C$2:$C$136,MATCH(Data!E1543,対訳マスタ!$B$2:$B$136,0)),Data!E1543) -> 社会言語的適切さと文化レパートリー | F1543: =Data!F1543 -> C1 | G1543: =Data!G1543 -> Can adapt their register to the audience concerned. | I1543: 対象外
A1544: =Data!A1544 -> 1543 | B1544: =IFERROR(INDEX(対訳マスタ!$C$2:$C$136,MATCH(Data!B1544,対訳マスタ!$B$2:$B$136,0)),Data!B1544) -> 手話能力 | C1544: =IF(Data!C1544="—","—",IFERROR(INDEX(対訳マスタ!$C$2:$C$136,MATCH(Data!C1544,対訳マスタ!$B$2:$B$136,0)),Data!C1544)) -> 産出 | D1544: =IF(Data!D1544="—","—",IFERROR(INDEX(対訳マスタ!$C$2:$C$136,MATCH(Data!D1544,対訳マスタ!$B$2:$B$136,0)),Data!D1544)) -> 社会言語能力 | E1544: =IFERROR(INDEX(対訳マスタ!$C$2:$C$136,MATCH(Data!E1544,対訳マスタ!$B$2:$B$136,0)),Data!E1544) -> 社会言語的適切さと文化レパートリー | F1544: =Data!F1544 -> C1 | G1544: =Data!G1544 -> Can switch between formal and informal registers without effort. | I1544: 対象外
A1545: =Data!A1545 -> 1544 | B1545: =IFERROR(INDEX(対訳マスタ!$C$2:$C$136,MATCH(Data!B1545,対訳マスタ!$B$2:$B$136,0)),Data!B1545) -> 手話能力 | C1545: =IF(Data!C1545="—","—",IFERROR(INDEX(対訳マスタ!$C$2:$C$136,MATCH(Data!C1545,対訳マスタ!$B$2:$B$136,0)),Data!C1545)) -> 産出 | D1545: =IF(Data!D1545="—","—",IFERROR(INDEX(対訳マスタ!$C$2:$C$136,MATCH(Data!D1545,対訳マスタ!$B$2:$B$136,0)),Data!D1545)) -> 社会言語能力 | E1545: =IFERROR(INDEX(対訳マスタ!$C$2:$C$136,MATCH(Data!E1545,対訳マスタ!$B$2:$B$136,0)),Data!E1545) -> 社会言語的適切さと文化レパートリー | F1545: =Data!F1545 -> C1 | G1545: =Data!G1545 -> Can express non-lexical difference of register through both manual and non-manual means. | I1545: 対象外
A1546: =Data!A1546 -> 1545 | B1546: =IFERROR(INDEX(対訳マスタ!$C$2:$C$136,MATCH(Data!B1546,対訳マスタ!$B$2:$B$136,0)),Data!B1546) -> 手話能力 | C1546: =IF(Data!C1546="—","—",IFERROR(INDEX(対訳マスタ!$C$2:$C$136,MATCH(Data!C1546,対訳マスタ!$B$2:$B$136,0)),Data!C1546)) -> 産出 | D1546: =IF(Data!D1546="—","—",IFERROR(INDEX(対訳マスタ!$C$2:$C$136,MATCH(Data!D1546,対訳マスタ!$B$2:$B$136,0)),Data!D1546)) -> 社会言語能力 | E1546: =IFERROR(INDEX(対訳マスタ!$C$2:$C$136,MATCH(Data!E1546,対訳マスタ!$B$2:$B$136,0)),Data!E1546) -> 社会言語的適切さと文化レパートリー | F1546: =Data!F1546 -> C1 | G1546: =Data!G1546 -> Can tell a joke that relates to deaf experiences. | I1546: 対象外
A1547: =Data!A1547 -> 1546 | B1547: =IFERROR(INDEX(対訳マスタ!$C$2:$C$136,MATCH(Data!B1547,対訳マスタ!$B$2:$B$136,0)),Data!B1547) -> 手話能力 | C1547: =IF(Data!C1547="—","—",IFERROR(INDEX(対訳マスタ!$C$2:$C$136,MATCH(Data!C1547,対訳マスタ!$B$2:$B$136,0)),Data!C1547)) -> 産出 | D1547: =IF(Data!D1547="—","—",IFERROR(INDEX(対訳マスタ!$C$2:$C$136,MATCH(Data!D1547,対訳マスタ!$B$2:$B$136,0)),Data!D1547)) -> 社会言語能力 | E1547: =IFERROR(INDEX(対訳マスタ!$C$2:$C$136,MATCH(Data!E1547,対訳マスタ!$B$2:$B$136,0)),Data!E1547) -> 社会言語的適切さと文化レパートリー | F1547: =Data!F1547 -> B2+ | G1547: =Data!G1547 -> Can gauge whether the public concerned is familiar with deafness and can explain things explicitly if necessary. | I1547: 対象外
A1548: =Data!A1548 -> 1547 | B1548: =IFERROR(INDEX(対訳マスタ!$C$2:$C$136,MATCH(Data!B1548,対訳マスタ!$B$2:$B$136,0)),Data!B1548) -> 手話能力 | C1548: =IF(Data!C1548="—","—",IFERROR(INDEX(対訳マスタ!$C$2:$C$136,MATCH(Data!C1548,対訳マスタ!$B$2:$B$136,0)),Data!C1548)) -> 産出 | D1548: =IF(Data!D1548="—","—",IFERROR(INDEX(対訳マスタ!$C$2:$C$136,MATCH(Data!D1548,対訳マスタ!$B$2:$B$136,0)),Data!D1548)) -> 社会言語能力 | E1548: =IFERROR(INDEX(対訳マスタ!$C$2:$C$136,MATCH(Data!E1548,対訳マスタ!$B$2:$B$136,0)),Data!E1548) -> 社会言語的適切さと文化レパートリー | F1548: =Data!F1548 -> B2+ | G1548: =Data!G1548 -> Can produce lexicalised signs of different registers. | I1548: 対象外
A1549: =Data!A1549 -> 1548 | B1549: =IFERROR(INDEX(対訳マスタ!$C$2:$C$136,MATCH(Data!B1549,対訳マスタ!$B$2:$B$136,0)),Data!B1549) -> 手話能力 | C1549: =IF(Data!C1549="—","—",IFERROR(INDEX(対訳マスタ!$C$2:$C$136,MATCH(Data!C1549,対訳マスタ!$B$2:$B$136,0)),Data!C1549)) -> 産出 | D1549: =IF(Data!D1549="—","—",IFERROR(INDEX(対訳マスタ!$C$2:$C$136,MATCH(Data!D1549,対訳マスタ!$B$2:$B$136,0)),Data!D1549)) -> 社会言語能力 | E1549: =IFERROR(INDEX(対訳マスタ!$C$2:$C$136,MATCH(Data!E1549,対訳マスタ!$B$2:$B$136,0)),Data!E1549) -> 社会言語的適切さと文化レパートリー | F1549: =Data!F1549 -> B2+ | G1549: =Data!G1549 -> Can explain facts and events that are important in deaf communities. | I1549: 対象外
A1550: =Data!A1550 -> 1549 | B1550: =IFERROR(INDEX(対訳マスタ!$C$2:$C$136,MATCH(Data!B1550,対訳マスタ!$B$2:$B$136,0)),Data!B1550) -> 手話能力 | C1550: =IF(Data!C1550="—","—",IFERROR(INDEX(対訳マスタ!$C$2:$C$136,MATCH(Data!C1550,対訳マスタ!$B$2:$B$136,0)),Data!C1550)) -> 産出 | D1550: =IF(Data!D1550="—","—",IFERROR(INDEX(対訳マスタ!$C$2:$C$136,MATCH(Data!D1550,対訳マスタ!$B$2:$B$136,0)),Data!D1550)) -> 社会言語能力 | E1550: =IFERROR(INDEX(対訳マスタ!$C$2:$C$136,MATCH(Data!E1550,対訳マスタ!$B$2:$B$136,0)),Data!E1550) -> 社会言語的適切さと文化レパートリー | F1550: =Data!F1550 -> B2 | G1550: =Data!G1550 -> Can adopt the appropriate formal register in order to maintain distance from the reported issue. | I1550: 対象外
A1551: =Data!A1551 -> 1550 | B1551: =IFERROR(INDEX(対訳マスタ!$C$2:$C$136,MATCH(Data!B1551,対訳マスタ!$B$2:$B$136,0)),Data!B1551) -> 手話能力 | C1551: =IF(Data!C1551="—","—",IFERROR(INDEX(対訳マスタ!$C$2:$C$136,MATCH(Data!C1551,対訳マスタ!$B$2:$B$136,0)),Data!C1551)) -> 産出 | D1551: =IF(Data!D1551="—","—",IFERROR(INDEX(対訳マスタ!$C$2:$C$136,MATCH(Data!D1551,対訳マスタ!$B$2:$B$136,0)),Data!D1551)) -> 社会言語能力 | E1551: =IFERROR(INDEX(対訳マスタ!$C$2:$C$136,MATCH(Data!E1551,対訳マスタ!$B$2:$B$136,0)),Data!E1551) -> 社会言語的適切さと文化レパートリー | F1551: =Data!F1551 -> B2 | G1551: =Data!G1551 -> Can indicate someone’s social status through the articulation of signs in the signing space (e.g. use of a higher locus in signing space to indicate a higher status than the signer’s). | I1551: 対象外
A1552: =Data!A1552 -> 1551 | B1552: =IFERROR(INDEX(対訳マスタ!$C$2:$C$136,MATCH(Data!B1552,対訳マスタ!$B$2:$B$136,0)),Data!B1552) -> 手話能力 | C1552: =IF(Data!C1552="—","—",IFERROR(INDEX(対訳マスタ!$C$2:$C$136,MATCH(Data!C1552,対訳マスタ!$B$2:$B$136,0)),Data!C1552)) -> 産出 | D1552: =IF(Data!D1552="—","—",IFERROR(INDEX(対訳マスタ!$C$2:$C$136,MATCH(Data!D1552,対訳マスタ!$B$2:$B$136,0)),Data!D1552)) -> 社会言語能力 | E1552: =IFERROR(INDEX(対訳マスタ!$C$2:$C$136,MATCH(Data!E1552,対訳マスタ!$B$2:$B$136,0)),Data!E1552) -> 社会言語的適切さと文化レパートリー | F1552: =Data!F1552 -> B1+ | G1552: =Data!G1552 -> Can, as appropriate, engage in greeting/leave-taking remark, according to the type of text and the public concerned. | I1552: 対象外
A1553: =Data!A1553 -> 1552 | B1553: =IFERROR(INDEX(対訳マスタ!$C$2:$C$136,MATCH(Data!B1553,対訳マスタ!$B$2:$B$136,0)),Data!B1553) -> 手話能力 | C1553: =IF(Data!C1553="—","—",IFERROR(INDEX(対訳マスタ!$C$2:$C$136,MATCH(Data!C1553,対訳マスタ!$B$2:$B$136,0)),Data!C1553)) -> 産出 | D1553: =IF(Data!D1553="—","—",IFERROR(INDEX(対訳マスタ!$C$2:$C$136,MATCH(Data!D1553,対訳マスタ!$B$2:$B$136,0)),Data!D1553)) -> 社会言語能力 | E1553: =IFERROR(INDEX(対訳マスタ!$C$2:$C$136,MATCH(Data!E1553,対訳マスタ!$B$2:$B$136,0)),Data!E1553) -> 社会言語的適切さと文化レパートリー | F1553: =Data!F1553 -> B1+ | G1553: =Data!G1553 -> Can present themselves in a manner appropriate to the type of text and the public concerned (e.g. clothes, accessories, personal appearance).[1] | I1553: 対象外
... A1656: =Data!A1656 -> 1655 | B1656: =IFERROR(INDEX(対訳マスタ!$C$2:$C$136,MATCH(Data!B1656,対訳マスタ!$B$2:$B$136,0)),Data!B1656) -> 手話能力 | C1656: =IF(Data!C1656="—","—",IFERROR(INDEX(対訳マスタ!$C$2:$C$136,MATCH(Data!C1656,対訳マスタ!$B$2:$B$136,0)),Data!C1656)) -> 産出 | D1656: =IF(Data!D1656="—","—",IFERROR(INDEX(対訳マスタ!$C$2:$C$136,MATCH(Data!D1656,対訳マスタ!$B$2:$B$136,0)),Data!D1656)) -> 語用能力 | E1656: =IFERROR(INDEX(対訳マスタ!$C$2:$C$136,MATCH(Data!E1656,対訳マスタ!$B$2:$B$136,0)),Data!E1656) -> 手話テキストの構造 | F1656: =Data!F1656 -> A2 | G1656: =Data!G1656 -> Can, at the beginning of a text, give the details necessary to frame the description, providing answers to the key “what”, “where” and “who” questions. | I1656: 対象外
A1657: =Data!A1657 -> 1656 | B1657: =IFERROR(INDEX(対訳マスタ!$C$2:$C$136,MATCH(Data!B1657,対訳マスタ!$B$2:$B$136,0)),Data!B1657) -> 手話能力 | C1657: =IF(Data!C1657="—","—",IFERROR(INDEX(対訳マスタ!$C$2:$C$136,MATCH(Data!C1657,対訳マスタ!$B$2:$B$136,0)),Data!C1657)) -> 産出 | D1657: =IF(Data!D1657="—","—",IFERROR(INDEX(対訳マスタ!$C$2:$C$136,MATCH(Data!D1657,対訳マスタ!$B$2:$B$136,0)),Data!D1657)) -> 語用能力 | E1657: =IFERROR(INDEX(対訳マスタ!$C$2:$C$136,MATCH(Data!E1657,対訳マスタ!$B$2:$B$136,0)),Data!E1657) -> 手話テキストの構造 | F1657: =Data!F1657 -> A1 | G1657: =Data!G1657 -> No descriptors available | H1657: — | I1657: —
A1658: =Data!A1658 -> 1657 | B1658: =IFERROR(INDEX(対訳マスタ!$C$2:$C$136,MATCH(Data!B1658,対訳マスタ!$B$2:$B$136,0)),Data!B1658) -> 手話能力 | C1658: =IF(Data!C1658="—","—",IFERROR(INDEX(対訳マスタ!$C$2:$C$136,MATCH(Data!C1658,対訳マスタ!$B$2:$B$136,0)),Data!C1658)) -> 受容 | D1658: =IF(Data!D1658="—","—",IFERROR(INDEX(対訳マスタ!$C$2:$C$136,MATCH(Data!D1658,対訳マスタ!$B$2:$B$136,0)),Data!D1658)) -> 語用能力 | E1658: =IFERROR(INDEX(対訳マスタ!$C$2:$C$136,MATCH(Data!E1658,対訳マスタ!$B$2:$B$136,0)),Data!E1658) -> 場面設定と視点 | F1658: =Data!F1658 -> C2 | G1658: =Data!G1658 -> Can follow a constructed dialogue between several characters without difficulty even if the marking of role changes is reduced e.g., to the direction of vision. | I1658: 対象外
A1659: =Data!A1659 -> 1658 | B1659: =IFERROR(INDEX(対訳マスタ!$C$2:$C$136,MATCH(Data!B1659,対訳マスタ!$B$2:$B$136,0)),Data!B1659) -> 手話能力 | C1659: =IF(Data!C1659="—","—",IFERROR(INDEX(対訳マスタ!$C$2:$C$136,MATCH(Data!C1659,対訳マスタ!$B$2:$B$136,0)),Data!C1659)) -> 受容 | D1659: =IF(Data!D1659="—","—",IFERROR(INDEX(対訳マスタ!$C$2:$C$136,MATCH(Data!D1659,対訳マスタ!$B$2:$B$136,0)),Data!D1659)) -> 語用能力 | E1659: =IFERROR(INDEX(対訳マスタ!$C$2:$C$136,MATCH(Data!E1659,対訳マスタ!$B$2:$B$136,0)),Data!E1659) -> 場面設定と視点 | F1659: =Data!F1659 -> C2 | G1659: =Data!G1659 -> Can follow changes of scene, locations or persons during an action. | I1659: 対象外
A1660: =Data!A1660 -> 1659 | B1660: =IFERROR(INDEX(対訳マスタ!$C$2:$C$136,MATCH(Data!B1660,対訳マスタ!$B$2:$B$136,0)),Data!B1660) -> 手話能力 | C1660: =IF(Data!C1660="—","—",IFERROR(INDEX(対訳マスタ!$C$2:$C$136,MATCH(Data!C1660,対訳マスタ!$B$2:$B$136,0)),Data!C1660)) -> 受容 | D1660: =IF(Data!D1660="—","—",IFERROR(INDEX(対訳マスタ!$C$2:$C$136,MATCH(Data!D1660,対訳マスタ!$B$2:$B$136,0)),Data!D1660)) -> 語用能力 | E1660: =IFERROR(INDEX(対訳マスタ!$C$2:$C$136,MATCH(Data!E1660,対訳マスタ!$B$2:$B$136,0)),Data!E1660) -> 場面設定と視点 | F1660: =Data!F1660 -> C2 | G1660: =Data!G1660 -> Can easily follow several changes of perspective and role. | I1660: 対象外
A1661: =Data!A1661 -> 1660 | B1661: =IFERROR(INDEX(対訳マスタ!$C$2:$C$136,MATCH(Data!B1661,対訳マスタ!$B$2:$B$136,0)),Data!B1661) -> 手話能力 | C1661: =IF(Data!C1661="—","—",IFERROR(INDEX(対訳マスタ!$C$2:$C$136,MATCH(Data!C1661,対訳マスタ!$B$2:$B$136,0)),Data!C1661)) -> 受容 | D1661: =IF(Data!D1661="—","—",IFERROR(INDEX(対訳マスタ!$C$2:$C$136,MATCH(Data!D1661,対訳マスタ!$B$2:$B$136,0)),Data!D1661)) -> 語用能力 | E1661: =IFERROR(INDEX(対訳マスタ!$C$2:$C$136,MATCH(Data!E1661,対訳マスタ!$B$2:$B$136,0)),Data!E1661) -> 場面設定と視点 | F1661: =Data!F1661 -> C1 | G1661: =Data!G1661 -> Can memorise spatial settings established in signing space (e.g., landscape, family, situation) and follow references within the settings without difficulty. | I1661: 対象外
A1662: =Data!A1662 -> 1661 | B1662: =IFERROR(INDEX(対訳マスタ!$C$2:$C$136,MATCH(Data!B1662,対訳マスタ!$B$2:$B$136,0)),Data!B1662) -> 手話能力 | C1662: =IF(Data!C1662="—","—",IFERROR(INDEX(対訳マスタ!$C$2:$C$136,MATCH(Data!C1662,対訳マスタ!$B$2:$B$136,0)),Data!C1662)) -> 受容 | D1662: =IF(Data!D1662="—","—",IFERROR(INDEX(対訳マスタ!$C$2:$C$136,MATCH(Data!D1662,対訳マスタ!$B$2:$B$136,0)),Data!D1662)) -> 語用能力 | E1662: =IFERROR(INDEX(対訳マスタ!$C$2:$C$136,MATCH(Data!E1662,対訳マスタ!$B$2:$B$136,0)),Data!E1662) -> 場面設定と視点 | F1662: =Data!F1662 -> C1 | G1662: =Data!G1662 -> Can fully grasp a setting established in the signing space (e.g., landscape, family relations, situation), even if it is only indicated by depicting verbs. | I1662: 対象外
A1663: =Data!A1663 -> 1662 | B1663: =IFERROR(INDEX(対訳マスタ!$C$2:$C$136,MATCH(Data!B1663,対訳マスタ!$B$2:$B$136,0)),Data!B1663) -> 手話能力 | C1663: =IF(Data!C1663="—","—",IFERROR(INDEX(対訳マスタ!$C$2:$C$136,MATCH(Data!C1663,対訳マスタ!$B$2:$B$136,0)),Data!C1663)) -> 受容 | D1663: =IF(Data!D1663="—","—",IFERROR(INDEX(対訳マスタ!$C$2:$C$136,MATCH(Data!D1663,対訳マスタ!$B$2:$B$136,0)),Data!D1663)) -> 語用能力 | E1663: =IFERROR(INDEX(対訳マスタ!$C$2:$C$136,MATCH(Data!E1663,対訳マスタ!$B$2:$B$136,0)),Data!E1663) -> 場面設定と視点 | F1663: =Data!F1663 -> C1 | G1663: =Data!G1663 -> Can recognise when the signer is establishing a new scene for reference (a setting) in signing space. | I1663: 対象外
A1664: =Data!A1664 -> 1663 | B1664: =IFERROR(INDEX(対訳マスタ!$C$2:$C$136,MATCH(Data!B1664,対訳マスタ!$B$2:$B$136,0)),Data!B1664) -> 手話能力 | C1664: =IF(Data!C1664="—","—",IFERROR(INDEX(対訳マスタ!$C$2:$C$136,MATCH(Data!C1664,対訳マスタ!$B$2:$B$136,0)),Data!C1664)) -> 受容 | D1664: =IF(Data!D1664="—","—",IFERROR(INDEX(対訳マスタ!$C$2:$C$136,MATCH(Data!D1664,対訳マスタ!$B$2:$B$136,0)),Data!D1664)) -> 語用能力 | E1664: =IFERROR(INDEX(対訳マスタ!$C$2:$C$136,MATCH(Data!E1664,対訳マスタ!$B$2:$B$136,0)),Data!E1664) -> 場面設定と視点 | F1664: =Data!F1664 -> C1 | G1664: =Data!G1664 -> Can distinguish between various perspectives (observer/narrator), provided they are clearly marked. | I1664: 対象外
A1665: =Data!A1665 -> 1664 | B1665: =IFERROR(INDEX(対訳マスタ!$C$2:$C$136,MATCH(Data!B1665,対訳マスタ!$B$2:$B$136,0)),Data!B1665) -> 手話能力 | C1665: =IF(Data!C1665="—","—",IFERROR(INDEX(対訳マスタ!$C$2:$C$136,MATCH(Data!C1665,対訳マスタ!$B$2:$B$136,0)),Data!C1665)) -> 受容 | D1665: =IF(Data!D1665="—","—",IFERROR(INDEX(対訳マスタ!$C$2:$C$136,MATCH(Data!D1665,対訳マスタ!$B$2:$B$136,0)),Data!D1665)) -> 語用能力 | E1665: =IFERROR(INDEX(対訳マスタ!$C$2:$C$136,MATCH(Data!E1665,対訳マスタ!$B$2:$B$136,0)),Data!E1665) -> 場面設定と視点 | F1665: =Data!F1665 -> C1 | G1665: =Data!G1665 -> Can recognise what the signer says from their own perspective and what they say from another person’s perspective. | I1665: 対象外
A1666: =Data!A1666 -> 1665 | B1666: =IFERROR(INDEX(対訳マスタ!$C$2:$C$136,MATCH(Data!B1666,対訳マスタ!$B$2:$B$136,0)),Data!B1666) -> 手話能力 | C1666: =IF(Data!C1666="—","—",IFERROR(INDEX(対訳マスタ!$C$2:$C$136,MATCH(Data!C1666,対訳マスタ!$B$2:$B$136,0)),Data!C1666)) -> 受容 | D1666: =IF(Data!D1666="—","—",IFERROR(INDEX(対訳マスタ!$C$2:$C$136,MATCH(Data!D1666,対訳マスタ!$B$2:$B$136,0)),Data!D1666)) -> 語用能力 | E1666: =IFERROR(INDEX(対訳マスタ!$C$2:$C$136,MATCH(Data!E1666,対訳マスタ!$B$2:$B$136,0)),Data!E1666) -> 場面設定と視点 | F1666: =Data!F1666 -> C1 | G1666: =Data!G1666 -> Can, in their interpretation of the text, take account of the perspective of a participant in the action (e.g., that the character does not see everything). | I1666: 対象外
A1667: =Data!A1667 -> 1666 | B1667: =IFERROR(INDEX(対訳マスタ!$C$2:$C$136,MATCH(Data!B1667,対訳マスタ!$B$2:$B$136,0)),Data!B1667) -> 手話能力 | C1667: =IF(Data!C1667="—","—",IFERROR(INDEX(対訳マスタ!$C$2:$C$136,MATCH(Data!C1667,対訳マスタ!$B$2:$B$136,0)),Data!C1667)) -> 受容 | D1667: =IF(Data!D1667="—","—",IFERROR(INDEX(対訳マスタ!$C$2:$C$136,MATCH(Data!D1667,対訳マスタ!$B$2:$B$136,0)),Data!D1667)) -> 語用能力 | E1667: =IFERROR(INDEX(対訳マスタ!$C$2:$C$136,MATCH(Data!E1667,対訳マスタ!$B$2:$B$136,0)),Data!E1667) -> 場面設定と視点 | F1667: =Data!F1667 -> B2+ | G1667: =Data!G1667 -> Can understand a narrative with several characters when the changes of roles are clearly and slowly marked (e.g., by the position of the upper body and eye gaze). | I1667: 対象外
A1668: =Data!A1668 -> 1667 | B1668: =IFERROR(INDEX(対訳マスタ!$C$2:$C$136,MATCH(Data!B1668,対訳マスタ!$B$2:$B$136,0)),Data!B1668) -> 手話能力 | C1668: =IF(Data!C1668="—","—",IFERROR(INDEX(対訳マスタ!$C$2:$C$136,MATCH(Data!C1668,対訳マスタ!$B$2:$B$136,0)),Data!C1668)) -> 受容 | D1668: =IF(Data!D1668="—","—",IFERROR(INDEX(対訳マスタ!$C$2:$C$136,MATCH(Data!D1668,対訳マスタ!$B$2:$B$136,0)),Data!D1668)) -> 語用能力 | E1668: =IFERROR(INDEX(対訳マスタ!$C$2:$C$136,MATCH(Data!E1668,対訳マスタ!$B$2:$B$136,0)),Data!E1668) -> 場面設定と視点 | F1668: =Data!F1668 -> B2 | G1668: =Data!G1668 -> Can grasp the spatial references in signing space and use these for comprehension. | I1668: 対象外
A1669: =Data!A1669 -> 1668 | B1669: =IFERROR(INDEX(対訳マスタ!$C$2:$C$136,MATCH(Data!B1669,対訳マスタ!$B$2:$B$136,0)),Data!B1669) -> 手話能力 | C1669: =IF(Data!C1669="—","—",IFERROR(INDEX(対訳マスタ!$C$2:$C$136,MATCH(Data!C1669,対訳マスタ!$B$2:$B$136,0)),Data!C1669)) -> 受容 | D1669: =IF(Data!D1669="—","—",IFERROR(INDEX(対訳マスタ!$C$2:$C$136,MATCH(Data!D1669,対訳マスタ!$B$2:$B$136,0)),Data!D1669)) -> 語用能力 | E1669: =IFERROR(INDEX(対訳マスタ!$C$2:$C$136,MATCH(Data!E1669,対訳マスタ!$B$2:$B$136,0)),Data!E1669) -> 場面設定と視点 | F1669: =Data!F1669 -> B2 | G1669: =Data!G1669 -> Can recognise what the signer says themselves and what they say from the perspective of another person. | I1669: 対象外
... A1675: =Data!A1675 -> 1674 | B1675: =IFERROR(INDEX(対訳マスタ!$C$2:$C$136,MATCH(Data!B1675,対訳マスタ!$B$2:$B$136,0)),Data!B1675) -> 手話能力 | C1675: =IF(Data!C1675="—","—",IFERROR(INDEX(対訳マスタ!$C$2:$C$136,MATCH(Data!C1675,対訳マスタ!$B$2:$B$136,0)),Data!C1675)) -> 受容 | D1675: =IF(Data!D1675="—","—",IFERROR(INDEX(対訳マスタ!$C$2:$C$136,MATCH(Data!D1675,対訳マスタ!$B$2:$B$136,0)),Data!D1675)) -> 語用能力 | E1675: =IFERROR(INDEX(対訳マスタ!$C$2:$C$136,MATCH(Data!E1675,対訳マスタ!$B$2:$B$136,0)),Data!E1675) -> 場面設定と視点 | F1675: =Data!F1675 -> B1 | G1675: =Data!G1675 -> Can, by means of subsequent indexical references, once again identify objects and persons previously situated in the signing space. | I1675: 対象外
A1676: =Data!A1676 -> 1675 | B1676: =IFERROR(INDEX(対訳マスタ!$C$2:$C$136,MATCH(Data!B1676,対訳マスタ!$B$2:$B$136,0)),Data!B1676) -> 手話能力 | C1676: =IF(Data!C1676="—","—",IFERROR(INDEX(対訳マスタ!$C$2:$C$136,MATCH(Data!C1676,対訳マスタ!$B$2:$B$136,0)),Data!C1676)) -> 受容 | D1676: =IF(Data!D1676="—","—",IFERROR(INDEX(対訳マスタ!$C$2:$C$136,MATCH(Data!D1676,対訳マスタ!$B$2:$B$136,0)),Data!D1676)) -> 語用能力 | E1676: =IFERROR(INDEX(対訳マスタ!$C$2:$C$136,MATCH(Data!E1676,対訳マスタ!$B$2:$B$136,0)),Data!E1676) -> 場面設定と視点 | F1676: =Data!F1676 -> A2+ | G1676: =Data!G1676 -> No descriptors available | H1676: — | I1676: —
A1677: =Data!A1677 -> 1676 | B1677: =IFERROR(INDEX(対訳マスタ!$C$2:$C$136,MATCH(Data!B1677,対訳マスタ!$B$2:$B$136,0)),Data!B1677) -> 手話能力 | C1677: =IF(Data!C1677="—","—",IFERROR(INDEX(対訳マスタ!$C$2:$C$136,MATCH(Data!C1677,対訳マスタ!$B$2:$B$136,0)),Data!C1677)) -> 受容 | D1677: =IF(Data!D1677="—","—",IFERROR(INDEX(対訳マスタ!$C$2:$C$136,MATCH(Data!D1677,対訳マスタ!$B$2:$B$136,0)),Data!D1677)) -> 語用能力 | E1677: =IFERROR(INDEX(対訳マスタ!$C$2:$C$136,MATCH(Data!E1677,対訳マスタ!$B$2:$B$136,0)),Data!E1677) -> 場面設定と視点 | F1677: =Data!F1677 -> A2 | G1677: =Data!G1677 -> Can understand simple constructed action where the signer takes another person’s role. | I1677: 対象外
A1678: =Data!A1678 -> 1677 | B1678: =IFERROR(INDEX(対訳マスタ!$C$2:$C$136,MATCH(Data!B1678,対訳マスタ!$B$2:$B$136,0)),Data!B1678) -> 手話能力 | C1678: =IF(Data!C1678="—","—",IFERROR(INDEX(対訳マスタ!$C$2:$C$136,MATCH(Data!C1678,対訳マスタ!$B$2:$B$136,0)),Data!C1678)) -> 受容 | D1678: =IF(Data!D1678="—","—",IFERROR(INDEX(対訳マスタ!$C$2:$C$136,MATCH(Data!D1678,対訳マスタ!$B$2:$B$136,0)),Data!D1678)) -> 語用能力 | E1678: =IFERROR(INDEX(対訳マスタ!$C$2:$C$136,MATCH(Data!E1678,対訳マスタ!$B$2:$B$136,0)),Data!E1678) -> 場面設定と視点 | F1678: =Data!F1678 -> A1 | G1678: =Data!G1678 -> No descriptors available | H1678: — | I1678: —
A1679: =Data!A1679 -> 1678 | B1679: =IFERROR(INDEX(対訳マスタ!$C$2:$C$136,MATCH(Data!B1679,対訳マスタ!$B$2:$B$136,0)),Data!B1679) -> 手話能力 | C1679: =IF(Data!C1679="—","—",IFERROR(INDEX(対訳マスタ!$C$2:$C$136,MATCH(Data!C1679,対訳マスタ!$B$2:$B$136,0)),Data!C1679)) -> 産出 | D1679: =IF(Data!D1679="—","—",IFERROR(INDEX(対訳マスタ!$C$2:$C$136,MATCH(Data!D1679,対訳マスタ!$B$2:$B$136,0)),Data!D1679)) -> 語用能力 | E1679: =IFERROR(INDEX(対訳マスタ!$C$2:$C$136,MATCH(Data!E1679,対訳マスタ!$B$2:$B$136,0)),Data!E1679) -> 場面設定と視点 | F1679: =Data!F1679 -> C2 | G1679: =Data!G1679 -> Can present a complex action or event by playing different roles and adopting different perspectives. | I1679: 対象外
A1680: =Data!A1680 -> 1679 | B1680: =IFERROR(INDEX(対訳マスタ!$C$2:$C$136,MATCH(Data!B1680,対訳マスタ!$B$2:$B$136,0)),Data!B1680) -> 手話能力 | C1680: =IF(Data!C1680="—","—",IFERROR(INDEX(対訳マスタ!$C$2:$C$136,MATCH(Data!C1680,対訳マスタ!$B$2:$B$136,0)),Data!C1680)) -> 産出 | D1680: =IF(Data!D1680="—","—",IFERROR(INDEX(対訳マスタ!$C$2:$C$136,MATCH(Data!D1680,対訳マスタ!$B$2:$B$136,0)),Data!D1680)) -> 語用能力 | E1680: =IFERROR(INDEX(対訳マスタ!$C$2:$C$136,MATCH(Data!E1680,対訳マスタ!$B$2:$B$136,0)),Data!E1680) -> 場面設定と視点 | F1680: =Data!F1680 -> C1 | G1680: =Data!G1680 -> Can switch between different perspectives. | I1680: 対象外
A1681: =Data!A1681 -> 1680 | B1681: =IFERROR(INDEX(対訳マスタ!$C$2:$C$136,MATCH(Data!B1681,対訳マスタ!$B$2:$B$136,0)),Data!B1681) -> 手話能力 | C1681: =IF(Data!C1681="—","—",IFERROR(INDEX(対訳マスタ!$C$2:$C$136,MATCH(Data!C1681,対訳マスタ!$B$2:$B$136,0)),Data!C1681)) -> 産出 | D1681: =IF(Data!D1681="—","—",IFERROR(INDEX(対訳マスタ!$C$2:$C$136,MATCH(Data!D1681,対訳マスタ!$B$2:$B$136,0)),Data!D1681)) -> 語用能力 | E1681: =IFERROR(INDEX(対訳マスタ!$C$2:$C$136,MATCH(Data!E1681,対訳マスタ!$B$2:$B$136,0)),Data!E1681) -> 場面設定と視点 | F1681: =Data!F1681 -> C1 | G1681: =Data!G1681 -> Can create a complex 3-D image including objects in motion. | I1681: 対象外
A1682: =Data!A1682 -> 1681 | B1682: =IFERROR(INDEX(対訳マスタ!$C$2:$C$136,MATCH(Data!B1682,対訳マスタ!$B$2:$B$136,0)),Data!B1682) -> 手話能力 | C1682: =IF(Data!C1682="—","—",IFERROR(INDEX(対訳マスタ!$C$2:$C$136,MATCH(Data!C1682,対訳マスタ!$B$2:$B$136,0)),Data!C1682)) -> 産出 | D1682: =IF(Data!D1682="—","—",IFERROR(INDEX(対訳マスタ!$C$2:$C$136,MATCH(Data!D1682,対訳マスタ!$B$2:$B$136,0)),Data!D1682)) -> 語用能力 | E1682: =IFERROR(INDEX(対訳マスタ!$C$2:$C$136,MATCH(Data!E1682,対訳マスタ!$B$2:$B$136,0)),Data!E1682) -> 場面設定と視点 | F1682: =Data!F1682 -> B2+ | G1682: =Data!G1682 -> Can use the signing space correctly while presenting an interaction between more than two people (e.g. family dinner). | I1682: 対象外
A1683: =Data!A1683 -> 1682 | B1683: =IFERROR(INDEX(対訳マスタ!$C$2:$C$136,MATCH(Data!B1683,対訳マスタ!$B$2:$B$136,0)),Data!B1683) -> 手話能力 | C1683: =IF(Data!C1683="—","—",IFERROR(INDEX(対訳マスタ!$C$2:$C$136,MATCH(Data!C1683,対訳マスタ!$B$2:$B$136,0)),Data!C1683)) -> 産出 | D1683: =IF(Data!D1683="—","—",IFERROR(INDEX(対訳マスタ!$C$2:$C$136,MATCH(Data!D1683,対訳マスタ!$B$2:$B$136,0)),Data!D1683)) -> 語用能力 | E1683: =IFERROR(INDEX(対訳マスタ!$C$2:$C$136,MATCH(Data!E1683,対訳マスタ!$B$2:$B$136,0)),Data!E1683) -> 場面設定と視点 | F1683: =Data!F1683 -> B2+ | G1683: =Data!G1683 -> Can correctly introduce and effect a role shift. | I1683: 対象外
A1684: =Data!A1684 -> 1683 | B1684: =IFERROR(INDEX(対訳マスタ!$C$2:$C$136,MATCH(Data!B1684,対訳マスタ!$B$2:$B$136,0)),Data!B1684) -> 手話能力 | C1684: =IF(Data!C1684="—","—",IFERROR(INDEX(対訳マスタ!$C$2:$C$136,MATCH(Data!C1684,対訳マスタ!$B$2:$B$136,0)),Data!C1684)) -> 産出 | D1684: =IF(Data!D1684="—","—",IFERROR(INDEX(対訳マスタ!$C$2:$C$136,MATCH(Data!D1684,対訳マスタ!$B$2:$B$136,0)),Data!D1684)) -> 語用能力 | E1684: =IFERROR(INDEX(対訳マスタ!$C$2:$C$136,MATCH(Data!E1684,対訳マスタ!$B$2:$B$136,0)),Data!E1684) -> 場面設定と視点 | F1684: =Data!F1684 -> B2+ | G1684: =Data!G1684 -> Can present a simple action or event from the perspective of a participant. | I1684: 対象外
A1685: =Data!A1685 -> 1684 | B1685: =IFERROR(INDEX(対訳マスタ!$C$2:$C$136,MATCH(Data!B1685,対訳マスタ!$B$2:$B$136,0)),Data!B1685) -> 手話能力 | C1685: =IF(Data!C1685="—","—",IFERROR(INDEX(対訳マスタ!$C$2:$C$136,MATCH(Data!C1685,対訳マスタ!$B$2:$B$136,0)),Data!C1685)) -> 産出 | D1685: =IF(Data!D1685="—","—",IFERROR(INDEX(対訳マスタ!$C$2:$C$136,MATCH(Data!D1685,対訳マスタ!$B$2:$B$136,0)),Data!D1685)) -> 語用能力 | E1685: =IFERROR(INDEX(対訳マスタ!$C$2:$C$136,MATCH(Data!E1685,対訳マスタ!$B$2:$B$136,0)),Data!E1685) -> 場面設定と視点 | F1685: =Data!F1685 -> B2+ | G1685: =Data!G1685 -> Can present a simple action or event from the perspective of an observer/narrator. | I1685: 対象外
A1686: =Data!A1686 -> 1685 | B1686: =IFERROR(INDEX(対訳マスタ!$C$2:$C$136,MATCH(Data!B1686,対訳マスタ!$B$2:$B$136,0)),Data!B1686) -> 手話能力 | C1686: =IF(Data!C1686="—","—",IFERROR(INDEX(対訳マスタ!$C$2:$C$136,MATCH(Data!C1686,対訳マスタ!$B$2:$B$136,0)),Data!C1686)) -> 産出 | D1686: =IF(Data!D1686="—","—",IFERROR(INDEX(対訳マスタ!$C$2:$C$136,MATCH(Data!D1686,対訳マスタ!$B$2:$B$136,0)),Data!D1686)) -> 語用能力 | E1686: =IFERROR(INDEX(対訳マスタ!$C$2:$C$136,MATCH(Data!E1686,対訳マスタ!$B$2:$B$136,0)),Data!E1686) -> 場面設定と視点 | F1686: =Data!F1686 -> B2 | G1686: =Data!G1686 -> Can linguistically correctly construct a new setting when the text requires a new topic or situation to be addressed. | I1686: 対象外
